Workbook

Sheet Inputs
B2: Offshore discount | C2: 0.5
A4: x | B4: Role | C4: Total | D4: US count | E4: US salary | F4: Offshore count | G4: Offshore salary | H4: Hours per week | I4: Weighted average salary
B5: SSR | C5: =COUNTA(_xlfn.UNIQUE(SSRs!$A$2:$A$3338)) -> 188 | D5: =C5-F5 -> 188 | E5: 60000 | G5: =E5*$C$2 -> 30000 | H5: 40 | I5: =(E5*D5+G5*F5)/C5 -> 60000
B6: TM | C6: =COUNTA(_xlfn.UNIQUE(TMs!$A$2:$A$11972)) -> 139 | D6: =C6-F6 -> 139 | E6: 60000 | G6: =E6*$C$2 -> 30000 | H6: 40 | I6: =(E6*D6+G6*F6)/C6 -> 60000
B7: MTS Pod | C7: =COUNTA(_xlfn.UNIQUE('MTS Pod'!$A$2:$A$1481)) -> 73 | D7: =C7-F7 -> 57 | E7: 60000 | F7: {=COUNTA(_xlfn.UNIQUE(_xlfn._xlws.FILTER('MTS Pod'!$A$2:$A$1481,'MTS Pod'!$E$2:$E$1481="Pod_Ovs")))} -> 16 | G7: =E7*$C$2 -> 30000 | H7: 40 | I7: =(E7*D7+G7*F7)/C7 -> 53424.658
B8: R+R Pod | C8: =COUNTA(_xlfn.UNIQUE('RnR Pod'!$A$2:$A$961)) -> 48 | D8: =C8-F8 -> 43 | E8: 60000 | F8: {=COUNTA(_xlfn.UNIQUE(_xlfn._xlws.FILTER('RnR Pod'!$A$2:$A$961,'RnR Pod'!$F$2:$F$961="Pod_Ovs")))} -> 5 | G8: =E8*$C$2 -> 30000 | H8: 40 | I8: =(E8*D8+G8*F8)/C8 -> 56875
B9: Customer Care | C9: =SUM('Customer Service'!$V$13:$V$15) -> 51 | D9: =C9-F9 -> 21 | E9: 60000 | F9: ='Customer Service'!V15 -> 30 | G9: =E9*$C$2 -> 30000 | H9: 40 | I9: =(E9*D9+G9*F9)/C9 -> 42352.941
B10: Purchasing | C10: 50 | E10: 60000 | H10: 40
B11: Fin. Services | C11: 75 | E11: 60000 | H11: 40

Sheet Summary
B2: Role | C2: Total hours per week | D2: Hours saved per week (low-end) | E2: Hours saved per week (high-end) | F2: Efficiency impact on total hours (low-end) | G2: Efficiency impact on total hours (high-end) | H2: Baseline | I2: $ impact (low-end) | J2: $ impact (high-end) | K2: $ impact (average)
B3: SSR | C3: =_xlfn.XLOOKUP($B3,Inputs!$B$5:$B$9,Inputs!$H$5:$H$9) -> 40 | D3: =SUMIFS('Individual Initiative Impact'!M$4:M$95,'Individual Initiative Impact'!$B$4:$B$95,$B3) -> 9.8181818 | E3: =SUMIFS('Individual Initiative Impact'!N$4:N$95,'Individual Initiative Impact'!$B$4:$B$95,$B3) -> 17.545455 | F3: =D3/$C3 -> 0.24545455 | G3: =E3/$C3 -> 0.43863636 | H3: =Inputs!I5*Inputs!C5 -> 11280000 | I3: =SUMIFS('Individual Initiative Impact'!Q$4:Q$95,'Individual Initiative Impact'!$B$4:$B$95,$B3) -> 2768727.3 | J3: =SUMIFS('Individual Initiative Impact'!R$4:R$95,'Individual Initiative Impact'!$B$4:$B$95,$B3) -> 4947818.2 | K3: =AVERAGE(I3:J3) -> 3858272.7
B4: TM | C4: =_xlfn.XLOOKUP($B4,Inputs!$B$5:$B$9,Inputs!$H$5:$H$9) -> 40 | D4: =SUMIFS('Individual Initiative Impact'!M$4:M$95,'Individual Initiative Impact'!$B$4:$B$95,$B4) -> 15.237209 | E4: =SUMIFS('Individual Initiative Impact'!N$4:N$95,'Individual Initiative Impact'!$B$4:$B$95,$B4) -> 25.395349 | F4: =D4/$C4 -> 0.38093023 | G4: =E4/$C4 -> 0.63488372 | H4: =Inputs!I6*Inputs!C6 -> 8340000 | I4: =SUMIFS('Individual Initiative Impact'!Q$4:Q$95,'Individual Initiative Impact'!$B$4:$B$95,$B4) -> 3176958.1 | J4: =SUMIFS('Individual Initiative Impact'!R$4:R$95,'Individual Initiative Impact'!$B$4:$B$95,$B4) -> 5294930.2 | K4: =AVERAGE(I4:J4) -> 4235944.2
B5: MTS Pod | C5: =_xlfn.XLOOKUP($B5,Inputs!$B$5:$B$9,Inputs!$H$5:$H$9) -> 40 | D5: =SUMIFS('Individual Initiative Impact'!M$4:M$95,'Individual Initiative Impact'!$B$4:$B$95,$B5) -> 17.821782 | E5: =SUMIFS('Individual Initiative Impact'!N$4:N$95,'Individual Initiative Impact'!$B$4:$B$95,$B5) -> 25.108911 | F5: =D5/$C5 -> 0.44554455 | G5: =E5/$C5 -> 0.62772277 | H5: =Inputs!I7*Inputs!C7 -> 3900000 | I5: =SUMIFS('Individual Initiative Impact'!Q$4:Q$95,'Individual Initiative Impact'!$B$4:$B$95,$B5) -> 1737623.8 | J5: =SUMIFS('Individual Initiative Impact'!R$4:R$95,'Individual Initiative Impact'!$B$4:$B$95,$B5) -> 2448118.8 | K5: =AVERAGE(I5:J5) -> 2092871.3
B6: R+R Pod | C6: =_xlfn.XLOOKUP($B6,Inputs!$B$5:$B$9,Inputs!$H$5:$H$9) -> 40 | D6: =SUMIFS('Individual Initiative Impact'!M$4:M$95,'Individual Initiative Impact'!$B$4:$B$95,$B6) -> 11.612245 | E6: =SUMIFS('Individual Initiative Impact'!N$4:N$95,'Individual Initiative Impact'!$B$4:$B$95,$B6) -> 17.326531 | F6: =D6/$C6 -> 0.29030612 | G6: =E6/$C6 -> 0.43316327 | H6: =Inputs!I8*Inputs!C8 -> 2730000 | I6: =SUMIFS('Individual Initiative Impact'!Q$4:Q$95,'Individual Initiative Impact'!$B$4:$B$95,$B6) -> 792535.71 | J6: =SUMIFS('Individual Initiative Impact'!R$4:R$95,'Individual Initiative Impact'!$B$4:$B$95,$B6) -> 1182535.7 | K6: =AVERAGE(I6:J6) -> 987535.71
B7: Customer Care | C7: =_xlfn.XLOOKUP($B7,Inputs!$B$5:$B$9,Inputs!$H$5:$H$9) -> 40 | D7: =SUMIFS('Individual Initiative Impact'!M$4:M$95,'Individual Initiative Impact'!$B$4:$B$95,$B7) -> 13.380676 | E7: =SUMIFS('Individual Initiative Impact'!N$4:N$95,'Individual Initiative Impact'!$B$4:$B$95,$B7) -> 20.585655 | F7: =D7/$C7 -> 0.33451689 | G7: =E7/$C7 -> 0.51464138 | H7: =Inputs!I9*Inputs!C9 -> 2160000 | I7: =SUMIFS('Individual Initiative Impact'!Q$4:Q$95,'Individual Initiative Impact'!$B$4:$B$95,$B7) -> 722556.49 | J7: =SUMIFS('Individual Initiative Impact'!R$4:R$95,'Individual Initiative Impact'!$B$4:$B$95,$B7) -> 1111625.4 | K7: =AVERAGE(I7:J7) -> 917090.93
B9: Total | C9: =SUMPRODUCT(C3:C7,Inputs!$C$5:$C$9)/SUM(Inputs!$C$5:$C$9) -> 40 | D9: =SUMPRODUCT(D3:D7,Inputs!$C$5:$C$9)/SUM(Inputs!$C$5:$C$9) -> 13.035236 | E9: =SUMPRODUCT(E3:E7,Inputs!$C$5:$C$9)/SUM(Inputs!$C$5:$C$9) -> 21.128239 | F9: =D9/$C9 -> 0.32588089 | G9: =E9/$C9 -> 0.52820598 | H9: =SUM(H3:H7) -> 28410000 | I9: =SUM(I3:I7) -> 9198401.4 | J9: =SUM(J3:J7) -> 14985028 | K9: =SUM(K3:K7) -> 12091715

Sheet Individual Initiative Impact
B3: Role | C3: FTEs for ROLE | D3: Cost per year for ROLE | E3: Total hours per week for ROLE | F3: Archetype | G3: Category of opportunity | H3: Opportunity description | I3: Current time spent on activity category (%) | J3: Current time spent on activity archetype (hrs per week) | K3: Efficiency gained on activity archetype % (low-end) | L3: Efficiency gained on activity archetype % (high-end) | M3: Hours saved (low-end) | N3: Hours saved (high-end) | O3: Efficiency gained % on total workweek (low-end) | P3: Efficiency gained % on total workweek (high-end) | Q3: $ impact (low-end) | R3: $ impact (high-end)
B4: R+R Pod | C4: =_xlfn.XLOOKUP($B4,Inputs!$B$5:$B$9,Inputs!$C$5:$C$9) -> 48 | D4: =_xlfn.XLOOKUP($B4,Inputs!$B$5:$B$9,Inputs!I$5:I$9) -> 56875 | E4: =_xlfn.XLOOKUP($B4,Inputs!$B$5:$B$9,Inputs!H$5:H$9) -> 40 | F4: Communication & coordination | G4: Process | H4: Standardize and schedule reminder templates for vendor follow-ups (e.g., pending return authorization, missing info) | I4: {=_xlfn.IFNA(_xlfn.XLOOKUP(B4&F4,'Activity by Category'!$B$4:$B$99&'Activity by Category'!$C$4:$C$99,'Activity by Category'!$E$4:$E$99)/100,1)} -> 0.20408163 | J4: =I4*_xlfn.XLOOKUP($B4,Inputs!$B$5:$B$9,Inputs!$H$5:$H$9) -> 8.1632653 | K4: 0.04 | L4: 0.06 | M4: =$J4*K4 -> 0.32653061 | N4: =$J4*L4 -> 0.48979592 | O4: =M4/$E4 -> 0.0081632653 | P4: =N4/$E4 -> 0.012244898 | Q4: =O4*$C4*$D4 -> 22285.714 | R4: =P4*$C4*$D4 -> 33428.571
B5: Customer Care | C5: =_xlfn.XLOOKUP($B5,Inputs!$B$5:$B$9,Inputs!$C$5:$C$9) -> 51 | D5: =_xlfn.XLOOKUP($B5,Inputs!$B$5:$B$9,Inputs!I$5:I$9) -> 42352.941 | E5: =_xlfn.XLOOKUP($B5,Inputs!$B$5:$B$9,Inputs!H$5:H$9) -> 40 | F5: Issue resolution | G5: Automation | H5: Implement a Contact Center Co-Pilot that provides real-time, contextual guidance to agents for faster and more accurate issue resolution | I5: {=_xlfn.IFNA(_xlfn.XLOOKUP(B5&F5,'Activity by Category'!$B$4:$B$99&'Activity by Category'!$C$4:$C$99,'Activity by Category'!$E$4:$E$99)/100,1)} -> 0.85773563 | J5: =I5*_xlfn.XLOOKUP($B5,Inputs!$B$5:$B$9,Inputs!$H$5:$H$9) -> 34.309425 | K5: 0.2 | L5: 0.25 | M5: =$J5*K5 -> 6.861885 | N5: =$J5*L5 -> 8.5773563 | O5: =M5/$E5 -> 0.17154713 | P5: =N5/$E5 -> 0.21443391 | Q5: =O5*$C5*$D5 -> 370541.79 | R5: =P5*$C5*$D5 -> 463177.24
B6: R+R Pod | C6: =_xlfn.XLOOKUP($B6,Inputs!$B$5:$B$9,Inputs!$C$5:$C$9) -> 48 | D6: =_xlfn.XLOOKUP($B6,Inputs!$B$5:$B$9,Inputs!I$5:I$9) -> 56875 | E6: =_xlfn.XLOOKUP($B6,Inputs!$B$5:$B$9,Inputs!H$5:H$9) -> 40 | F6: Case management and processing | G6: Process | H6: Implement standardized intake checklist for new cases | I6: {=_xlfn.IFNA(_xlfn.XLOOKUP(B6&F6,'Activity by Category'!$B$4:$B$99&'Activity by Category'!$C$4:$C$99,'Activity by Category'!$E$4:$E$99)/100,1)} -> 0.66326531 | J6: =I6*_xlfn.XLOOKUP($B6,Inputs!$B$5:$B$9,Inputs!$H$5:$H$9) -> 26.530612 | K6: 0.04 | L6: 0.06 | M6: =$J6*K6 -> 1.0612245 | N6: =$J6*L6 -> 1.5918367 | O6: =M6/$E6 -> 0.026530612 | P6: =N6/$E6 -> 0.039795918 | Q6: =O6*$C6*$D6 -> 72428.571 | R6: =P6*$C6*$D6 -> 108642.86
B7: MTS Pod | C7: =_xlfn.XLOOKUP($B7,Inputs!$B$5:$B$9,Inputs!$C$5:$C$9) -> 73 | D7: =_xlfn.XLOOKUP($B7,Inputs!$B$5:$B$9,Inputs!I$5:I$9) -> 53424.658 | E7: =_xlfn.XLOOKUP($B7,Inputs!$B$5:$B$9,Inputs!H$5:H$9) -> 40 | F7: Shop creation | G7: Process | H7: Streamline QC and standardize review process to minimize rework | I7: {=_xlfn.IFNA(_xlfn.XLOOKUP(B7&F7,'Activity by Category'!$B$4:$B$99&'Activity by Category'!$C$4:$C$99,'Activity by Category'!$E$4:$E$99)/100,1)} -> 0.69306931 | J7: =I7*_xlfn.XLOOKUP($B7,Inputs!$B$5:$B$9,Inputs!$H$5:$H$9) -> 27.722772 | K7: 0.02 | L7: 0.03 | M7: =$J7*K7 -> 0.55445545 | N7: =$J7*L7 -> 0.83168317 | O7: =M7/$E7 -> 0.013861386 | P7: =N7/$E7 -> 0.020792079 | Q7: =O7*$C7*$D7 -> 54059.406 | R7: =P7*$C7*$D7 -> 81089.109
B8: R+R Pod | C8: =_xlfn.XLOOKUP($B8,Inputs!$B$5:$B$9,Inputs!$C$5:$C$9) -> 48 | D8: =_xlfn.XLOOKUP($B8,Inputs!$B$5:$B$9,Inputs!I$5:I$9) -> 56875 | E8: =_xlfn.XLOOKUP($B8,Inputs!$B$5:$B$9,Inputs!H$5:H$9) -> 40 | F8: Case management and processing | G8: Automation | H8: Provide self-serve channel for customers to initiate R+R | I8: {=_xlfn.IFNA(_xlfn.XLOOKUP(B8&F8,'Activity by Category'!$B$4:$B$99&'Activity by Category'!$C$4:$C$99,'Activity by Category'!$E$4:$E$99)/100,1)} -> 0.66326531 | J8: =I8*_xlfn.XLOOKUP($B8,Inputs!$B$5:$B$9,Inputs!$H$5:$H$9) -> 26.530612 | K8: 0.2 | L8: 0.3 | M8: =$J8*K8 -> 5.3061224 | N8: =$J8*L8 -> 7.9591837 | O8: =M8/$E8 -> 0.13265306 | P8: =N8/$E8 -> 0.19897959 | Q8: =O8*$C8*$D8 -> 362142.86 | R8: =P8*$C8*$D8 -> 543214.29
B9: TM | C9: =_xlfn.XLOOKUP($B9,Inputs!$B$5:$B$9,Inputs!$C$5:$C$9) -> 139 | D9: =_xlfn.XLOOKUP($B9,Inputs!$B$5:$B$9,Inputs!I$5:I$9) -> 60000 | E9: =_xlfn.XLOOKUP($B9,Inputs!$B$5:$B$9,Inputs!H$5:H$9) -> 40 | F9: Sales support activities | G9: Automation | H9: Deploy an AI Co-Pilot that instantly provides the right SKU and product details to speed up quoting and order creation | I9: {=_xlfn.IFNA(_xlfn.XLOOKUP(B9&F9,'Activity by Category'!$B$4:$B$99&'Activity by Category'!$C$4:$C$99,'Activity by Category'!$E$4:$E$99)/100,1)} -> 0.90697674 | J9: =I9*_xlfn.XLOOKUP($B9,Inputs!$B$5:$B$9,Inputs!$H$5:$H$9) -> 36.27907 | K9: 0.1 | L9: 0.15 | M9: =$J9*K9 -> 3.627907 | N9: =$J9*L9 -> 5.4418605 | O9: =M9/$E9 -> 0.090697674 | P9: =N9/$E9 -> 0.13604651 | Q9: =O9*$C9*$D9 -> 756418.6 | R9: =P9*$C9*$D9 -> 1134627.9
B10: MTS Pod | C10: =_xlfn.XLOOKUP($B10,Inputs!$B$5:$B$9,Inputs!$C$5:$C$9) -> 73 | D10: =_xlfn.XLOOKUP($B10,Inputs!$B$5:$B$9,Inputs!I$5:I$9) -> 53424.658 | E10: =_xlfn.XLOOKUP($B10,Inputs!$B$5:$B$9,Inputs!H$5:H$9) -> 40 | F10: Shop creation support activities | G10: Process | H10: Streamline MTS change requests processes | I10: {=_xlfn.IFNA(_xlfn.XLOOKUP(B10&F10,'Activity by Category'!$B$4:$B$99&'Activity by Category'!$C$4:$C$99,'Activity by Category'!$E$4:$E$99)/100,1)} -> 0.15841584 | J10: =I10*_xlfn.XLOOKUP($B10,Inputs!$B$5:$B$9,Inputs!$H$5:$H$9) -> 6.3366337 | K10: 0.1 | L10: 0.2 | M10: =$J10*K10 -> 0.63366337 | N10: =$J10*L10 -> 1.2673267 | O10: =M10/$E10 -> 0.015841584 | P10: =N10/$E10 -> 0.031683168 | Q10: =O10*$C10*$D10 -> 61782.178 | R10: =P10*$C10*$D10 -> 123564.36
B11: TM | C11: =_xlfn.XLOOKUP($B11,Inputs!$B$5:$B$9,Inputs!$C$5:$C$9) -> 139 | D11: =_xlfn.XLOOKUP($B11,Inputs!$B$5:$B$9,Inputs!I$5:I$9) -> 60000 | E11: =_xlfn.XLOOKUP($B11,Inputs!$B$5:$B$9,Inputs!H$5:H$9) -> 40 | F11: Sales support activities | G11: Automation | H11: Streamline cart and order creation with auto-fill for previous customer orders and costs | I11: {=_xlfn.IFNA(_xlfn.XLOOKUP(B11&F11,'Activity by Category'!$B$4:$B$99&'Activity by Category'!$C$4:$C$99,'Activity by Category'!$E$4:$E$99)/100,1)} -> 0.90697674 | J11: =I11*_xlfn.XLOOKUP($B11,Inputs!$B$5:$B$9,Inputs!$H$5:$H$9) -> 36.27907 | K11: 0.1 | L11: 0.15 | M11: =$J11*K11 -> 3.627907 | N11: =$J11*L11 -> 5.4418605 | O11: =M11/$E11 -> 0.090697674 | P11: =N11/$E11 -> 0.13604651 | Q11: =O11*$C11*$D11 -> 756418.6 | R11: =P11*$C11*$D11 -> 1134627.9
B12: SSR | C12: =_xlfn.XLOOKUP($B12,Inputs!$B$5:$B$9,Inputs!$C$5:$C$9) -> 188 | D12: =_xlfn.XLOOKUP($B12,Inputs!$B$5:$B$9,Inputs!I$5:I$9) -> 60000 | E12: =_xlfn.XLOOKUP($B12,Inputs!$B$5:$B$9,Inputs!H$5:H$9) -> 40 | F12: Order management | G12: Automation | H12: Use system integrations and dashboards to automate proactive order tracking and alerts - in progress | I12: {=_xlfn.IFNA(_xlfn.XLOOKUP(B12&F12,'Activity by Category'!$B$4:$B$99&'Activity by Category'!$C$4:$C$99,'Activity by Category'!$E$4:$E$99)/100,1)} -> 0.70454545 | J12: =I12*_xlfn.XLOOKUP($B12,Inputs!$B$5:$B$9,Inputs!$H$5:$H$9) -> 28.181818 | K12: 0.1 | L12: 0.15 | M12: =$J12*K12 -> 2.8181818 | N12: =$J12*L12 -> 4.2272727 | O12: =M12/$E12 -> 0.070454545 | P12: =N12/$E12 -> 0.10568182 | Q12: =O12*$C12*$D12 -> 794727.27 | R12: =P12*$C12*$D12 -> 1192090.9
B13: TM | C13: =_xlfn.XLOOKUP($B13,Inputs!$B$5:$B$9,Inputs!$C$5:$C$9) -> 139 | D13: =_xlfn.XLOOKUP($B13,Inputs!$B$5:$B$9,Inputs!I$5:I$9) -> 60000 | E13: =_xlfn.XLOOKUP($B13,Inputs!$B$5:$B$9,Inputs!H$5:H$9) -> 40 | F13: Sales support activities | G13: Process | H13: Clarify boundaries between TMs and SSRs for quoting vs. order setup | I13: {=_xlfn.IFNA(_xlfn.XLOOKUP(B13&F13,'Activity by Category'!$B$4:$B$99&'Activity by Category'!$C$4:$C$99,'Activity by Category'!$E$4:$E$99)/100,1)} -> 0.90697674 | J13: =I13*_xlfn.XLOOKUP($B13,Inputs!$B$5:$B$9,Inputs!$H$5:$H$9) -> 36.27907 | K13: 0.02 | L13: 0.03 | M13: =$J13*K13 -> 0.7255814 | N13: =$J13*L13 -> 1.0883721 | O13: =M13/$E13 -> 0.018139535 | P13: =N13/$E13 -> 0.027209302 | Q13: =O13*$C13*$D13 -> 151283.72 | R13: =P13*$C13*$D13 -> 226925.58
B14: SSR | C14: =_xlfn.XLOOKUP($B14,Inputs!$B$5:$B$9,Inputs!$C$5:$C$9) -> 188 | D14: =_xlfn.XLOOKUP($B14,Inputs!$B$5:$B$9,Inputs!I$5:I$9) -> 60000 | E14: =_xlfn.XLOOKUP($B14,Inputs!$B$5:$B$9,Inputs!H$5:H$9) -> 40 | F14: Order management | G14: Automation | H14: Auto-populate purchase order details using historical vendor data and enabling one-click PO duplication | I14: {=_xlfn.IFNA(_xlfn.XLOOKUP(B14&F14,'Activity by Category'!$B$4:$B$99&'Activity by Category'!$C$4:$C$99,'Activity by Category'!$E$4:$E$99)/100,1)} -> 0.70454545 | J14: =I14*_xlfn.XLOOKUP($B14,Inputs!$B$5:$B$9,Inputs!$H$5:$H$9) -> 28.181818 | K14: 0.1 | L14: 0.15 | M14: =$J14*K14 -> 2.8181818 | N14: =$J14*L14 -> 4.2272727 | O14: =M14/$E14 -> 0.070454545 | P14: =N14/$E14 -> 0.10568182 | Q14: =O14*$C14*$D14 -> 794727.27 | R14: =P14*$C14*$D14 -> 1192090.9
B15: R+R Pod | C15: =_xlfn.XLOOKUP($B15,Inputs!$B$5:$B$9,Inputs!$C$5:$C$9) -> 48 | D15: =_xlfn.XLOOKUP($B15,Inputs!$B$5:$B$9,Inputs!I$5:I$9) -> 56875 | E15: =_xlfn.XLOOKUP($B15,Inputs!$B$5:$B$9,Inputs!H$5:H$9) -> 40 | F15: Case management and processing | G15: Automation | H15: Auto-generate replacement orders (ZREP/RE), shipping labels, and freight pickup scheduling from case data | I15: {=_xlfn.IFNA(_xlfn.XLOOKUP(B15&F15,'Activity by Category'!$B$4:$B$99&'Activity by Category'!$C$4:$C$99,'Activity by Category'!$E$4:$E$99)/100,1)} -> 0.66326531 | J15: =I15*_xlfn.XLOOKUP($B15,Inputs!$B$5:$B$9,Inputs!$H$5:$H$9) -> 26.530612 | K15: 0.1 | L15: 0.15 | M15: =$J15*K15 -> 2.6530612 | N15: =$J15*L15 -> 3.9795918 | O15: =M15/$E15 -> 0.066326531 | P15: =N15/$E15 -> 0.099489796 | Q15: =O15*$C15*$D15 -> 181071.43 | R15: =P15*$C15*$D15 -> 271607.14
... B36: Customer Care | C36: =_xlfn.XLOOKUP($B36,Inputs!$B$5:$B$9,Inputs!$C$5:$C$9) -> 51 | D36: =_xlfn.XLOOKUP($B36,Inputs!$B$5:$B$9,Inputs!I$5:I$9) -> 42352.941 | E36: =_xlfn.XLOOKUP($B36,Inputs!$B$5:$B$9,Inputs!H$5:H$9) -> 40 | F36: Issue resolution | G36: Process | H36: Clarify ownership boundaries between Customer Care, SSRs, and R&R for order tracking and problem resolution | I36: {=_xlfn.IFNA(_xlfn.XLOOKUP(B36&F36,'Activity by Category'!$B$4:$B$99&'Activity by Category'!$C$4:$C$99,'Activity by Category'!$E$4:$E$99)/100,1)} -> 0.85773563 | J36: =I36*_xlfn.XLOOKUP($B36,Inputs!$B$5:$B$9,Inputs!$H$5:$H$9) -> 34.309425 | K36: 0.03 | L36: 0.05 | M36: =$J36*K36 -> 1.0292828 | N36: =$J36*L36 -> 1.7154713 | O36: =M36/$E36 -> 0.025732069 | P36: =N36/$E36 -> 0.042886781 | Q36: =O36*$C36*$D36 -> 55581.269 | R36: =P36*$C36*$D36 -> 92635.448

Sheet Temp (save)
B3: Order | C3: Role | D3: FTEs for ROLE | E3: Cost per year for ROLE | F3: Total hours per week for ROLE | G3: New archetype | H3: Category of opportunity | I3: Opportunity description | J3: Feasibility | K3: Feasibility label | L3: Description | M3: Current time spent on activity category (%) | N3: Current time spent on activity archetype (hrs per week) | O3: Efficiency gained on activity archetype % (low-end) | P3: Efficiency gained on activity archetype % (high-end) | Q3: Hours saved (low-end) | R3: Hours saved (high-end) | S3: Efficiency gained % on total workweek (low-end) | T3: Efficiency gained % on total workweek (high-end) | U3: $ impact (low-end) | V3: $ impact (high-end) | W3: Label
B4: 1 | C4: SSR | D4: =_xlfn.XLOOKUP($C4,Inputs!$B$5:$B$9,Inputs!C$5:C$9) -> 188 | E4: =_xlfn.XLOOKUP($C4,Inputs!$B$5:$B$9,Inputs!E$5:E$9) -> 60000 | F4: =_xlfn.XLOOKUP($C4,Inputs!$B$5:$B$9,Inputs!H$5:H$9) -> 40 | G4: Order management | H4: Automation | I4: Use system integrations and dashboards to automate proactive order tracking and alerts - in progress | J4: 2 – Medium | K4: 2 | L4: Already in progress; incremental development | M4: {=_xlfn.IFNA(_xlfn.XLOOKUP(C4&G4,'Activity by Category'!$B$4:$B$99&'Activity by Category'!$C$4:$C$99,'Activity by Category'!$E$4:$E$99)/100,1)} -> 0.70454545 | N4: =M4*_xlfn.XLOOKUP($C4,Inputs!$B$5:$B$9,Inputs!$H$5:$H$9) -> 28.181818 | O4: 0.1 | P4: 0.15 | Q4: =$N4*O4 -> 2.8181818 | R4: =$N4*P4 -> 4.2272727 | S4: =Q4/$F4 -> 0.070454545 | T4: =R4/$F4 -> 0.10568182 | U4: =S4*$D4*$E4 -> 794727.27 | V4: =T4*$D4*$E4 -> 1192090.9 | W4: 1
B5: 1 | C5: SSR | D5: =_xlfn.XLOOKUP($C5,Inputs!$B$5:$B$9,Inputs!C$5:C$9) -> 188 | E5: =_xlfn.XLOOKUP($C5,Inputs!$B$5:$B$9,Inputs!E$5:E$9) -> 60000 | F5: =_xlfn.XLOOKUP($C5,Inputs!$B$5:$B$9,Inputs!H$5:H$9) -> 40 | G5: Order management | H5: Automation | I5: Auto-populate purchase order details using historical vendor data and enabling one-click PO duplication | J5: 2 – Medium | K5: 2 | L5: Engage workflow logic update; moderate effort | M5: {=_xlfn.IFNA(_xlfn.XLOOKUP(C5&G5,'Activity by Category'!$B$4:$B$99&'Activity by Category'!$C$4:$C$99,'Activity by Category'!$E$4:$E$99)/100,1)} -> 0.70454545 | N5: =M5*_xlfn.XLOOKUP($C5,Inputs!$B$5:$B$9,Inputs!$H$5:$H$9) -> 28.181818 | O5: 0.1 | P5: 0.15 | Q5: =$N5*O5 -> 2.8181818 | R5: =$N5*P5 -> 4.2272727 | S5: =Q5/$F5 -> 0.070454545 | T5: =R5/$F5 -> 0.10568182 | U5: =S5*$D5*$E5 -> 794727.27 | V5: =T5*$D5*$E5 -> 1192090.9 | W5: 2
B6: 1 | C6: SSR | D6: =_xlfn.XLOOKUP($C6,Inputs!$B$5:$B$9,Inputs!C$5:C$9) -> 188 | E6: =_xlfn.XLOOKUP($C6,Inputs!$B$5:$B$9,Inputs!E$5:E$9) -> 60000 | F6: =_xlfn.XLOOKUP($C6,Inputs!$B$5:$B$9,Inputs!H$5:H$9) -> 40 | G6: Order management | H6: Automation | I6: Automatically detect and remove back-ordered or out-of-stock SKUs during order creation or extension | J6: 2 – Medium | K6: 2 | L6: System configuration and data rules; achievable but tech-involved | M6: {=_xlfn.IFNA(_xlfn.XLOOKUP(C6&G6,'Activity by Category'!$B$4:$B$99&'Activity by Category'!$C$4:$C$99,'Activity by Category'!$E$4:$E$99)/100,1)} -> 0.70454545 | N6: =M6*_xlfn.XLOOKUP($C6,Inputs!$B$5:$B$9,Inputs!$H$5:$H$9) -> 28.181818 | O6: 0.05 | P6: 0.1 | Q6: =$N6*O6 -> 1.4090909 | R6: =$N6*P6 -> 2.8181818 | S6: =Q6/$F6 -> 0.035227273 | T6: =R6/$F6 -> 0.070454545 | U6: =S6*$D6*$E6 -> 397363.64 | V6: =T6*$D6*$E6 -> 794727.27 | W6: 3
B7: 1 | C7: SSR | D7: =_xlfn.XLOOKUP($C7,Inputs!$B$5:$B$9,Inputs!C$5:C$9) -> 188 | E7: =_xlfn.XLOOKUP($C7,Inputs!$B$5:$B$9,Inputs!E$5:E$9) -> 60000 | F7: =_xlfn.XLOOKUP($C7,Inputs!$B$5:$B$9,Inputs!H$5:H$9) -> 40 | G7: Order management | H7: Process | I7: Create standardized communication templates for recurring inquiries (e.g., SAP order corrections, order status updates) | J7: 3 – High | K7: 3 | L7: Low tech dependency; clear process gain | M7: {=_xlfn.IFNA(_xlfn.XLOOKUP(C7&G7,'Activity by Category'!$B$4:$B$99&'Activity by Category'!$C$4:$C$99,'Activity by Category'!$E$4:$E$99)/100,1)} -> 0.70454545 | N7: =M7*_xlfn.XLOOKUP($C7,Inputs!$B$5:$B$9,Inputs!$H$5:$H$9) -> 28.181818 | O7: 0.02 | P7: 0.05 | Q7: =$N7*O7 -> 0.56363636 | R7: =$N7*P7 -> 1.4090909 | S7: =Q7/$F7 -> 0.014090909 | T7: =R7/$F7 -> 0.035227273 | U7: =S7*$D7*$E7 -> 158945.45 | V7: =T7*$D7*$E7 -> 397363.64 | W7: 4
B8: 1 | C8: SSR | D8: =_xlfn.XLOOKUP($C8,Inputs!$B$5:$B$9,Inputs!C$5:C$9) -> 188 | E8: =_xlfn.XLOOKUP($C8,Inputs!$B$5:$B$9,Inputs!E$5:E$9) -> 60000 | F8: =_xlfn.XLOOKUP($C8,Inputs!$B$5:$B$9,Inputs!H$5:H$9) -> 40 | G8: Issue resolution | H8: Automation | I8: Implement smart routing and exception handling to focus reps on complex cases | J8: 2 – Medium | K8: 2 | L8: Moderate Engage workflow logic required | M8: {=_xlfn.IFNA(_xlfn.XLOOKUP(C8&G8,'Activity by Category'!$B$4:$B$99&'Activity by Category'!$C$4:$C$99,'Activity by Category'!$E$4:$E$99)/100,1)} -> 0.17045455 | N8: =M8*_xlfn.XLOOKUP($C8,Inputs!$B$5:$B$9,Inputs!$H$5:$H$9) -> 6.8181818 | O8: 0.15 | P8: 0.2 | Q8: =$N8*O8 -> 1.0227273 | R8: =$N8*P8 -> 1.3636364 | S8: =Q8/$F8 -> 0.025568182 | T8: =R8/$F8 -> 0.034090909 | U8: =S8*$D8*$E8 -> 288409.09 | V8: =T8*$D8*$E8 -> 384545.45 | W8: 5
B9: 1 | C9: SSR | D9: =_xlfn.XLOOKUP($C9,Inputs!$B$5:$B$9,Inputs!C$5:C$9) -> 188 | E9: =_xlfn.XLOOKUP($C9,Inputs!$B$5:$B$9,Inputs!E$5:E$9) -> 60000 | F9: =_xlfn.XLOOKUP($C9,Inputs!$B$5:$B$9,Inputs!H$5:H$9) -> 40 | G9: Issue resolution | H9: Process | I9: Redesign post-order processes to reduce redundant communication loops and follow-ups | J9: 2 – Medium | K9: 2 | L9: Governance and coordination changes; achievable with clear SOPs | M9: {=_xlfn.IFNA(_xlfn.XLOOKUP(C9&G9,'Activity by Category'!$B$4:$B$99&'Activity by Category'!$C$4:$C$99,'Activity by Category'!$E$4:$E$99)/100,1)} -> 0.17045455 | N9: =M9*_xlfn.XLOOKUP($C9,Inputs!$B$5:$B$9,Inputs!$H$5:$H$9) -> 6.8181818 | O9: 0.05 | P9: 0.1 | Q9: =$N9*O9 -> 0.34090909 | R9: =$N9*P9 -> 0.68181818 | S9: =Q9/$F9 -> 0.0085227273 | T9: =R9/$F9 -> 0.017045455 | U9: =S9*$D9*$E9 -> 96136.364 | V9: =T9*$D9*$E9 -> 192272.73 | W9: 6
B10: 2 | C10: TM | D10: =_xlfn.XLOOKUP($C10,Inputs!$B$5:$B$9,Inputs!C$5:C$9) -> 139 | E10: =_xlfn.XLOOKUP($C10,Inputs!$B$5:$B$9,Inputs!E$5:E$9) -> 60000 | F10: =_xlfn.XLOOKUP($C10,Inputs!$B$5:$B$9,Inputs!H$5:H$9) -> 40 | G10: Sales support activities | H10: Automation | I10: Streamline cart and order creation with auto-fill for previous customer orders and costs | J10: 2 – Medium | K10: 2 | L10: System logic enhancement; dependent on CRM customization | M10: {=_xlfn.IFNA(_xlfn.XLOOKUP(C10&G10,'Activity by Category'!$B$4:$B$99&'Activity by Category'!$C$4:$C$99,'Activity by Category'!$E$4:$E$99)/100,1)} -> 0.90697674 | N10: =M10*_xlfn.XLOOKUP($C10,Inputs!$B$5:$B$9,Inputs!$H$5:$H$9) -> 36.27907 | O10: 0.1 | P10: 0.15 | Q10: =$N10*O10 -> 3.627907 | R10: =$N10*P10 -> 5.4418605 | S10: =Q10/$F10 -> 0.090697674 | T10: =R10/$F10 -> 0.13604651 | U10: =S10*$D10*$E10 -> 756418.6 | V10: =T10*$D10*$E10 -> 1134627.9 | W10: 7
B11: 2 | C11: TM | D11: =_xlfn.XLOOKUP($C11,Inputs!$B$5:$B$9,Inputs!C$5:C$9) -> 139 | E11: =_xlfn.XLOOKUP($C11,Inputs!$B$5:$B$9,Inputs!E$5:E$9) -> 60000 | F11: =_xlfn.XLOOKUP($C11,Inputs!$B$5:$B$9,Inputs!H$5:H$9) -> 40 | G11: Sales support activities | H11: Process | I11: Align data fields across CRM and Engage to eliminate re-entry | J11: 2 – Medium | K11: 2 | L11: Integration light lift but requires IT coordination | M11: {=_xlfn.IFNA(_xlfn.XLOOKUP(C11&G11,'Activity by Category'!$B$4:$B$99&'Activity by Category'!$C$4:$C$99,'Activity by Category'!$E$4:$E$99)/100,1)} -> 0.90697674 | N11: =M11*_xlfn.XLOOKUP($C11,Inputs!$B$5:$B$9,Inputs!$H$5:$H$9) -> 36.27907 | O11: 0.05 | P11: 0.1 | Q11: =$N11*O11 -> 1.8139535 | R11: =$N11*P11 -> 3.627907 | S11: =Q11/$F11 -> 0.045348837 | T11: =R11/$F11 -> 0.090697674 | U11: =S11*$D11*$E11 -> 378209.3 | V11: =T11*$D11*$E11 -> 756418.6 | W11: 8
B12: 2 | C12: TM | D12: =_xlfn.XLOOKUP($C12,Inputs!$B$5:$B$9,Inputs!C$5:C$9) -> 139 | E12: =_xlfn.XLOOKUP($C12,Inputs!$B$5:$B$9,Inputs!E$5:E$9) -> 60000 | F12: =_xlfn.XLOOKUP($C12,Inputs!$B$5:$B$9,Inputs!H$5:H$9) -> 40 | G12: Sales support activities | H12: Automation | I12: Auto-suggest products, bundles, or pricing tiers based on customer history, region, and performance data | J12: 1 – Low | K12: 1 | L12: Requires AI model training and CRM integration; high tech dependency | M12: {=_xlfn.IFNA(_xlfn.XLOOKUP(C12&G12,'Activity by Category'!$B$4:$B$99&'Activity by Category'!$C$4:$C$99,'Activity by Category'!$E$4:$E$99)/100,1)} -> 0.90697674 | N12: =M12*_xlfn.XLOOKUP($C12,Inputs!$B$5:$B$9,Inputs!$H$5:$H$9) -> 36.27907 | O12: 0.05 | P12: 0.1 | Q12: =$N12*O12 -> 1.8139535 | R12: =$N12*P12 -> 3.627907 | S12: =Q12/$F12 -> 0.045348837 | T12: =R12/$F12 -> 0.090697674 | U12: =S12*$D12*$E12 -> 378209.3 | V12: =T12*$D12*$E12 -> 756418.6 | W12: 9
B13: 2 | C13: TM | D13: =_xlfn.XLOOKUP($C13,Inputs!$B$5:$B$9,Inputs!C$5:C$9) -> 139 | E13: =_xlfn.XLOOKUP($C13,Inputs!$B$5:$B$9,Inputs!E$5:E$9) -> 60000 | F13: =_xlfn.XLOOKUP($C13,Inputs!$B$5:$B$9,Inputs!H$5:H$9) -> 40 | G13: Sales support activities | H13: Process | I13: Standardize quote-to-order workflow and templates to minimize manual input | J13: 3 – High | K13: 3 | L13: Simple process documentation; templates already partially exist | M13: {=_xlfn.IFNA(_xlfn.XLOOKUP(C13&G13,'Activity by Category'!$B$4:$B$99&'Activity by Category'!$C$4:$C$99,'Activity by Category'!$E$4:$E$99)/100,1)} -> 0.90697674 | N13: =M13*_xlfn.XLOOKUP($C13,Inputs!$B$5:$B$9,Inputs!$H$5:$H$9) -> 36.27907 | O13: 0.03 | P13: 0.05 | Q13: =$N13*O13 -> 1.0883721 | R13: =$N13*P13 -> 1.8139535 | S13: =Q13/$F13 -> 0.027209302 | T13: =R13/$F13 -> 0.045348837 | U13: =S13*$D13*$E13 -> 226925.58 | V13: =T13*$D13*$E13 -> 378209.3 | W13: 10
B14: 2 | C14: TM | D14: =_xlfn.XLOOKUP($C14,Inputs!$B$5:$B$9,Inputs!C$5:C$9) -> 139 | E14: =_xlfn.XLOOKUP($C14,Inputs!$B$5:$B$9,Inputs!E$5:E$9) -> 60000 | F14: =_xlfn.XLOOKUP($C14,Inputs!$B$5:$B$9,Inputs!H$5:H$9) -> 40 | G14: Sales support activities | H14: Process | I14: Clarify boundaries between TMs and SSRs for quoting vs. order setup | J14: 3 – High | K14: 3 | L14: Organizational clarification; no tech dependency | M14: {=_xlfn.IFNA(_xlfn.XLOOKUP(C14&G14,'Activity by Category'!$B$4:$B$99&'Activity by Category'!$C$4:$C$99,'Activity by Category'!$E$4:$E$99)/100,1)} -> 0.90697674 | N14: =M14*_xlfn.XLOOKUP($C14,Inputs!$B$5:$B$9,Inputs!$H$5:$H$9) -> 36.27907 | O14: 0.02 | P14: 0.03 | Q14: =$N14*O14 -> 0.7255814 | R14: =$N14*P14 -> 1.0883721 | S14: =Q14/$F14 -> 0.018139535 | T14: =R14/$F14 -> 0.027209302 | U14: =S14*$D14*$E14 -> 151283.72 | V14: =T14*$D14*$E14 -> 226925.58 | W14: 11
B15: 3 | C15: MTS Pod | D15: =_xlfn.XLOOKUP($C15,Inputs!$B$5:$B$9,Inputs!C$5:C$9) -> 73 | E15: =_xlfn.XLOOKUP($C15,Inputs!$B$5:$B$9,Inputs!E$5:E$9) -> 60000 | F15: =_xlfn.XLOOKUP($C15,Inputs!$B$5:$B$9,Inputs!H$5:H$9) -> 40 | G15: Shop creation | H15: Automation | I15: Develop ready-to-use shop templates by sport or season with pre-approved products, pricing, and images | J15: 3 – High | K15: 3 | L15: Low technical lift; preconfiguration and governance | M15: {=_xlfn.IFNA(_xlfn.XLOOKUP(C15&G15,'Activity by Category'!$B$4:$B$99&'Activity by Category'!$C$4:$C$99,'Activity by Category'!$E$4:$E$99)/100,1)} -> 0.69306931 | N15: =M15*_xlfn.XLOOKUP($C15,Inputs!$B$5:$B$9,Inputs!$H$5:$H$9) -> 27.722772 | O15: 0.3 | P15: 0.4 | Q15: =$N15*O15 -> 8.3168317 | R15: =$N15*P15 -> 11.089109 | S15: =Q15/$F15 -> 0.20792079 | T15: =R15/$F15 -> 0.27722772 | U15: =S15*$D15*$E15 -> 910693.07 | V15: =T15*$D15*$E15 -> 1214257.4 | W15: 12
... B32: 5 | C32: R+R Pod | D32: =_xlfn.XLOOKUP($C32,Inputs!$B$5:$B$9,Inputs!C$5:C$9) -> 48 | E32: =_xlfn.XLOOKUP($C32,Inputs!$B$5:$B$9,Inputs!E$5:E$9) -> 60000 | F32: =_xlfn.XLOOKUP($C32,Inputs!$B$5:$B$9,Inputs!H$5:H$9) -> 40 | G32: Communication & coordination | H32: Process | I32: Standardize and schedule reminder templates for vendor follow-ups (e.g., pending return authorization, missing info) | J32: 3 – High | K32: 3 | L32: Simple process documentation and SOP rollout; minimal tech dependency | M32: {=_xlfn.IFNA(_xlfn.XLOOKUP(C32&G32,'Activity by Category'!$B$4:$B$99&'Activity by Category'!$C$4:$C$99,'Activity by Category'!$E$4:$E$99)/100,1)} -> 0.20408163 | N32: =M32*_xlfn.XLOOKUP($C32,Inputs!$B$5:$B$9,Inputs!$H$5:$H$9) -> 8.1632653 | O32: 0.04 | P32: 0.06 | Q32: =$N32*O32 -> 0.32653061 | R32: =$N32*P32 -> 0.48979592 | S32: =Q32/$F32 -> 0.0081632653 | T32: =R32/$F32 -> 0.012244898 | U32: =S32*$D32*$E32 -> 23510.204 | V32: =T32*$D32*$E32 -> 35265.306 | W32: 29

Sheet Activity by Category
E2: 100
B3: Role | C3: Activity | D3: Median % of Time | E3: Scaled Median % of Time
B4: Customer Care | C4: Other activities | D4: =SUMIFS('Activity Mapping'!F$3:F$73,'Activity Mapping'!$E$3:$E$73,$B4,'Activity Mapping'!$H$3:$H$73,$C4) -> 12 | E4: =D4/SUMIFS($D$4:$D$30,$B$4:$B$30,B4)*$E$2 -> 14.226437
B5: Customer Care | C5: Issue resolution | D5: =SUMIFS('Activity Mapping'!F$3:F$73,'Activity Mapping'!$E$3:$E$73,$B5,'Activity Mapping'!$H$3:$H$73,$C5) -> 72.35 | E5: =D5/SUMIFS($D$4:$D$30,$B$4:$B$30,B5)*$E$2 -> 85.773563
B6: SSR | C6: Issue resolution | D6: =SUMIFS('Activity Mapping'!F$3:F$73,'Activity Mapping'!$E$3:$E$73,$B6,'Activity Mapping'!$H$3:$H$73,$C6) -> 15 | E6: =D6/SUMIFS($D$4:$D$30,$B$4:$B$30,B6)*$E$2 -> 17.045455
B7: SSR | C7: Order management | D7: =SUMIFS('Activity Mapping'!F$3:F$73,'Activity Mapping'!$E$3:$E$73,$B7,'Activity Mapping'!$H$3:$H$73,$C7) -> 62 | E7: =D7/SUMIFS($D$4:$D$30,$B$4:$B$30,B7)*$E$2 -> 70.454545
B8: SSR | C8: Other activities | D8: =SUMIFS('Activity Mapping'!F$3:F$73,'Activity Mapping'!$E$3:$E$73,$B8,'Activity Mapping'!$H$3:$H$73,$C8) -> 11 | E8: =D8/SUMIFS($D$4:$D$30,$B$4:$B$30,B8)*$E$2 -> 12.5
B9: TM | C9: Other activities | D9: =SUMIFS('Activity Mapping'!F$3:F$73,'Activity Mapping'!$E$3:$E$73,$B9,'Activity Mapping'!$H$3:$H$73,$C9) -> 8 | E9: =D9/SUMIFS($D$4:$D$30,$B$4:$B$30,B9)*$E$2 -> 9.3023256
B10: TM | C10: Sales support activities | D10: =SUMIFS('Activity Mapping'!F$3:F$73,'Activity Mapping'!$E$3:$E$73,$B10,'Activity Mapping'!$H$3:$H$73,$C10) -> 78 | E10: =D10/SUMIFS($D$4:$D$30,$B$4:$B$30,B10)*$E$2 -> 90.697674
B11: R+R Pod | C11: Case management and processing | D11: =SUMIFS('Activity Mapping'!F$3:F$73,'Activity Mapping'!$E$3:$E$73,$B11,'Activity Mapping'!$H$3:$H$73,$C11) -> 65 | E11: =D11/SUMIFS($D$4:$D$30,$B$4:$B$30,B11)*$E$2 -> 66.326531
B12: R+R Pod | C12: Communication & coordination | D12: =SUMIFS('Activity Mapping'!F$3:F$73,'Activity Mapping'!$E$3:$E$73,$B12,'Activity Mapping'!$H$3:$H$73,$C12) -> 20 | E12: =D12/SUMIFS($D$4:$D$30,$B$4:$B$30,B12)*$E$2 -> 20.408163
B13: R+R Pod | C13: Other activities | D13: =SUMIFS('Activity Mapping'!F$3:F$73,'Activity Mapping'!$E$3:$E$73,$B13,'Activity Mapping'!$H$3:$H$73,$C13) -> 13 | E13: =D13/SUMIFS($D$4:$D$30,$B$4:$B$30,B13)*$E$2 -> 13.265306
B14: MTS Pod | C14: Other activities | D14: =SUMIFS('Activity Mapping'!F$3:F$73,'Activity Mapping'!$E$3:$E$73,$B14,'Activity Mapping'!$H$3:$H$73,$C14) -> 15 | E14: =D14/SUMIFS($D$4:$D$30,$B$4:$B$30,B14)*$E$2 -> 14.851485
B15: MTS Pod | C15: Shop creation | D15: =SUMIFS('Activity Mapping'!F$3:F$73,'Activity Mapping'!$E$3:$E$73,$B15,'Activity Mapping'!$H$3:$H$73,$C15) -> 70 | E15: =D15/SUMIFS($D$4:$D$30,$B$4:$B$30,B15)*$E$2 -> 69.306931
B16: MTS Pod | C16: Shop creation support activities | D16: =SUMIFS('Activity Mapping'!F$3:F$73,'Activity Mapping'!$E$3:$E$73,$B16,'Activity Mapping'!$H$3:$H$73,$C16) -> 16 | E16: =D16/SUMIFS($D$4:$D$30,$B$4:$B$30,B16)*$E$2 -> 15.841584

Sheet Temp
A3: order | B3: Role | C3: FTEs for ROLE | D3: Cost per year for ROLE | E3: Total hours per week for ROLE | F3: Archetype | G3: Category of opportunity | H3: Opportunity description | I3: Current time spent on activity category (%) | J3: Current time spent on activity archetype (hrs per week) | K3: Efficiency gained on activity archetype % (low-end) | L3: Efficiency gained on activity archetype % (high-end) | M3: Hours saved (low-end) | N3: Hours saved (high-end) | O3: Efficiency gained % on total workweek (low-end) | P3: Efficiency gained % on total workweek (high-end) | Q3: $ impact (low-end) | R3: $ impact (high-end) | S3: rank | T3: Label
A4: 1 | B4: SSR | C4: =_xlfn.XLOOKUP($B4,Inputs!$B$5:$B$9,Inputs!$D$5:$D$9) -> 188 | D4: =_xlfn.XLOOKUP($B4,Inputs!$B$5:$B$9,Inputs!E$5:E$9) -> 60000 | E4: =_xlfn.XLOOKUP($B4,Inputs!$B$5:$B$9,Inputs!H$5:H$9) -> 40 | F4: Order management | G4: Automation | H4: Use system integrations and dashboards to automate proactive order tracking and alerts - in progress | I4: {=_xlfn.IFNA(_xlfn.XLOOKUP(B4&F4,'Activity by Category'!$B$4:$B$99&'Activity by Category'!$C$4:$C$99,'Activity by Category'!$E$4:$E$99)/100,1)} -> 0.70454545 | J4: =I4*_xlfn.XLOOKUP($B4,Inputs!$B$5:$B$9,Inputs!$H$5:$H$9) -> 28.181818 | K4: 0.1 | L4: 0.15 | M4: =$J4*K4 -> 2.8181818 | N4: =$J4*L4 -> 4.2272727 | O4: =M4/$E4 -> 0.070454545 | P4: =N4/$E4 -> 0.10568182 | Q4: =O4*$C4*$D4 -> 794727.27 | R4: =P4*$C4*$D4 -> 1192090.9 | S4: 1 | T4: BB
A5: 1 | B5: SSR | C5: =_xlfn.XLOOKUP($B5,Inputs!$B$5:$B$9,Inputs!$D$5:$D$9) -> 188 | D5: =_xlfn.XLOOKUP($B5,Inputs!$B$5:$B$9,Inputs!E$5:E$9) -> 60000 | E5: =_xlfn.XLOOKUP($B5,Inputs!$B$5:$B$9,Inputs!H$5:H$9) -> 40 | F5: Order management | G5: Automation | H5: Auto-populate purchase order details using historical vendor data and enabling one-click PO duplication | I5: {=_xlfn.IFNA(_xlfn.XLOOKUP(B5&F5,'Activity by Category'!$B$4:$B$99&'Activity by Category'!$C$4:$C$99,'Activity by Category'!$E$4:$E$99)/100,1)} -> 0.70454545 | J5: =I5*_xlfn.XLOOKUP($B5,Inputs!$B$5:$B$9,Inputs!$H$5:$H$9) -> 28.181818 | K5: 0.1 | L5: 0.15 | M5: =$J5*K5 -> 2.8181818 | N5: =$J5*L5 -> 4.2272727 | O5: =M5/$E5 -> 0.070454545 | P5: =N5/$E5 -> 0.10568182 | Q5: =O5*$C5*$D5 -> 794727.27 | R5: =P5*$C5*$D5 -> 1192090.9 | S5: 2 | T5: bb
A6: 2 | B6: TM | C6: =_xlfn.XLOOKUP($B6,Inputs!$B$5:$B$9,Inputs!$D$5:$D$9) -> 139 | D6: =_xlfn.XLOOKUP($B6,Inputs!$B$5:$B$9,Inputs!E$5:E$9) -> 60000 | E6: =_xlfn.XLOOKUP($B6,Inputs!$B$5:$B$9,Inputs!H$5:H$9) -> 40 | F6: Sales support activities | G6: Automation | H6: Streamline cart and order creation with auto-fill for previous customer orders and costs | I6: {=_xlfn.IFNA(_xlfn.XLOOKUP(B6&F6,'Activity by Category'!$B$4:$B$99&'Activity by Category'!$C$4:$C$99,'Activity by Category'!$E$4:$E$99)/100,1)} -> 0.90697674 | J6: =I6*_xlfn.XLOOKUP($B6,Inputs!$B$5:$B$9,Inputs!$H$5:$H$9) -> 36.27907 | K6: 0.1 | L6: 0.15 | M6: =$J6*K6 -> 3.627907 | N6: =$J6*L6 -> 5.4418605 | O6: =M6/$E6 -> 0.090697674 | P6: =N6/$E6 -> 0.13604651 | Q6: =O6*$C6*$D6 -> 756418.6 | R6: =P6*$C6*$D6 -> 1134627.9 | S6: 10 | T6: BB
A7: 2 | B7: TM | C7: =_xlfn.XLOOKUP($B7,Inputs!$B$5:$B$9,Inputs!$D$5:$D$9) -> 139 | D7: =_xlfn.XLOOKUP($B7,Inputs!$B$5:$B$9,Inputs!E$5:E$9) -> 60000 | E7: =_xlfn.XLOOKUP($B7,Inputs!$B$5:$B$9,Inputs!H$5:H$9) -> 40 | F7: Sales support activities | G7: Automation | H7: Deploy an AI Co-Pilot that instantly provides the right SKU and product details to speed up quoting and order creation | I7: {=_xlfn.IFNA(_xlfn.XLOOKUP(B7&F7,'Activity by Category'!$B$4:$B$99&'Activity by Category'!$C$4:$C$99,'Activity by Category'!$E$4:$E$99)/100,1)} -> 0.90697674 | J7: =I7*_xlfn.XLOOKUP($B7,Inputs!$B$5:$B$9,Inputs!$H$5:$H$9) -> 36.27907 | K7: 0.1 | L7: 0.15 | M7: =$J7*K7 -> 3.627907 | N7: =$J7*L7 -> 5.4418605 | O7: =M7/$E7 -> 0.090697674 | P7: =N7/$E7 -> 0.13604651 | Q7: =O7*$C7*$D7 -> 756418.6 | R7: =P7*$C7*$D7 -> 1134627.9 | S7: 9 | T7: bb
A8: 3 | B8: MTS Pod | C8: =_xlfn.XLOOKUP($B8,Inputs!$B$5:$B$9,Inputs!$D$5:$D$9) -> 57 | D8: =_xlfn.XLOOKUP($B8,Inputs!$B$5:$B$9,Inputs!E$5:E$9) -> 60000 | E8: =_xlfn.XLOOKUP($B8,Inputs!$B$5:$B$9,Inputs!H$5:H$9) -> 40 | F8: Shop creation | G8: Process | H8: Develop ready-to-use shop build templates by sport or season with pre-approved products, pricing, and images | I8: {=_xlfn.IFNA(_xlfn.XLOOKUP(B8&F8,'Activity by Category'!$B$4:$B$99&'Activity by Category'!$C$4:$C$99,'Activity by Category'!$E$4:$E$99)/100,1)} -> 0.69306931 | J8: =I8*_xlfn.XLOOKUP($B8,Inputs!$B$5:$B$9,Inputs!$H$5:$H$9) -> 27.722772 | K8: 0.3 | L8: 0.4 | M8: =$J8*K8 -> 8.3168317 | N8: =$J8*L8 -> 11.089109 | O8: =M8/$E8 -> 0.20792079 | P8: =N8/$E8 -> 0.27722772 | Q8: =O8*$C8*$D8 -> 711089.11 | R8: =P8*$C8*$D8 -> 948118.81 | S8: 16 | T8: BB
A9: 2 | B9: TM | C9: =_xlfn.XLOOKUP($B9,Inputs!$B$5:$B$9,Inputs!$D$5:$D$9) -> 139 | D9: =_xlfn.XLOOKUP($B9,Inputs!$B$5:$B$9,Inputs!E$5:E$9) -> 60000 | E9: =_xlfn.XLOOKUP($B9,Inputs!$B$5:$B$9,Inputs!H$5:H$9) -> 40 | F9: Sales support activities | G9: Automation | H9: Implement a conversational Co-Pilot that generates complete carts from customer requirements, removing the need for manual SKU selection and speeding up quote creation | I9: {=_xlfn.IFNA(_xlfn.XLOOKUP(B9&F9,'Activity by Category'!$B$4:$B$99&'Activity by Category'!$C$4:$C$99,'Activity by Category'!$E$4:$E$99)/100,1)} -> 0.90697674 | J9: =I9*_xlfn.XLOOKUP($B9,Inputs!$B$5:$B$9,Inputs!$H$5:$H$9) -> 36.27907 | K9: 0.07 | L9: 0.12 | M9: =$J9*K9 -> 2.5395349 | N9: =$J9*L9 -> 4.3534884 | O9: =M9/$E9 -> 0.063488372 | P9: =N9/$E9 -> 0.10883721 | Q9: =O9*$C9*$D9 -> 529493.02 | R9: =P9*$C9*$D9 -> 907702.33 | S9: 11 | T9: bb
A10: 1 | B10: SSR | C10: =_xlfn.XLOOKUP($B10,Inputs!$B$5:$B$9,Inputs!$D$5:$D$9) -> 188 | D10: =_xlfn.XLOOKUP($B10,Inputs!$B$5:$B$9,Inputs!E$5:E$9) -> 60000 | E10: =_xlfn.XLOOKUP($B10,Inputs!$B$5:$B$9,Inputs!H$5:H$9) -> 40 | F10: Order management | G10: Automation | H10: Automatically detect and remove back-ordered or out-of-stock SKUs during order creation or extension | I10: {=_xlfn.IFNA(_xlfn.XLOOKUP(B10&F10,'Activity by Category'!$B$4:$B$99&'Activity by Category'!$C$4:$C$99,'Activity by Category'!$E$4:$E$99)/100,1)} -> 0.70454545 | J10: =I10*_xlfn.XLOOKUP($B10,Inputs!$B$5:$B$9,Inputs!$H$5:$H$9) -> 28.181818 | K10: 0.05 | L10: 0.1 | M10: =$J10*K10 -> 1.4090909 | N10: =$J10*L10 -> 2.8181818 | O10: =M10/$E10 -> 0.035227273 | P10: =N10/$E10 -> 0.070454545 | Q10: =O10*$C10*$D10 -> 397363.64 | R10: =P10*$C10*$D10 -> 794727.27 | S10: 3 | T10: bb
A11: 2 | B11: TM | C11: =_xlfn.XLOOKUP($B11,Inputs!$B$5:$B$9,Inputs!$D$5:$D$9) -> 139 | D11: =_xlfn.XLOOKUP($B11,Inputs!$B$5:$B$9,Inputs!E$5:E$9) -> 60000 | E11: =_xlfn.XLOOKUP($B11,Inputs!$B$5:$B$9,Inputs!H$5:H$9) -> 40 | F11: Sales support activities | G11: Process | H11: Align data fields across CRM and Engage to eliminate re-entry | I11: {=_xlfn.IFNA(_xlfn.XLOOKUP(B11&F11,'Activity by Category'!$B$4:$B$99&'Activity by Category'!$C$4:$C$99,'Activity by Category'!$E$4:$E$99)/100,1)} -> 0.90697674 | J11: =I11*_xlfn.XLOOKUP($B11,Inputs!$B$5:$B$9,Inputs!$H$5:$H$9) -> 36.27907 | K11: 0.05 | L11: 0.1 | M11: =$J11*K11 -> 1.8139535 | N11: =$J11*L11 -> 3.627907 | O11: =M11/$E11 -> 0.045348837 | P11: =N11/$E11 -> 0.090697674 | Q11: =O11*$C11*$D11 -> 378209.3 | R11: =P11*$C11*$D11 -> 756418.6 | S11: 12 | T11: bb
A12: 2 | B12: TM | C12: =_xlfn.XLOOKUP($B12,Inputs!$B$5:$B$9,Inputs!$D$5:$D$9) -> 139 | D12: =_xlfn.XLOOKUP($B12,Inputs!$B$5:$B$9,Inputs!E$5:E$9) -> 60000 | E12: =_xlfn.XLOOKUP($B12,Inputs!$B$5:$B$9,Inputs!H$5:H$9) -> 40 | F12: Sales support activities | G12: Automation | H12: Auto-suggest products, bundles, or pricing tiers based on customer history, region, and performance data | I12: {=_xlfn.IFNA(_xlfn.XLOOKUP(B12&F12,'Activity by Category'!$B$4:$B$99&'Activity by Category'!$C$4:$C$99,'Activity by Category'!$E$4:$E$99)/100,1)} -> 0.90697674 | J12: =I12*_xlfn.XLOOKUP($B12,Inputs!$B$5:$B$9,Inputs!$H$5:$H$9) -> 36.27907 | K12: 0.05 | L12: 0.1 | M12: =$J12*K12 -> 1.8139535 | N12: =$J12*L12 -> 3.627907 | O12: =M12/$E12 -> 0.045348837 | P12: =N12/$E12 -> 0.090697674 | Q12: =O12*$C12*$D12 -> 378209.3 | R12: =P12*$C12*$D12 -> 756418.6 | S12: 13 | T12: bb
A13: 4 | B13: Customer Care | C13: =_xlfn.XLOOKUP($B13,Inputs!$B$5:$B$9,Inputs!$D$5:$D$9) -> 21 | D13: =_xlfn.XLOOKUP($B13,Inputs!$B$5:$B$9,Inputs!E$5:E$9) -> 60000 | E13: =_xlfn.XLOOKUP($B13,Inputs!$B$5:$B$9,Inputs!H$5:H$9) -> 40 | F13: Issue resolution | G13: Automation | H13: Implement a Contact Center Co-Pilot that provides real-time, contextual guidance to agents for faster and more accurate issue resolution | I13: {=_xlfn.IFNA(_xlfn.XLOOKUP(B13&F13,'Activity by Category'!$B$4:$B$99&'Activity by Category'!$C$4:$C$99,'Activity by Category'!$E$4:$E$99)/100,1)} -> 0.85773563 | J13: =I13*_xlfn.XLOOKUP($B13,Inputs!$B$5:$B$9,Inputs!$H$5:$H$9) -> 34.309425 | K13: 0.25 | L13: 0.35 | M13: =$J13*K13 -> 8.5773563 | N13: =$J13*L13 -> 12.008299 | O13: =M13/$E13 -> 0.21443391 | P13: =N13/$E13 -> 0.30020747 | Q13: =O13*$C13*$D13 -> 270186.72 | R13: =P13*$C13*$D13 -> 378261.41 | S13: 22 | T13: bb
A14: 3 | B14: MTS Pod | C14: =_xlfn.XLOOKUP($B14,Inputs!$B$5:$B$9,Inputs!$D$5:$D$9) -> 57 | D14: =_xlfn.XLOOKUP($B14,Inputs!$B$5:$B$9,Inputs!E$5:E$9) -> 60000 | E14: =_xlfn.XLOOKUP($B14,Inputs!$B$5:$B$9,Inputs!H$5:H$9) -> 40 | F14: Shop creation | G14: Process | H14: Reduce or eliminate unprofitable demo shop creations | I14: {=_xlfn.IFNA(_xlfn.XLOOKUP(B14&F14,'Activity by Category'!$B$4:$B$99&'Activity by Category'!$C$4:$C$99,'Activity by Category'!$E$4:$E$99)/100,1)} -> 0.69306931 | J14: =I14*_xlfn.XLOOKUP($B14,Inputs!$B$5:$B$9,Inputs!$H$5:$H$9) -> 27.722772 | K14: 0.2 | L14: 0.25 | M14: =$J14*K14 -> 5.5445545 | N14: =$J14*L14 -> 6.9306931 | O14: =M14/$E14 -> 0.13861386 | P14: =N14/$E14 -> 0.17326733 | Q14: =O14*$C14*$D14 -> 474059.41 | R14: =P14*$C14*$D14 -> 592574.26 | S14: 17 | T14: qw
A15: 5 | B15: R+R Pod | C15: =_xlfn.XLOOKUP($B15,Inputs!$B$5:$B$9,Inputs!$D$5:$D$9) -> 43 | D15: =_xlfn.XLOOKUP($B15,Inputs!$B$5:$B$9,Inputs!E$5:E$9) -> 60000 | E15: =_xlfn.XLOOKUP($B15,Inputs!$B$5:$B$9,Inputs!H$5:H$9) -> 40 | F15: Case management and processing | G15: Automation | H15: Provide self-serve channel for customers to initiate R+R | I15: {=_xlfn.IFNA(_xlfn.XLOOKUP(B15&F15,'Activity by Category'!$B$4:$B$99&'Activity by Category'!$C$4:$C$99,'Activity by Category'!$E$4:$E$99)/100,1)} -> 0.66326531 | J15: =I15*_xlfn.XLOOKUP($B15,Inputs!$B$5:$B$9,Inputs!$H$5:$H$9) -> 26.530612 | K15: 0.2 | L15: 0.3 | M15: =$J15*K15 -> 5.3061224 | N15: =$J15*L15 -> 7.9591837 | O15: =M15/$E15 -> 0.13265306 | P15: =N15/$E15 -> 0.19897959 | Q15: =O15*$C15*$D15 -> 342244.9 | R15: =P15*$C15*$D15 -> 513367.35 | S15: 28 | T15: qw
... A22: 4 | B22: Customer Care | C22: =_xlfn.XLOOKUP($B22,Inputs!$B$5:$B$9,Inputs!$D$5:$D$9) -> 21 | D22: =_xlfn.XLOOKUP($B22,Inputs!$B$5:$B$9,Inputs!E$5:E$9) -> 60000 | E22: =_xlfn.XLOOKUP($B22,Inputs!$B$5:$B$9,Inputs!H$5:H$9) -> 40 | F22: Issue resolution | G22: Process | H22: Clarify ownership boundaries between Customer Care, SSRs, and R&R for order tracking and problem resolution | I22: {=_xlfn.IFNA(_xlfn.XLOOKUP(B22&F22,'Activity by Category'!$B$4:$B$99&'Activity by Category'!$C$4:$C$99,'Activity by Category'!$E$4:$E$99)/100,1)} -> 0.85773563 | J22: =I22*_xlfn.XLOOKUP($B22,Inputs!$B$5:$B$9,Inputs!$H$5:$H$9) -> 34.309425 | K22: 0.03 | L22: 0.05 | M22: =$J22*K22 -> 1.0292828 | N22: =$J22*L22 -> 1.7154713 | O22: =M22/$E22 -> 0.025732069 | P22: =N22/$E22 -> 0.042886781 | Q22: =O22*$C22*$D22 -> 32422.407 | R22: =P22*$C22*$D22 -> 54037.344 | S22: 27 | T22: qw
A23: 1 | B23: SSR | C23: =_xlfn.XLOOKUP($B23,Inputs!$B$5:$B$9,Inputs!$D$5:$D$9) -> 188 | D23: =_xlfn.XLOOKUP($B23,Inputs!$B$5:$B$9,Inputs!E$5:E$9) -> 60000 | E23: =_xlfn.XLOOKUP($B23,Inputs!$B$5:$B$9,Inputs!H$5:H$9) -> 40 | F23: Order management | G23: Automation | H23: Implement a self-service channel that allows customers to submit core order change requests and routes them to an approve/reject workflow | I23: {=_xlfn.IFNA(_xlfn.XLOOKUP(B23&F23,'Activity by Category'!$B$4:$B$99&'Activity by Category'!$C$4:$C$99,'Activity by Category'!$E$4:$E$99)/100,1)} -> 0.70454545 | J23: =I23*_xlfn.XLOOKUP($B23,Inputs!$B$5:$B$9,Inputs!$H$5:$H$9) -> 28.181818 | K23: 0.02 | L23: 0.07 | M23: =$J23*K23 -> 0.56363636 | N23: =$J23*L23 -> 1.9727273 | O23: =M23/$E23 -> 0.014090909 | P23: =N23/$E23 -> 0.049318182 | Q23: =O23*$C23*$D23 -> 158945.45 | R23: =P23*$C23*$D23 -> 556309.09 | S23: 4
A24: 1 | B24: SSR | C24: =_xlfn.XLOOKUP($B24,Inputs!$B$5:$B$9,Inputs!$D$5:$D$9) -> 188 | D24: =_xlfn.XLOOKUP($B24,Inputs!$B$5:$B$9,Inputs!E$5:E$9) -> 60000 | E24: =_xlfn.XLOOKUP($B24,Inputs!$B$5:$B$9,Inputs!H$5:H$9) -> 40 | F24: Issue resolution | G24: Automation | H24: Implement smart routing and exception handling to focus reps on complex cases | I24: {=_xlfn.IFNA(_xlfn.XLOOKUP(B24&F24,'Activity by Category'!$B$4:$B$99&'Activity by Category'!$C$4:$C$99,'Activity by Category'!$E$4:$E$99)/100,1)} -> 0.17045455 | J24: =I24*_xlfn.XLOOKUP($B24,Inputs!$B$5:$B$9,Inputs!$H$5:$H$9) -> 6.8181818 | K24: 0.15 | L24: 0.2 | M24: =$J24*K24 -> 1.0227273 | N24: =$J24*L24 -> 1.3636364 | O24: =M24/$E24 -> 0.025568182 | P24: =N24/$E24 -> 0.034090909 | Q24: =O24*$C24*$D24 -> 288409.09 | R24: =P24*$C24*$D24 -> 384545.45 | S24: 6
A25: 2 | B25: TM | C25: =_xlfn.XLOOKUP($B25,Inputs!$B$5:$B$9,Inputs!$D$5:$D$9) -> 139 | D25: =_xlfn.XLOOKUP($B25,Inputs!$B$5:$B$9,Inputs!E$5:E$9) -> 60000 | E25: =_xlfn.XLOOKUP($B25,Inputs!$B$5:$B$9,Inputs!H$5:H$9) -> 40 | F25: Sales support activities | G25: Process | H25: Clarify boundaries between TMs and SSRs for quoting vs. order setup | I25: {=_xlfn.IFNA(_xlfn.XLOOKUP(B25&F25,'Activity by Category'!$B$4:$B$99&'Activity by Category'!$C$4:$C$99,'Activity by Category'!$E$4:$E$99)/100,1)} -> 0.90697674 | J25: =I25*_xlfn.XLOOKUP($B25,Inputs!$B$5:$B$9,Inputs!$H$5:$H$9) -> 36.27907 | K25: 0.02 | L25: 0.03 | M25: =$J25*K25 -> 0.7255814 | N25: =$J25*L25 -> 1.0883721 | O25: =M25/$E25 -> 0.018139535 | P25: =N25/$E25 -> 0.027209302 | Q25: =O25*$C25*$D25 -> 151283.72 | R25: =P25*$C25*$D25 -> 226925.58 | S25: 15
A26: 1 | B26: SSR | C26: =_xlfn.XLOOKUP($B26,Inputs!$B$5:$B$9,Inputs!$D$5:$D$9) -> 188 | D26: =_xlfn.XLOOKUP($B26,Inputs!$B$5:$B$9,Inputs!E$5:E$9) -> 60000 | E26: =_xlfn.XLOOKUP($B26,Inputs!$B$5:$B$9,Inputs!H$5:H$9) -> 40 | F26: Issue resolution | G26: Process | H26: Redesign post-order processes to reduce redundant communication loops and follow-ups | I26: {=_xlfn.IFNA(_xlfn.XLOOKUP(B26&F26,'Activity by Category'!$B$4:$B$99&'Activity by Category'!$C$4:$C$99,'Activity by Category'!$E$4:$E$99)/100,1)} -> 0.17045455 | J26: =I26*_xlfn.XLOOKUP($B26,Inputs!$B$5:$B$9,Inputs!$H$5:$H$9) -> 6.8181818 | K26: 0.05 | L26: 0.1 | M26: =$J26*K26 -> 0.34090909 | N26: =$J26*L26 -> 0.68181818 | O26: =M26/$E26 -> 0.0085227273 | P26: =N26/$E26 -> 0.017045455 | Q26: =O26*$C26*$D26 -> 96136.364 | R26: =P26*$C26*$D26 -> 192272.73 | S26: 8
A27: 3 | B27: MTS Pod | C27: =_xlfn.XLOOKUP($B27,Inputs!$B$5:$B$9,Inputs!$D$5:$D$9) -> 57 | D27: =_xlfn.XLOOKUP($B27,Inputs!$B$5:$B$9,Inputs!E$5:E$9) -> 60000 | E27: =_xlfn.XLOOKUP($B27,Inputs!$B$5:$B$9,Inputs!H$5:H$9) -> 40 | F27: Shop creation | G27: Automation | H27: Streamline artwork submissions and auto-route licensing submissions for approval | I27: {=_xlfn.IFNA(_xlfn.XLOOKUP(B27&F27,'Activity by Category'!$B$4:$B$99&'Activity by Category'!$C$4:$C$99,'Activity by Category'!$E$4:$E$99)/100,1)} -> 0.69306931 | J27: =I27*_xlfn.XLOOKUP($B27,Inputs!$B$5:$B$9,Inputs!$H$5:$H$9) -> 27.722772 | K27: 0.05 | L27: 0.08 | M27: =$J27*K27 -> 1.3861386 | N27: =$J27*L27 -> 2.2178218 | O27: =M27/$E27 -> 0.034653465 | P27: =N27/$E27 -> 0.055445545 | Q27: =O27*$C27*$D27 -> 118514.85 | R27: =P27*$C27*$D27 -> 189623.76 | S27: 19
A28: 5 | B28: R+R Pod | C28: =_xlfn.XLOOKUP($B28,Inputs!$B$5:$B$9,Inputs!$D$5:$D$9) -> 43 | D28: =_xlfn.XLOOKUP($B28,Inputs!$B$5:$B$9,Inputs!E$5:E$9) -> 60000 | E28: =_xlfn.XLOOKUP($B28,Inputs!$B$5:$B$9,Inputs!H$5:H$9) -> 40 | F28: Case management and processing | G28: Automation | H28: Digitally request and receive vendor return authorizations within Engage, removing email dependency | I28: {=_xlfn.IFNA(_xlfn.XLOOKUP(B28&F28,'Activity by Category'!$B$4:$B$99&'Activity by Category'!$C$4:$C$99,'Activity by Category'!$E$4:$E$99)/100,1)} -> 0.66326531 | J28: =I28*_xlfn.XLOOKUP($B28,Inputs!$B$5:$B$9,Inputs!$H$5:$H$9) -> 26.530612 | K28: 0.07 | L28: 0.1 | M28: =$J28*K28 -> 1.8571429 | N28: =$J28*L28 -> 2.6530612 | O28: =M28/$E28 -> 0.046428571 | P28: =N28/$E28 -> 0.066326531 | Q28: =O28*$C28*$D28 -> 119785.71 | R28: =P28*$C28*$D28 -> 171122.45 | S28: 30
A29: 4 | B29: Customer Care | C29: =_xlfn.XLOOKUP($B29,Inputs!$B$5:$B$9,Inputs!$D$5:$D$9) -> 21 | D29: =_xlfn.XLOOKUP($B29,Inputs!$B$5:$B$9,Inputs!E$5:E$9) -> 60000 | E29: =_xlfn.XLOOKUP($B29,Inputs!$B$5:$B$9,Inputs!H$5:H$9) -> 40 | F29: Issue resolution | G29: Automation | H29: Enable customers to resolve common issues with self-service chatbot | I29: {=_xlfn.IFNA(_xlfn.XLOOKUP(B29&F29,'Activity by Category'!$B$4:$B$99&'Activity by Category'!$C$4:$C$99,'Activity by Category'!$E$4:$E$99)/100,1)} -> 0.85773563 | J29: =I29*_xlfn.XLOOKUP($B29,Inputs!$B$5:$B$9,Inputs!$H$5:$H$9) -> 34.309425 | K29: 0.1 | L29: 0.15 | M29: =$J29*K29 -> 3.4309425 | N29: =$J29*L29 -> 5.1464138 | O29: =M29/$E29 -> 0.085773563 | P29: =N29/$E29 -> 0.12866034 | Q29: =O29*$C29*$D29 -> 108074.69 | R29: =P29*$C29*$D29 -> 162112.03 | S29: 23
A30: 3 | B30: MTS Pod | C30: =_xlfn.XLOOKUP($B30,Inputs!$B$5:$B$9,Inputs!$D$5:$D$9) -> 57 | D30: =_xlfn.XLOOKUP($B30,Inputs!$B$5:$B$9,Inputs!E$5:E$9) -> 60000 | E30: =_xlfn.XLOOKUP($B30,Inputs!$B$5:$B$9,Inputs!H$5:H$9) -> 40 | F30: Shop creation support activities | G30: Process | H30: Streamline MTS change requests processes | I30: {=_xlfn.IFNA(_xlfn.XLOOKUP(B30&F30,'Activity by Category'!$B$4:$B$99&'Activity by Category'!$C$4:$C$99,'Activity by Category'!$E$4:$E$99)/100,1)} -> 0.15841584 | J30: =I30*_xlfn.XLOOKUP($B30,Inputs!$B$5:$B$9,Inputs!$H$5:$H$9) -> 6.3366337 | K30: 0.1 | L30: 0.2 | M30: =$J30*K30 -> 0.63366337 | N30: =$J30*L30 -> 1.2673267 | O30: =M30/$E30 -> 0.015841584 | P30: =N30/$E30 -> 0.031683168 | Q30: =O30*$C30*$D30 -> 54178.218 | R30: =P30*$C30*$D30 -> 108356.44 | S30: 20
A31: 4 | B31: Customer Care | C31: =_xlfn.XLOOKUP($B31,Inputs!$B$5:$B$9,Inputs!$D$5:$D$9) -> 21 | D31: =_xlfn.XLOOKUP($B31,Inputs!$B$5:$B$9,Inputs!E$5:E$9) -> 60000 | E31: =_xlfn.XLOOKUP($B31,Inputs!$B$5:$B$9,Inputs!H$5:H$9) -> 40 | F31: Issue resolution | G31: Automation | H31: Utilize intelligent ticket routing to assign customer issues to the right queue or specialist | I31: {=_xlfn.IFNA(_xlfn.XLOOKUP(B31&F31,'Activity by Category'!$B$4:$B$99&'Activity by Category'!$C$4:$C$99,'Activity by Category'!$E$4:$E$99)/100,1)} -> 0.85773563 | J31: =I31*_xlfn.XLOOKUP($B31,Inputs!$B$5:$B$9,Inputs!$H$5:$H$9) -> 34.309425 | K31: 0.05 | L31: 0.1 | M31: =$J31*K31 -> 1.7154713 | N31: =$J31*L31 -> 3.4309425 | O31: =M31/$E31 -> 0.042886781 | P31: =N31/$E31 -> 0.085773563 | Q31: =O31*$C31*$D31 -> 54037.344 | R31: =P31*$C31*$D31 -> 108074.69 | S31: 24
A32: 4 | B32: Customer Care | C32: =_xlfn.XLOOKUP($B32,Inputs!$B$5:$B$9,Inputs!$D$5:$D$9) -> 21 | D32: =_xlfn.XLOOKUP($B32,Inputs!$B$5:$B$9,Inputs!E$5:E$9) -> 60000 | E32: =_xlfn.XLOOKUP($B32,Inputs!$B$5:$B$9,Inputs!H$5:H$9) -> 40 | F32: Issue resolution | G32: Automation | H32: Streamline ticket generation follow-ups and other post-call activities | I32: {=_xlfn.IFNA(_xlfn.XLOOKUP(B32&F32,'Activity by Category'!$B$4:$B$99&'Activity by Category'!$C$4:$C$99,'Activity by Category'!$E$4:$E$99)/100,1)} -> 0.85773563 | J32: =I32*_xlfn.XLOOKUP($B32,Inputs!$B$5:$B$9,Inputs!$H$5:$H$9) -> 34.309425 | K32: 0.05 | L32: 0.1 | M32: =$J32*K32 -> 1.7154713 | N32: =$J32*L32 -> 3.4309425 | O32: =M32/$E32 -> 0.042886781 | P32: =N32/$E32 -> 0.085773563 | Q32: =O32*$C32*$D32 -> 54037.344 | R32: =P32*$C32*$D32 -> 108074.69 | S32: 25
A33: 5 | B33: R+R Pod | C33: =_xlfn.XLOOKUP($B33,Inputs!$B$5:$B$9,Inputs!$D$5:$D$9) -> 43 | D33: =_xlfn.XLOOKUP($B33,Inputs!$B$5:$B$9,Inputs!E$5:E$9) -> 60000 | E33: =_xlfn.XLOOKUP($B33,Inputs!$B$5:$B$9,Inputs!H$5:H$9) -> 40 | F33: Case management and processing | G33: Process | H33: Implement standardized intake checklist for new cases | I33: {=_xlfn.IFNA(_xlfn.XLOOKUP(B33&F33,'Activity by Category'!$B$4:$B$99&'Activity by Category'!$C$4:$C$99,'Activity by Category'!$E$4:$E$99)/100,1)} -> 0.66326531 | J33: =I33*_xlfn.XLOOKUP($B33,Inputs!$B$5:$B$9,Inputs!$H$5:$H$9) -> 26.530612 | K33: 0.04 | L33: 0.06 | M33: =$J33*K33 -> 1.0612245 | N33: =$J33*L33 -> 1.5918367 | O33: =M33/$E33 -> 0.026530612 | P33: =N33/$E33 -> 0.039795918 | Q33: =O33*$C33*$D33 -> 68448.98 | R33: =P33*$C33*$D33 -> 102673.47 | S33: 31
A34: 3 | B34: MTS Pod | C34: =_xlfn.XLOOKUP($B34,Inputs!$B$5:$B$9,Inputs!$D$5:$D$9) -> 57 | D34: =_xlfn.XLOOKUP($B34,Inputs!$B$5:$B$9,Inputs!E$5:E$9) -> 60000 | E34: =_xlfn.XLOOKUP($B34,Inputs!$B$5:$B$9,Inputs!H$5:H$9) -> 40 | F34: Shop creation | G34: Process | H34: Streamline QC and standardize review process to minimize rework | I34: {=_xlfn.IFNA(_xlfn.XLOOKUP(B34&F34,'Activity by Category'!$B$4:$B$99&'Activity by Category'!$C$4:$C$99,'Activity by Category'!$E$4:$E$99)/100,1)} -> 0.69306931 | J34: =I34*_xlfn.XLOOKUP($B34,Inputs!$B$5:$B$9,Inputs!$H$5:$H$9) -> 27.722772 | K34: 0.02 | L34: 0.03 | M34: =$J34*K34 -> 0.55445545 | N34: =$J34*L34 -> 0.83168317 | O34: =M34/$E34 -> 0.013861386 | P34: =N34/$E34 -> 0.020792079 | Q34: =O34*$C34*$D34 -> 47405.941 | R34: =P34*$C34*$D34 -> 71108.911 | S34: 21
... A36: 5 | B36: R+R Pod | C36: =_xlfn.XLOOKUP($B36,Inputs!$B$5:$B$9,Inputs!$D$5:$D$9) -> 43 | D36: =_xlfn.XLOOKUP($B36,Inputs!$B$5:$B$9,Inputs!E$5:E$9) -> 60000 | E36: =_xlfn.XLOOKUP($B36,Inputs!$B$5:$B$9,Inputs!H$5:H$9) -> 40 | F36: Communication & coordination | G36: Process | H36: Standardize and schedule reminder templates for vendor follow-ups (e.g., pending return authorization, missing info) | I36: {=_xlfn.IFNA(_xlfn.XLOOKUP(B36&F36,'Activity by Category'!$B$4:$B$99&'Activity by Category'!$C$4:$C$99,'Activity by Category'!$E$4:$E$99)/100,1)} -> 0.20408163 | J36: =I36*_xlfn.XLOOKUP($B36,Inputs!$B$5:$B$9,Inputs!$H$5:$H$9) -> 8.1632653 | K36: 0.04 | L36: 0.06 | M36: =$J36*K36 -> 0.32653061 | N36: =$J36*L36 -> 0.48979592 | O36: =M36/$E36 -> 0.0081632653 | P36: =N36/$E36 -> 0.012244898 | Q36: =O36*$C36*$D36 -> 21061.224 | R36: =P36*$C36*$D36 -> 31591.837 | S36: 33

Sheet temp2
B3: Role | C3: FTEs for ROLE | D3: Cost per year for ROLE | E3: Total hours per week for ROLE | F3: Archetype | G3: Category of opportunity | H3: Opportunity description | I3: Current time spent on activity category (%) | J3: Current time spent on activity archetype (hrs per week) | K3: Efficiency gained on activity archetype % (low-end) | L3: Efficiency gained on activity archetype % (high-end) | M3: Hours saved (low-end) | N3: Hours saved (high-end) | O3: Efficiency gained % on total workweek (low-end) | P3: Efficiency gained % on total workweek (high-end) | Q3: $ impact (low-end) | R3: $ impact (high-end)
B4: R+R Pod | C4: =_xlfn.XLOOKUP($B4,Inputs!$B$5:$B$9,Inputs!$C$5:$C$9) -> 48 | D4: =_xlfn.XLOOKUP($B4,Inputs!$B$5:$B$9,Inputs!I$5:I$9) -> 56875 | E4: =_xlfn.XLOOKUP($B4,Inputs!$B$5:$B$9,Inputs!H$5:H$9) -> 40 | F4: Communication & coordination | G4: Process | H4: Standardize and schedule reminder templates for vendor follow-ups (e.g., pending return authorization, missing info) | I4: {=_xlfn.IFNA(_xlfn.XLOOKUP(B4&F4,'Activity by Category'!$B$4:$B$99&'Activity by Category'!$C$4:$C$99,'Activity by Category'!$E$4:$E$99)/100,1)} -> 0.20408163 | J4: =I4*_xlfn.XLOOKUP($B4,Inputs!$B$5:$B$9,Inputs!$H$5:$H$9) -> 8.1632653 | K4: 0.04 | L4: 0.06 | M4: =$J4*K4 -> 0.32653061 | N4: =$J4*L4 -> 0.48979592 | O4: =M4/$E4 -> 0.0081632653 | P4: =N4/$E4 -> 0.012244898 | Q4: =O4*$C4*$D4 -> 22285.714 | R4: =P4*$C4*$D4 -> 33428.571
B5: R+R Pod | C5: =_xlfn.XLOOKUP($B5,Inputs!$B$5:$B$9,Inputs!$C$5:$C$9) -> 48 | D5: =_xlfn.XLOOKUP($B5,Inputs!$B$5:$B$9,Inputs!I$5:I$9) -> 56875 | E5: =_xlfn.XLOOKUP($B5,Inputs!$B$5:$B$9,Inputs!H$5:H$9) -> 40 | F5: Communication & coordination | G5: Automation | H5: Send automatic updates at major status milestones (e.g., “Return received,” “Replacement shipped,” “Credit applied”). | I5: {=_xlfn.IFNA(_xlfn.XLOOKUP(B5&F5,'Activity by Category'!$B$4:$B$99&'Activity by Category'!$C$4:$C$99,'Activity by Category'!$E$4:$E$99)/100,1)} -> 0.20408163 | J5: =I5*_xlfn.XLOOKUP($B5,Inputs!$B$5:$B$9,Inputs!$H$5:$H$9) -> 8.1632653 | K5: 0.05 | L5: 0.08 | M5: =$J5*K5 -> 0.40816327 | N5: =$J5*L5 -> 0.65306122 | O5: =M5/$E5 -> 0.010204082 | P5: =N5/$E5 -> 0.016326531 | Q5: =O5*$C5*$D5 -> 27857.143 | R5: =P5*$C5*$D5 -> 44571.429
B6: R+R Pod | C6: =_xlfn.XLOOKUP($B6,Inputs!$B$5:$B$9,Inputs!$C$5:$C$9) -> 48 | D6: =_xlfn.XLOOKUP($B6,Inputs!$B$5:$B$9,Inputs!I$5:I$9) -> 56875 | E6: =_xlfn.XLOOKUP($B6,Inputs!$B$5:$B$9,Inputs!H$5:H$9) -> 40 | F6: Case management and processing | G6: Process | H6: Implement standardized intake checklist for new cases | I6: {=_xlfn.IFNA(_xlfn.XLOOKUP(B6&F6,'Activity by Category'!$B$4:$B$99&'Activity by Category'!$C$4:$C$99,'Activity by Category'!$E$4:$E$99)/100,1)} -> 0.66326531 | J6: =I6*_xlfn.XLOOKUP($B6,Inputs!$B$5:$B$9,Inputs!$H$5:$H$9) -> 26.530612 | K6: 0.04 | L6: 0.06 | M6: =$J6*K6 -> 1.0612245 | N6: =$J6*L6 -> 1.5918367 | O6: =M6/$E6 -> 0.026530612 | P6: =N6/$E6 -> 0.039795918 | Q6: =O6*$C6*$D6 -> 72428.571 | R6: =P6*$C6*$D6 -> 108642.86
B7: MTS Pod | C7: =_xlfn.XLOOKUP($B7,Inputs!$B$5:$B$9,Inputs!$C$5:$C$9) -> 73 | D7: =_xlfn.XLOOKUP($B7,Inputs!$B$5:$B$9,Inputs!I$5:I$9) -> 53424.658 | E7: =_xlfn.XLOOKUP($B7,Inputs!$B$5:$B$9,Inputs!H$5:H$9) -> 40 | F7: Shop creation | G7: Process | H7: Streamline QC and standardize review process to minimize rework | I7: {=_xlfn.IFNA(_xlfn.XLOOKUP(B7&F7,'Activity by Category'!$B$4:$B$99&'Activity by Category'!$C$4:$C$99,'Activity by Category'!$E$4:$E$99)/100,1)} -> 0.69306931 | J7: =I7*_xlfn.XLOOKUP($B7,Inputs!$B$5:$B$9,Inputs!$H$5:$H$9) -> 27.722772 | K7: 0.02 | L7: 0.03 | M7: =$J7*K7 -> 0.55445545 | N7: =$J7*L7 -> 0.83168317 | O7: =M7/$E7 -> 0.013861386 | P7: =N7/$E7 -> 0.020792079 | Q7: =O7*$C7*$D7 -> 54059.406 | R7: =P7*$C7*$D7 -> 81089.109
B8: Customer Care | C8: =_xlfn.XLOOKUP($B8,Inputs!$B$5:$B$9,Inputs!$C$5:$C$9) -> 51 | D8: =_xlfn.XLOOKUP($B8,Inputs!$B$5:$B$9,Inputs!I$5:I$9) -> 42352.941 | E8: =_xlfn.XLOOKUP($B8,Inputs!$B$5:$B$9,Inputs!H$5:H$9) -> 40 | F8: Issue resolution | G8: Process | H8: Define structured communication templates (email and Engage) to ensure consistent customer messaging | I8: {=_xlfn.IFNA(_xlfn.XLOOKUP(B8&F8,'Activity by Category'!$B$4:$B$99&'Activity by Category'!$C$4:$C$99,'Activity by Category'!$E$4:$E$99)/100,1)} -> 0.85773563 | J8: =I8*_xlfn.XLOOKUP($B8,Inputs!$B$5:$B$9,Inputs!$H$5:$H$9) -> 34.309425 | K8: 0.03 | L8: 0.05 | M8: =$J8*K8 -> 1.0292828 | N8: =$J8*L8 -> 1.7154713 | O8: =M8/$E8 -> 0.025732069 | P8: =N8/$E8 -> 0.042886781 | Q8: =O8*$C8*$D8 -> 55581.269 | R8: =P8*$C8*$D8 -> 92635.448
B9: Customer Care | C9: =_xlfn.XLOOKUP($B9,Inputs!$B$5:$B$9,Inputs!$C$5:$C$9) -> 51 | D9: =_xlfn.XLOOKUP($B9,Inputs!$B$5:$B$9,Inputs!I$5:I$9) -> 42352.941 | E9: =_xlfn.XLOOKUP($B9,Inputs!$B$5:$B$9,Inputs!H$5:H$9) -> 40 | F9: Issue resolution | G9: Process | H9: Clarify ownership boundaries between Customer Care, SSRs, and R&R for order tracking and problem resolution | I9: {=_xlfn.IFNA(_xlfn.XLOOKUP(B9&F9,'Activity by Category'!$B$4:$B$99&'Activity by Category'!$C$4:$C$99,'Activity by Category'!$E$4:$E$99)/100,1)} -> 0.85773563 | J9: =I9*_xlfn.XLOOKUP($B9,Inputs!$B$5:$B$9,Inputs!$H$5:$H$9) -> 34.309425 | K9: 0.03 | L9: 0.05 | M9: =$J9*K9 -> 1.0292828 | N9: =$J9*L9 -> 1.7154713 | O9: =M9/$E9 -> 0.025732069 | P9: =N9/$E9 -> 0.042886781 | Q9: =O9*$C9*$D9 -> 55581.269 | R9: =P9*$C9*$D9 -> 92635.448
B10: MTS Pod | C10: =_xlfn.XLOOKUP($B10,Inputs!$B$5:$B$9,Inputs!$C$5:$C$9) -> 73 | D10: =_xlfn.XLOOKUP($B10,Inputs!$B$5:$B$9,Inputs!I$5:I$9) -> 53424.658 | E10: =_xlfn.XLOOKUP($B10,Inputs!$B$5:$B$9,Inputs!H$5:H$9) -> 40 | F10: Shop creation support activities | G10: Process | H10: Streamline MTS change requests processes | I10: {=_xlfn.IFNA(_xlfn.XLOOKUP(B10&F10,'Activity by Category'!$B$4:$B$99&'Activity by Category'!$C$4:$C$99,'Activity by Category'!$E$4:$E$99)/100,1)} -> 0.15841584 | J10: =I10*_xlfn.XLOOKUP($B10,Inputs!$B$5:$B$9,Inputs!$H$5:$H$9) -> 6.3366337 | K10: 0.1 | L10: 0.2 | M10: =$J10*K10 -> 0.63366337 | N10: =$J10*L10 -> 1.2673267 | O10: =M10/$E10 -> 0.015841584 | P10: =N10/$E10 -> 0.031683168 | Q10: =O10*$C10*$D10 -> 61782.178 | R10: =P10*$C10*$D10 -> 123564.36
B11: R+R Pod | C11: =_xlfn.XLOOKUP($B11,Inputs!$B$5:$B$9,Inputs!$C$5:$C$9) -> 48 | D11: =_xlfn.XLOOKUP($B11,Inputs!$B$5:$B$9,Inputs!I$5:I$9) -> 56875 | E11: =_xlfn.XLOOKUP($B11,Inputs!$B$5:$B$9,Inputs!H$5:H$9) -> 40 | F11: Case management and processing | G11: Automation | H11: Digitally request and receive vendor return authorizations within Engage, removing email dependency | I11: {=_xlfn.IFNA(_xlfn.XLOOKUP(B11&F11,'Activity by Category'!$B$4:$B$99&'Activity by Category'!$C$4:$C$99,'Activity by Category'!$E$4:$E$99)/100,1)} -> 0.66326531 | J11: =I11*_xlfn.XLOOKUP($B11,Inputs!$B$5:$B$9,Inputs!$H$5:$H$9) -> 26.530612 | K11: 0.07 | L11: 0.1 | M11: =$J11*K11 -> 1.8571429 | N11: =$J11*L11 -> 2.6530612 | O11: =M11/$E11 -> 0.046428571 | P11: =N11/$E11 -> 0.066326531 | Q11: =O11*$C11*$D11 -> 126750 | R11: =P11*$C11*$D11 -> 181071.43
B12: R+R Pod | C12: =_xlfn.XLOOKUP($B12,Inputs!$B$5:$B$9,Inputs!$C$5:$C$9) -> 48 | D12: =_xlfn.XLOOKUP($B12,Inputs!$B$5:$B$9,Inputs!I$5:I$9) -> 56875 | E12: =_xlfn.XLOOKUP($B12,Inputs!$B$5:$B$9,Inputs!H$5:H$9) -> 40 | F12: Case management and processing | G12: Automation | H12: Auto-generate replacement orders (ZREP/RE), shipping labels, and freight pickup scheduling from case data | I12: {=_xlfn.IFNA(_xlfn.XLOOKUP(B12&F12,'Activity by Category'!$B$4:$B$99&'Activity by Category'!$C$4:$C$99,'Activity by Category'!$E$4:$E$99)/100,1)} -> 0.66326531 | J12: =I12*_xlfn.XLOOKUP($B12,Inputs!$B$5:$B$9,Inputs!$H$5:$H$9) -> 26.530612 | K12: 0.1 | L12: 0.15 | M12: =$J12*K12 -> 2.6530612 | N12: =$J12*L12 -> 3.9795918 | O12: =M12/$E12 -> 0.066326531 | P12: =N12/$E12 -> 0.099489796 | Q12: =O12*$C12*$D12 -> 181071.43 | R12: =P12*$C12*$D12 -> 271607.14
B13: TM | C13: =_xlfn.XLOOKUP($B13,Inputs!$B$5:$B$9,Inputs!$C$5:$C$9) -> 139 | D13: =_xlfn.XLOOKUP($B13,Inputs!$B$5:$B$9,Inputs!I$5:I$9) -> 60000 | E13: =_xlfn.XLOOKUP($B13,Inputs!$B$5:$B$9,Inputs!H$5:H$9) -> 40 | F13: Sales support activities | G13: Process | H13: Clarify boundaries between TMs and SSRs for quoting vs. order setup | I13: {=_xlfn.IFNA(_xlfn.XLOOKUP(B13&F13,'Activity by Category'!$B$4:$B$99&'Activity by Category'!$C$4:$C$99,'Activity by Category'!$E$4:$E$99)/100,1)} -> 0.90697674 | J13: =I13*_xlfn.XLOOKUP($B13,Inputs!$B$5:$B$9,Inputs!$H$5:$H$9) -> 36.27907 | K13: 0.02 | L13: 0.03 | M13: =$J13*K13 -> 0.7255814 | N13: =$J13*L13 -> 1.0883721 | O13: =M13/$E13 -> 0.018139535 | P13: =N13/$E13 -> 0.027209302 | Q13: =O13*$C13*$D13 -> 151283.72 | R13: =P13*$C13*$D13 -> 226925.58
B14: Customer Care | C14: =_xlfn.XLOOKUP($B14,Inputs!$B$5:$B$9,Inputs!$C$5:$C$9) -> 51 | D14: =_xlfn.XLOOKUP($B14,Inputs!$B$5:$B$9,Inputs!I$5:I$9) -> 42352.941 | E14: =_xlfn.XLOOKUP($B14,Inputs!$B$5:$B$9,Inputs!H$5:H$9) -> 40 | F14: Issue resolution | G14: Automation | H14: Utilize intelligent ticket routing to assign customer issues to the right queue or specialist | I14: {=_xlfn.IFNA(_xlfn.XLOOKUP(B14&F14,'Activity by Category'!$B$4:$B$99&'Activity by Category'!$C$4:$C$99,'Activity by Category'!$E$4:$E$99)/100,1)} -> 0.85773563 | J14: =I14*_xlfn.XLOOKUP($B14,Inputs!$B$5:$B$9,Inputs!$H$5:$H$9) -> 34.309425 | K14: 0.05 | L14: 0.1 | M14: =$J14*K14 -> 1.7154713 | N14: =$J14*L14 -> 3.4309425 | O14: =M14/$E14 -> 0.042886781 | P14: =N14/$E14 -> 0.085773563 | Q14: =O14*$C14*$D14 -> 92635.448 | R14: =P14*$C14*$D14 -> 185270.9
B15: MTS Pod | C15: =_xlfn.XLOOKUP($B15,Inputs!$B$5:$B$9,Inputs!$C$5:$C$9) -> 73 | D15: =_xlfn.XLOOKUP($B15,Inputs!$B$5:$B$9,Inputs!I$5:I$9) -> 53424.658 | E15: =_xlfn.XLOOKUP($B15,Inputs!$B$5:$B$9,Inputs!H$5:H$9) -> 40 | F15: Shop creation | G15: Automation | H15: Streamline artwork submissions and auto-route licensing submissions for approval | I15: {=_xlfn.IFNA(_xlfn.XLOOKUP(B15&F15,'Activity by Category'!$B$4:$B$99&'Activity by Category'!$C$4:$C$99,'Activity by Category'!$E$4:$E$99)/100,1)} -> 0.69306931 | J15: =I15*_xlfn.XLOOKUP($B15,Inputs!$B$5:$B$9,Inputs!$H$5:$H$9) -> 27.722772 | K15: 0.05 | L15: 0.08 | M15: =$J15*K15 -> 1.3861386 | N15: =$J15*L15 -> 2.2178218 | O15: =M15/$E15 -> 0.034653465 | P15: =N15/$E15 -> 0.055445545 | Q15: =O15*$C15*$D15 -> 135148.51 | R15: =P15*$C15*$D15 -> 216237.62
... B36: Customer Care | C36: =_xlfn.XLOOKUP($B36,Inputs!$B$5:$B$9,Inputs!$C$5:$C$9) -> 51 | D36: =_xlfn.XLOOKUP($B36,Inputs!$B$5:$B$9,Inputs!I$5:I$9) -> 42352.941 | E36: =_xlfn.XLOOKUP($B36,Inputs!$B$5:$B$9,Inputs!H$5:H$9) -> 40 | F36: Issue resolution | G36: Automation | H36: Streamline ticket generation follow-ups and other post-call activities | I36: {=_xlfn.IFNA(_xlfn.XLOOKUP(B36&F36,'Activity by Category'!$B$4:$B$99&'Activity by Category'!$C$4:$C$99,'Activity by Category'!$E$4:$E$99)/100,1)} -> 0.85773563 | J36: =I36*_xlfn.XLOOKUP($B36,Inputs!$B$5:$B$9,Inputs!$H$5:$H$9) -> 34.309425 | K36: 0.05 | L36: 0.1 | M36: =$J36*K36 -> 1.7154713 | N36: =$J36*L36 -> 3.4309425 | O36: =M36/$E36 -> 0.042886781 | P36: =N36/$E36 -> 0.085773563 | Q36: =O36*$C36*$D36 -> 92635.448 | R36: =P36*$C36*$D36 -> 185270.9

Sheet Activity Mapping
B2: Response ID | C2: Question | D2: Activity | E2: Role | F2: Percent of Time (Median) | G2: Best practice mapping | H2: New categorization | I2: Initiative suggestion
B3: Q2.1_15 | C3: What is the % mix of time that you spend on these categories of contact below in an average 40 hour work week, excluding lunch? (e.g. 10% of a week is 4 hours) | D3: Breaks | E3: Customer Care | F3: {=MEDIAN(IF('Percent Responses Cleaned'!$C$4:$C$375=$E3,INDEX('Percent Responses Cleaned'!$D$4:$BV$375,,MATCH($B3,'Percent Responses Cleaned'!$D$3:$BV$3,0))))} -> 10 | G3: Admin and other | H3: Other activities
B4: Q2.1_16 | C4: What is the % mix of time that you spend on these categories of contact below in an average 40 hour work week, excluding lunch? (e.g. 10% of a week is 4 hours) | D4: Other activities (specify activity and provide details on the following page) | E4: Customer Care | F4: {=MEDIAN(IF('Percent Responses Cleaned'!$C$4:$C$375=$E4,INDEX('Percent Responses Cleaned'!$D$4:$BV$375,,MATCH($B4,'Percent Responses Cleaned'!$D$3:$BV$3,0))))} -> 0 | G4: Admin and other | H4: Other activities
B5: Q2.1_8 | C5: What is the % mix of time that you spend on these categories of contact below in an average 40 hour work week, excluding lunch? (e.g. 10% of a week is 4 hours) | D5: Refund request | E5: Customer Care | F5: {=MEDIAN(IF('Percent Responses Cleaned'!$C$4:$C$375=$E5,INDEX('Percent Responses Cleaned'!$D$4:$BV$375,,MATCH($B5,'Percent Responses Cleaned'!$D$3:$BV$3,0))))} -> 10 | G5: Customer facing issue resolution tasks | H5: Issue resolution
B6: Q2.1_4 | C6: What is the % mix of time that you spend on these categories of contact below in an average 40 hour work week, excluding lunch? (e.g. 10% of a week is 4 hours) | D6: Replacements & returns | E6: Customer Care | F6: {=MEDIAN(IF('Percent Responses Cleaned'!$C$4:$C$375=$E6,INDEX('Percent Responses Cleaned'!$D$4:$BV$375,,MATCH($B6,'Percent Responses Cleaned'!$D$3:$BV$3,0))))} -> 10 | G6: Customer facing issue resolution tasks | H6: Issue resolution
B7: Q2.1_7 | C7: What is the % mix of time that you spend on these categories of contact below in an average 40 hour work week, excluding lunch? (e.g. 10% of a week is 4 hours) | D7: Sizing issues | E7: Customer Care | F7: {=MEDIAN(IF('Percent Responses Cleaned'!$C$4:$C$375=$E7,INDEX('Percent Responses Cleaned'!$D$4:$BV$375,,MATCH($B7,'Percent Responses Cleaned'!$D$3:$BV$3,0))))} -> 9 | G7: Customer facing issue resolution tasks | H7: Issue resolution
B8: Q2.1_3 | C8: What is the % mix of time that you spend on these categories of contact below in an average 40 hour work week, excluding lunch? (e.g. 10% of a week is 4 hours) | D8: Cancellation | E8: Customer Care | F8: {=MEDIAN(IF('Percent Responses Cleaned'!$C$4:$C$375=$E8,INDEX('Percent Responses Cleaned'!$D$4:$BV$375,,MATCH($B8,'Percent Responses Cleaned'!$D$3:$BV$3,0))))} -> 5 | G8: Customer facing issue resolution tasks | H8: Issue resolution
B9: Q2.1_10 | C9: What is the % mix of time that you spend on these categories of contact below in an average 40 hour work week, excluding lunch? (e.g. 10% of a week is 4 hours) | D9: Other customer inquiries | E9: Customer Care | F9: {=MEDIAN(IF('Percent Responses Cleaned'!$C$4:$C$375=$E9,INDEX('Percent Responses Cleaned'!$D$4:$BV$375,,MATCH($B9,'Percent Responses Cleaned'!$D$3:$BV$3,0))))} -> 5 | G9: Customer facing issue resolution tasks | H9: Issue resolution
B10: Q2.1_9 | C10: What is the % mix of time that you spend on these categories of contact below in an average 40 hour work week, excluding lunch? (e.g. 10% of a week is 4 hours) | D10: Missed order deadline | E10: Customer Care | F10: {=MEDIAN(IF('Percent Responses Cleaned'!$C$4:$C$375=$E10,INDEX('Percent Responses Cleaned'!$D$4:$BV$375,,MATCH($B10,'Percent Responses Cleaned'!$D$3:$BV$3,0))))} -> 3 | G10: Customer facing issue resolution tasks | H10: Issue resolution
B11: Q2.1_6 | C11: What is the % mix of time that you spend on these categories of contact below in an average 40 hour work week, excluding lunch? (e.g. 10% of a week is 4 hours) | D11: Website/ technical support | E11: Customer Care | F11: {=MEDIAN(IF('Percent Responses Cleaned'!$C$4:$C$375=$E11,INDEX('Percent Responses Cleaned'!$D$4:$BV$375,,MATCH($B11,'Percent Responses Cleaned'!$D$3:$BV$3,0))))} -> 3 | G11: Customer facing issue resolution tasks | H11: Issue resolution
B12: Q2.1_1 | C12: What is the % mix of time that you spend on these categories of contact below in an average 40 hour work week, excluding lunch? (e.g. 10% of a week is 4 hours) | D12: Order status/tracking | E12: Customer Care | F12: {=MEDIAN(IF('Percent Responses Cleaned'!$C$4:$C$375=$E12,INDEX('Percent Responses Cleaned'!$D$4:$BV$375,,MATCH($B12,'Percent Responses Cleaned'!$D$3:$BV$3,0))))} -> 10 | G12: Customer facing tasks | H12: Issue resolution
B13: Q2.1_2 | C13: What is the % mix of time that you spend on these categories of contact below in an average 40 hour work week, excluding lunch? (e.g. 10% of a week is 4 hours) | D13: New order/ quote | E13: Customer Care | F13: {=MEDIAN(IF('Percent Responses Cleaned'!$C$4:$C$375=$E13,INDEX('Percent Responses Cleaned'!$D$4:$BV$375,,MATCH($B13,'Percent Responses Cleaned'!$D$3:$BV$3,0))))} -> 5 | G13: Customer facing tasks | H13: Issue resolution
B14: Q2.1_5 | C14: What is the % mix of time that you spend on these categories of contact below in an average 40 hour work week, excluding lunch? (e.g. 10% of a week is 4 hours) | D14: Order edit/change | E14: Customer Care | F14: {=MEDIAN(IF('Percent Responses Cleaned'!$C$4:$C$375=$E14,INDEX('Percent Responses Cleaned'!$D$4:$BV$375,,MATCH($B14,'Percent Responses Cleaned'!$D$3:$BV$3,0))))} -> 5 | G14: Customer facing tasks | H14: Issue resolution
... B21: Q4.1_6 | C21: What is the % mix of time that you spend on these activities below in an average 40 hour work week, excluding lunch? (e.g. 10% of a week is 4 hours) | D21: Working on Open orders | E21: SSR | F21: {=MEDIAN(IF('Percent Responses Cleaned'!$C$4:$C$375=$E21,INDEX('Percent Responses Cleaned'!$D$4:$BV$375,,MATCH($B21,'Percent Responses Cleaned'!$D$3:$BV$3,0))))} -> 30 | G21: Order management tasks (e.g., core order changes, pushing carts, working on open orders, etc.) | H21: Order management
B22: Q4.1_5 | C22: What is the % mix of time that you spend on these activities below in an average 40 hour work week, excluding lunch? (e.g. 10% of a week is 4 hours) | D22: Core Order Changes | E22: SSR | F22: {=MEDIAN(IF('Percent Responses Cleaned'!$C$4:$C$375=$E22,INDEX('Percent Responses Cleaned'!$D$4:$BV$375,,MATCH($B22,'Percent Responses Cleaned'!$D$3:$BV$3,0))))} -> 10 | G22: Order management tasks (e.g., core order changes, pushing carts, working on open orders, etc.) | H22: Order management | I22: Self serve channel for customers to ask for core order changes (20% of activity)--> turn it into an approve / reject decision (process)
B23: Q4.1_13 | C23: What is the % mix of time that you spend on these activities below in an average 40 hour work week, excluding lunch? (e.g. 10% of a week is 4 hours) | D23: Internal communications (e.g. email/ calls to FSPs) | E23: SSR | F23: {=MEDIAN(IF('Percent Responses Cleaned'!$C$4:$C$375=$E23,INDEX('Percent Responses Cleaned'!$D$4:$BV$375,,MATCH($B23,'Percent Responses Cleaned'!$D$3:$BV$3,0))))} -> 10 | G23: Other activities | H23: Order management
B24: Q4.1_2 | C24: What is the % mix of time that you spend on these activities below in an average 40 hour work week, excluding lunch? (e.g. 10% of a week is 4 hours) | D24: MTS Changes | E24: SSR | F24: {=MEDIAN(IF('Percent Responses Cleaned'!$C$4:$C$375=$E24,INDEX('Percent Responses Cleaned'!$D$4:$BV$375,,MATCH($B24,'Percent Responses Cleaned'!$D$3:$BV$3,0))))} -> 5 | G24: Customer-facing time | H24: Order management | I24: How do yo use standard templates to ask for MTS changes vs. doing this ad hoc (20%) -->
B25: Q4.1_8 | C25: What is the % mix of time that you spend on these activities below in an average 40 hour work week, excluding lunch? (e.g. 10% of a week is 4 hours) | D25: AP/AR | E25: SSR | F25: {=MEDIAN(IF('Percent Responses Cleaned'!$C$4:$C$375=$E25,INDEX('Percent Responses Cleaned'!$D$4:$BV$375,,MATCH($B25,'Percent Responses Cleaned'!$D$3:$BV$3,0))))} -> 2 | G25: Order management tasks (e.g., core order changes, pushing carts, working on open orders, etc.) | H25: Order management
B26: Q4.1_3 | C26: What is the % mix of time that you spend on these activities below in an average 40 hour work week, excluding lunch? (e.g. 10% of a week is 4 hours) | D26: Consolidating MTS shops | E26: SSR | F26: {=MEDIAN(IF('Percent Responses Cleaned'!$C$4:$C$375=$E26,INDEX('Percent Responses Cleaned'!$D$4:$BV$375,,MATCH($B26,'Percent Responses Cleaned'!$D$3:$BV$3,0))))} -> 2 | G26: Order management tasks (e.g., core order changes, pushing carts, working on open orders, etc.) | H26: Order management
B27: Q4.1_4 | C27: What is the % mix of time that you spend on these activities below in an average 40 hour work week, excluding lunch? (e.g. 10% of a week is 4 hours) | D27: MTS Credits | E27: SSR | F27: {=MEDIAN(IF('Percent Responses Cleaned'!$C$4:$C$375=$E27,INDEX('Percent Responses Cleaned'!$D$4:$BV$375,,MATCH($B27,'Percent Responses Cleaned'!$D$3:$BV$3,0))))} -> 1 | G27: Post-sales (order-related handlings) | H27: Order management
B28: Q4.1_1 | C28: What is the % mix of time that you spend on these activities below in an average 40 hour work week, excluding lunch? (e.g. 10% of a week is 4 hours) | D28: Pushing Carts | E28: SSR | F28: {=MEDIAN(IF('Percent Responses Cleaned'!$C$4:$C$375=$E28,INDEX('Percent Responses Cleaned'!$D$4:$BV$375,,MATCH($B28,'Percent Responses Cleaned'!$D$3:$BV$3,0))))} -> 1 | G28: Order management tasks (e.g., core order changes, pushing carts, working on open orders, etc.) | H28: Order management
B29: Q4.1_10 | C29: What is the % mix of time that you spend on these activities below in an average 40 hour work week, excluding lunch? (e.g. 10% of a week is 4 hours) | D29: Label Requests (Freight) | E29: SSR | F29: {=MEDIAN(IF('Percent Responses Cleaned'!$C$4:$C$375=$E29,INDEX('Percent Responses Cleaned'!$D$4:$BV$375,,MATCH($B29,'Percent Responses Cleaned'!$D$3:$BV$3,0))))} -> 1 | G29: Order management tasks (e.g., core order changes, pushing carts, working on open orders, etc.) | H29: Order management
B30: Q4.1_12 | C30: What is the % mix of time that you spend on these activities below in an average 40 hour work week, excluding lunch? (e.g. 10% of a week is 4 hours) | D30: Processing Comp Goods | E30: SSR | F30: {=MEDIAN(IF('Percent Responses Cleaned'!$C$4:$C$375=$E30,INDEX('Percent Responses Cleaned'!$D$4:$BV$375,,MATCH($B30,'Percent Responses Cleaned'!$D$3:$BV$3,0))))} -> 0 | G30: Other activities | H30: Order management
B31: Q4.1_15 | C31: What is the % mix of time that you spend on these activities below in an average 40 hour work week, excluding lunch? (e.g. 10% of a week is 4 hours) | D31: Breaks | E31: SSR | F31: {=MEDIAN(IF('Percent Responses Cleaned'!$C$4:$C$375=$E31,INDEX('Percent Responses Cleaned'!$D$4:$BV$375,,MATCH($B31,'Percent Responses Cleaned'!$D$3:$BV$3,0))))} -> 10 | G31: Receiving training or coaching | H31: Other activities
B32: Q4.1_14 | C32: What is the % mix of time that you spend on these activities below in an average 40 hour work week, excluding lunch? (e.g. 10% of a week is 4 hours) | D32: Meetings (e.g. team meetings, townhalls) | E32: SSR | F32: {=MEDIAN(IF('Percent Responses Cleaned'!$C$4:$C$375=$E32,INDEX('Percent Responses Cleaned'!$D$4:$BV$375,,MATCH($B32,'Percent Responses Cleaned'!$D$3:$BV$3,0))))} -> 1 | G32: Receiving training or coaching | H32: Other activities
B33: Q4.1_16 | C33: What is the % mix of time that you spend on these activities below in an average 40 hour work week, excluding lunch? (e.g. 10% of a week is 4 hours) | D33: Other activities (specify activity and provide details on the following page) | E33: SSR | F33: {=MEDIAN(IF('Percent Responses Cleaned'!$C$4:$C$375=$E33,INDEX('Percent Responses Cleaned'!$D$4:$BV$375,,MATCH($B33,'Percent Responses Cleaned'!$D$3:$BV$3,0))))} -> 0 | G33: Other activities | H33: Other activities
B34: Q6.1_12 | C34: What is the % mix of time that you spend on these activities below in an average 40 hour work week, excluding lunch? (e.g. 10% of a week is 4 hours) | D34: Meetings (e.g. team meetings, townhalls) | E34: TM | F34: {=MEDIAN(IF('Percent Responses Cleaned'!$C$4:$C$375=$E34,INDEX('Percent Responses Cleaned'!$D$4:$BV$375,,MATCH($B34,'Percent Responses Cleaned'!$D$3:$BV$3,0))))} -> 5 | G34: Receiving training / coaching | H34: Other activities
B35: Q6.1_4 | C35: What is the % mix of time that you spend on these activities below in an average 40 hour work week, excluding lunch? (e.g. 10% of a week is 4 hours) | D35: Content Creation | E35: TM | F35: {=MEDIAN(IF('Percent Responses Cleaned'!$C$4:$C$375=$E35,INDEX('Percent Responses Cleaned'!$D$4:$BV$375,,MATCH($B35,'Percent Responses Cleaned'!$D$3:$BV$3,0))))} -> 2 | G35: Sales interactions (e.g., quote carting, fact finding, purchase ordering, etc.) | H35: Other activities
B36: Q6.1_5 | C36: What is the % mix of time that you spend on these activities below in an average 40 hour work week, excluding lunch? (e.g. 10% of a week is 4 hours) | D36: Rewards agreement | E36: TM | F36: {=MEDIAN(IF('Percent Responses Cleaned'!$C$4:$C$375=$E36,INDEX('Percent Responses Cleaned'!$D$4:$BV$375,,MATCH($B36,'Percent Responses Cleaned'!$D$3:$BV$3,0))))} -> 1 | G36: Sales interactions (e.g., quote carting, fact finding, purchase ordering, etc.) | H36: Other activities
... B38: Q6.1_13 | C38: What is the % mix of time that you spend on these activities below in an average 40 hour work week, excluding lunch? (e.g. 10% of a week is 4 hours) | D38: Other activities (specify activity and provide details on the following page) | E38: TM | F38: {=MEDIAN(IF('Percent Responses Cleaned'!$C$4:$C$375=$E38,INDEX('Percent Responses Cleaned'!$D$4:$BV$375,,MATCH($B38,'Percent Responses Cleaned'!$D$3:$BV$3,0))))} -> 0 | G38: Admin / other | H38: Other activities
B39: Q6.1_1 | C39: What is the % mix of time that you spend on these activities below in an average 40 hour work week, excluding lunch? (e.g. 10% of a week is 4 hours) | D39: Quote Cart | E39: TM | F39: {=MEDIAN(IF('Percent Responses Cleaned'!$C$4:$C$375=$E39,INDEX('Percent Responses Cleaned'!$D$4:$BV$375,,MATCH($B39,'Percent Responses Cleaned'!$D$3:$BV$3,0))))} -> 35 | G39: Sales interactions (e.g., quote carting, fact finding, purchase ordering, etc.) | H39: Sales support activities | I39: Add idea on copilot generation of carts using conversational engine - don't pull SKUs, tell customer requirements, and they'll pull it for you (25-30%)
B40: Q6.1_2 | C40: What is the % mix of time that you spend on these activities below in an average 40 hour work week, excluding lunch? (e.g. 10% of a week is 4 hours) | D40: Fact Finding | E40: TM | F40: {=MEDIAN(IF('Percent Responses Cleaned'!$C$4:$C$375=$E40,INDEX('Percent Responses Cleaned'!$D$4:$BV$375,,MATCH($B40,'Percent Responses Cleaned'!$D$3:$BV$3,0))))} -> 25 | G40: Sales interactions (e.g., quote carting, fact finding, purchase ordering, etc.) | H40: Sales support activities | I40: Agent that knows all SKUs and pulls all the right information and details you need (40-50%)
B41: Q6.1_10 | C41: What is the % mix of time that you spend on these activities below in an average 40 hour work week, excluding lunch? (e.g. 10% of a week is 4 hours) | D41: Internal communications (e.g. email/ calls to FSPs) | E41: TM | F41: {=MEDIAN(IF('Percent Responses Cleaned'!$C$4:$C$375=$E41,INDEX('Percent Responses Cleaned'!$D$4:$BV$375,,MATCH($B41,'Percent Responses Cleaned'!$D$3:$BV$3,0))))} -> 10 | G41: Admin / other | H41: Sales support activities
B42: Q6.1_11 | C42: What is the % mix of time that you spend on these activities below in an average 40 hour work week, excluding lunch? (e.g. 10% of a week is 4 hours) | D42: External communications (e.g. emails/ calls to vendors) | E42: TM | F42: {=MEDIAN(IF('Percent Responses Cleaned'!$C$4:$C$375=$E42,INDEX('Percent Responses Cleaned'!$D$4:$BV$375,,MATCH($B42,'Percent Responses Cleaned'!$D$3:$BV$3,0))))} -> 5 | G42: Sales interactions (e.g., quote carting, fact finding, purchase ordering, etc.) | H42: Sales support activities
B43: Q6.1_9 | C43: What is the % mix of time that you spend on these activities below in an average 40 hour work week, excluding lunch? (e.g. 10% of a week is 4 hours) | D43: Other supporting activities (Adidas, BSN Construction, Corporate, bid, Training) | E43: TM | F43: {=MEDIAN(IF('Percent Responses Cleaned'!$C$4:$C$375=$E43,INDEX('Percent Responses Cleaned'!$D$4:$BV$375,,MATCH($B43,'Percent Responses Cleaned'!$D$3:$BV$3,0))))} -> 1 | G43: Receiving training / coaching | H43: Sales support activities
B44: Q6.1_6 | C44: What is the % mix of time that you spend on these activities below in an average 40 hour work week, excluding lunch? (e.g. 10% of a week is 4 hours) | D44: Return/ Replacement | E44: TM | F44: {=MEDIAN(IF('Percent Responses Cleaned'!$C$4:$C$375=$E44,INDEX('Percent Responses Cleaned'!$D$4:$BV$375,,MATCH($B44,'Percent Responses Cleaned'!$D$3:$BV$3,0))))} -> 1 | G44: Post sales customer service | H44: Sales support activities
B45: Q6.1_8 | C45: What is the % mix of time that you spend on these activities below in an average 40 hour work week, excluding lunch? (e.g. 10% of a week is 4 hours) | D45: Freight Quote | E45: TM | F45: {=MEDIAN(IF('Percent Responses Cleaned'!$C$4:$C$375=$E45,INDEX('Percent Responses Cleaned'!$D$4:$BV$375,,MATCH($B45,'Percent Responses Cleaned'!$D$3:$BV$3,0))))} -> 1 | G45: Sales interactions (e.g., quote carting, fact finding, purchase ordering, etc.) | H45: Sales support activities
B46: Q6.1_3 | C46: What is the % mix of time that you spend on these activities below in an average 40 hour work week, excluding lunch? (e.g. 10% of a week is 4 hours) | D46: Purchase Order | E46: TM | F46: {=MEDIAN(IF('Percent Responses Cleaned'!$C$4:$C$375=$E46,INDEX('Percent Responses Cleaned'!$D$4:$BV$375,,MATCH($B46,'Percent Responses Cleaned'!$D$3:$BV$3,0))))} -> 0 | G46: Sales interactions (e.g., quote carting, fact finding, purchase ordering, etc.) | H46: Sales support activities
B47: Q7.1_1 | C47: What is the % mix of time that you spend on these activities below in an average 40 hour work week, excluding lunch? (e.g. 10% of a week is 4 hours) | D47: New Cases | E47: Comp Pod | F47: {=MEDIAN(IF('Percent Responses Cleaned'!$C$4:$C$375=$E47,INDEX('Percent Responses Cleaned'!$D$4:$BV$375,,MATCH($B47,'Percent Responses Cleaned'!$D$3:$BV$3,0))))} -> 15
B48: Q7.1_2 | C48: What is the % mix of time that you spend on these activities below in an average 40 hour work week, excluding lunch? (e.g. 10% of a week is 4 hours) | D48: Order Entry (e.g. creating comp carts, applying coupons from Nike, UA etc.) | E48: Comp Pod | F48: {=MEDIAN(IF('Percent Responses Cleaned'!$C$4:$C$375=$E48,INDEX('Percent Responses Cleaned'!$D$4:$BV$375,,MATCH($B48,'Percent Responses Cleaned'!$D$3:$BV$3,0))))} -> 15
B49: Q7.1_3 | C49: What is the % mix of time that you spend on these activities below in an average 40 hour work week, excluding lunch? (e.g. 10% of a week is 4 hours) | D49: Managing stocking issues | E49: Comp Pod | F49: {=MEDIAN(IF('Percent Responses Cleaned'!$C$4:$C$375=$E49,INDEX('Percent Responses Cleaned'!$D$4:$BV$375,,MATCH($B49,'Percent Responses Cleaned'!$D$3:$BV$3,0))))} -> 16
B50: Q7.1_4 | C50: What is the % mix of time that you spend on these activities below in an average 40 hour work week, excluding lunch? (e.g. 10% of a week is 4 hours) | D50: Internal communication (Emails/ Calls to FSPs) | E50: Comp Pod | F50: {=MEDIAN(IF('Percent Responses Cleaned'!$C$4:$C$375=$E50,INDEX('Percent Responses Cleaned'!$D$4:$BV$375,,MATCH($B50,'Percent Responses Cleaned'!$D$3:$BV$3,0))))} -> 10
B51: Q7.1_5 | C51: What is the % mix of time that you spend on these activities below in an average 40 hour work week, excluding lunch? (e.g. 10% of a week is 4 hours) | D51: External communications (e.g. emails/ calls to vendors) | E51: Comp Pod | F51: {=MEDIAN(IF('Percent Responses Cleaned'!$C$4:$C$375=$E51,INDEX('Percent Responses Cleaned'!$D$4:$BV$375,,MATCH($B51,'Percent Responses Cleaned'!$D$3:$BV$3,0))))} -> 5
B52: Q7.1_6 | C52: What is the % mix of time that you spend on these activities below in an average 40 hour work week, excluding lunch? (e.g. 10% of a week is 4 hours) | D52: Meetings (e.g. team meetings, townhalls) | E52: Comp Pod | F52: {=MEDIAN(IF('Percent Responses Cleaned'!$C$4:$C$375=$E52,INDEX('Percent Responses Cleaned'!$D$4:$BV$375,,MATCH($B52,'Percent Responses Cleaned'!$D$3:$BV$3,0))))} -> 5
B53: Q7.1_7 | C53: What is the % mix of time that you spend on these activities below in an average 40 hour work week, excluding lunch? (e.g. 10% of a week is 4 hours) | D53: Order Management (tracking order) | E53: Comp Pod | F53: {=MEDIAN(IF('Percent Responses Cleaned'!$C$4:$C$375=$E53,INDEX('Percent Responses Cleaned'!$D$4:$BV$375,,MATCH($B53,'Percent Responses Cleaned'!$D$3:$BV$3,0))))} -> 10
B54: Q7.1_8 | C54: What is the % mix of time that you spend on these activities below in an average 40 hour work week, excluding lunch? (e.g. 10% of a week is 4 hours) | D54: Breaks | E54: Comp Pod | F54: {=MEDIAN(IF('Percent Responses Cleaned'!$C$4:$C$375=$E54,INDEX('Percent Responses Cleaned'!$D$4:$BV$375,,MATCH($B54,'Percent Responses Cleaned'!$D$3:$BV$3,0))))} -> 10
B55: Q7.1_9 | C55: What is the % mix of time that you spend on these activities below in an average 40 hour work week, excluding lunch? (e.g. 10% of a week is 4 hours) | D55: Other activities (specify activity and provide details on the following page) | E55: Comp Pod | F55: {=MEDIAN(IF('Percent Responses Cleaned'!$C$4:$C$375=$E55,INDEX('Percent Responses Cleaned'!$D$4:$BV$375,,MATCH($B55,'Percent Responses Cleaned'!$D$3:$BV$3,0))))} -> 0
B56: Q8.1_1 | C56: What is the % mix of time that you spend on these activities below in an average 40 hour work week, excluding lunch? (e.g. 10% of a week is 4 hours) | D56: New Cases | E56: R+R Pod | F56: {=MEDIAN(IF('Percent Responses Cleaned'!$C$4:$C$375=$E56,INDEX('Percent Responses Cleaned'!$D$4:$BV$375,,MATCH($B56,'Percent Responses Cleaned'!$D$3:$BV$3,0))))} -> 25 | G56: Case management and processing | H56: Case management and processing
B57: Q8.1_2 | C57: What is the % mix of time that you spend on these activities below in an average 40 hour work week, excluding lunch? (e.g. 10% of a week is 4 hours) | D57: Order entry (ZREP/RE Entry) | E57: R+R Pod | F57: {=MEDIAN(IF('Percent Responses Cleaned'!$C$4:$C$375=$E57,INDEX('Percent Responses Cleaned'!$D$4:$BV$375,,MATCH($B57,'Percent Responses Cleaned'!$D$3:$BV$3,0))))} -> 20 | G57: Case management and processing | H57: Case management and processing
B58: Q8.1_3 | C58: What is the % mix of time that you spend on these activities below in an average 40 hour work week, excluding lunch? (e.g. 10% of a week is 4 hours) | D58: Order management (Status review of ZREPs/ RE/Original Order Open) | E58: R+R Pod | F58: {=MEDIAN(IF('Percent Responses Cleaned'!$C$4:$C$375=$E58,INDEX('Percent Responses Cleaned'!$D$4:$BV$375,,MATCH($B58,'Percent Responses Cleaned'!$D$3:$BV$3,0))))} -> 20 | G58: Case management and processing | H58: Case management and processing
B59: Q8.1_4 | C59: What is the % mix of time that you spend on these activities below in an average 40 hour work week, excluding lunch? (e.g. 10% of a week is 4 hours) | D59: Internal communication (Emails/ Calls to FSPs) | E59: R+R Pod | F59: {=MEDIAN(IF('Percent Responses Cleaned'!$C$4:$C$375=$E59,INDEX('Percent Responses Cleaned'!$D$4:$BV$375,,MATCH($B59,'Percent Responses Cleaned'!$D$3:$BV$3,0))))} -> 10 | G59: Communication & coordination | H59: Communication & coordination
B60: Q8.1_5 | C60: What is the % mix of time that you spend on these activities below in an average 40 hour work week, excluding lunch? (e.g. 10% of a week is 4 hours) | D60: External communications (e.g. emails/ calls to vendors) | E60: R+R Pod | F60: {=MEDIAN(IF('Percent Responses Cleaned'!$C$4:$C$375=$E60,INDEX('Percent Responses Cleaned'!$D$4:$BV$375,,MATCH($B60,'Percent Responses Cleaned'!$D$3:$BV$3,0))))} -> 10 | G60: Communication & coordination | H60: Communication & coordination
B61: Q8.1_6 | C61: What is the % mix of time that you spend on these activities below in an average 40 hour work week, excluding lunch? (e.g. 10% of a week is 4 hours) | D61: Meetings (e.g. team meetings, townhalls) | E61: R+R Pod | F61: {=MEDIAN(IF('Percent Responses Cleaned'!$C$4:$C$375=$E61,INDEX('Percent Responses Cleaned'!$D$4:$BV$375,,MATCH($B61,'Percent Responses Cleaned'!$D$3:$BV$3,0))))} -> 3 | G61: Meetings | H61: Other activities
B62: Q8.1_8 | C62: What is the % mix of time that you spend on these activities below in an average 40 hour work week, excluding lunch? (e.g. 10% of a week is 4 hours) | D62: Breaks | E62: R+R Pod | F62: {=MEDIAN(IF('Percent Responses Cleaned'!$C$4:$C$375=$E62,INDEX('Percent Responses Cleaned'!$D$4:$BV$375,,MATCH($B62,'Percent Responses Cleaned'!$D$3:$BV$3,0))))} -> 10 | G62: Admin / other | H62: Other activities
B63: Q8.1_9 | C63: What is the % mix of time that you spend on these activities below in an average 40 hour work week, excluding lunch? (e.g. 10% of a week is 4 hours) | D63: Other activities (specify activity and provide details on the following page) | E63: R+R Pod | F63: {=MEDIAN(IF('Percent Responses Cleaned'!$C$4:$C$375=$E63,INDEX('Percent Responses Cleaned'!$D$4:$BV$375,,MATCH($B63,'Percent Responses Cleaned'!$D$3:$BV$3,0))))} -> 0 | G63: Admin / other | H63: Other activities
B64: Q9.1_8 | C64: What is the % mix of time that you spend on these activities below in an average 40 hour work week, excluding lunch? (e.g. 10% of a week is 4 hours) | D64: Breaks | E64: MTS Pod | F64: {=MEDIAN(IF('Percent Responses Cleaned'!$C$4:$C$375=$E64,INDEX('Percent Responses Cleaned'!$D$4:$BV$375,,MATCH($B64,'Percent Responses Cleaned'!$D$3:$BV$3,0))))} -> 10 | G64: Other activities | H64: Other activities
B65: Q9.1_6 | C65: What is the % mix of time that you spend on these activities below in an average 40 hour work week, excluding lunch? (e.g. 10% of a week is 4 hours) | D65: Meetings (e.g. team meetings, townhalls) | E65: MTS Pod | F65: {=MEDIAN(IF('Percent Responses Cleaned'!$C$4:$C$375=$E65,INDEX('Percent Responses Cleaned'!$D$4:$BV$375,,MATCH($B65,'Percent Responses Cleaned'!$D$3:$BV$3,0))))} -> 5 | G65: Knowledge and skill building | H65: Other activities
B66: Q9.1_9 | C66: What is the % mix of time that you spend on these activities below in an average 40 hour work week, excluding lunch? (e.g. 10% of a week is 4 hours) | D66: Other activities (specify activity and provide details on the following page) | E66: MTS Pod | F66: {=MEDIAN(IF('Percent Responses Cleaned'!$C$4:$C$375=$E66,INDEX('Percent Responses Cleaned'!$D$4:$BV$375,,MATCH($B66,'Percent Responses Cleaned'!$D$3:$BV$3,0))))} -> 0 | G66: Other activities | H66: Other activities
B67: Q9.1_1 | C67: What is the % mix of time that you spend on these activities below in an average 40 hour work week, excluding lunch? (e.g. 10% of a week is 4 hours) | D67: Build Request Lead (new build, duplicate shop, etc..) | E67: MTS Pod | F67: {=MEDIAN(IF('Percent Responses Cleaned'!$C$4:$C$375=$E67,INDEX('Percent Responses Cleaned'!$D$4:$BV$375,,MATCH($B67,'Percent Responses Cleaned'!$D$3:$BV$3,0))))} -> 40 | G67: Customer (store) onboarding & feature upgrades | H67: Shop creation
... B73: Q9.1_15 | C73: What is the % mix of time that you spend on these activities below in an average 40 hour work week, excluding lunch? (e.g. 10% of a week is 4 hours) | D73: Issue Resolution / Q& A | E73: MTS Pod | F73: {=MEDIAN(IF('Percent Responses Cleaned'!$C$4:$C$375=$E73,INDEX('Percent Responses Cleaned'!$D$4:$BV$375,,MATCH($B73,'Percent Responses Cleaned'!$D$3:$BV$3,0))))} -> 5 | G73: Technical issue resolution | H73: Shop creation support activities

Sheet Cleaned Data >>>

Sheet Percent Responses Cleaned
B2: Response ID | C2: Select your role | D2: What is the % mix of time that you spend on these categories of contact below in an average 40 hour work week, excluding lunch? (e.g. 10% of a week is 4 hours) - Order status/tracking | E2: What is the % mix of time that you spend on these categories of contact below in an average 40 hour work week, excluding lunch? (e.g. 10% of a week is 4 hours) - New order/ quote | F2: What is the % mix of time that you spend on these categories of contact below in an average 40 hour work week, excluding lunch? (e.g. 10% of a week is 4 hours) - Cancellation | G2: What is the % mix of time that you spend on these categories of contact below in an average 40 hour work week, excluding lunch? (e.g. 10% of a week is 4 hours) - Replacements & returns | H2: What is the % mix of time that you spend on these categories of contact below in an average 40 hour work week, excluding lunch? (e.g. 10% of a week is 4 hours) - Order edit/change | I2: What is the % mix of time that you spend on these categories of contact below in an average 40 hour work week, excluding lunch? (e.g. 10% of a week is 4 hours) - Website/ technical support | J2: What is the % mix of time that you spend on these categories of contact below in an average 40 hour work week, excluding lunch? (e.g. 10% of a week is 4 hours) - Sizing issues | K2: What is the % mix of time that you spend on these categories of contact below in an average 40 hour work week, excluding lunch? (e.g. 10% of a week is 4 hours) - Refund request | L2: What is the % mix of time that you spend on these categories of contact below in an average 40 hour work week, excluding lunch? (e.g. 10% of a week is 4 hours) - Missed order deadline | M2: What is the % mix of time that you spend on these categories of contact below in an average 40 hour work week, excluding lunch? (e.g. 10% of a week is 4 hours) - Other customer inquiries | N2: What is the % mix of time that you spend on these categories of contact below in an average 40 hour work week, excluding lunch? (e.g. 10% of a week is 4 hours) - Internal communications (e.g. email/ calls to FSPs) | O2: What is the % mix of time that you spend on these categories of contact below in an average 40 hour work week, excluding lunch? (e.g. 10% of a week is 4 hours) - External communications (e.g. emails/ calls to vendors) | P2: What is the % mix of time that you spend on these categories of contact below in an average 40 hour work week, excluding lunch? (e.g. 10% of a week is 4 hours) - Meetings (e.g. team meetings, townhalls) | Q2: What is the % mix of time that you spend on these categories of contact below in an average 40 hour work week, excluding lunch? (e.g. 10% of a week is 4 hours) - Breaks | R2: What is the % mix of time that you spend on these categories of contact below in an average 40 hour work week, excluding lunch? (e.g. 10% of a week is 4 hours) - Other activities (specify activity and provide details on the following page) | S2: What is the % mix of time that you spend on these activities below in an average 40 hour work week, excluding lunch? (e.g. 10% of a week is 4 hours) - Pushing Carts | T2: What is the % mix of time that you spend on these activities below in an average 40 hour work week, excluding lunch? (e.g. 10% of a week is 4 hours) - MTS Changes | U2: What is the % mix of time that you spend on these activities below in an average 40 hour work week, excluding lunch? (e.g. 10% of a week is 4 hours) - Consolidating MTS shops | V2: What is the % mix of time that you spend on these activities below in an average 40 hour work week, excluding lunch? (e.g. 10% of a week is 4 hours) - MTS Credits | W2: What is the % mix of time that you spend on these activities below in an average 40 hour work week, excluding lunch? (e.g. 10% of a week is 4 hours) - Core Order Changes | X2: What is the % mix of time that you spend on these activities below in an average 40 hour work week, excluding lunch? (e.g. 10% of a week is 4 hours) - Working on Open orders | Y2: What is the % mix of time that you spend on these activities below in an average 40 hour work week, excluding lunch? (e.g. 10% of a week is 4 hours) - Reactive Order Tracking/ Status | Z2: What is the % mix of time that you spend on these activities below in an average 40 hour work week, excluding lunch? (e.g. 10% of a week is 4 hours) - AP/AR | AA2: What is the % mix of time that you spend on these activities below in an average 40 hour work week, excluding lunch? (e.g. 10% of a week is 4 hours) - Invoicing Questions | AB2: What is the % mix of time that you spend on these activities below in an average 40 hour work week, excluding lunch? (e.g. 10% of a week is 4 hours) - Label Requests (Freight) | AC2: What is the % mix of time that you spend on these activities below in an average 40 hour work week, excluding lunch? (e.g. 10% of a week is 4 hours) - Processing Returns/Replacements | AD2: What is the % mix of time that you spend on these activities below in an average 40 hour work week, excluding lunch? (e.g. 10% of a week is 4 hours) - Processing Comp Goods | AE2: What is the % mix of time that you spend on these activities below in an average 40 hour work week, excluding lunch? (e.g. 10% of a week is 4 hours) - Internal communications (e.g. email/ calls to FSPs) | AF2: What is the % mix of time that you spend on these activities below in an average 40 hour work week, excluding lunch? (e.g. 10% of a week is 4 hours) - Meetings (e.g. team meetings, townhalls) | AG2: What is the % mix of time that you spend on these activities below in an average 40 hour work week, excluding lunch? (e.g. 10% of a week is 4 hours) - Breaks | AH2: What is the % mix of time that you spend on these activities below in an average 40 hour work week, excluding lunch? (e.g. 10% of a week is 4 hours) - Other activities (specify activity and provide details on the following page) | AI2: What is the % mix of time that you spend on these activities below in an average 40 hour work week, excluding lunch? (e.g. 10% of a week is 4 hours) - Quote Cart | AJ2: What is the % mix of time that you spend on these activities below in an average 40 hour work week, excluding lunch? (e.g. 10% of a week is 4 hours) - Fact Finding | AK2: What is the % mix of time that you spend on these activities below in an average 40 hour work week, excluding lunch? (e.g. 10% of a week is 4 hours) - Purchase Order | AL2: What is the % mix of time that you spend on these activities below in an average 40 hour work week, excluding lunch? (e.g. 10% of a week is 4 hours) - Content Creation | AM2: What is the % mix of time that you spend on these activities below in an average 40 hour work week, excluding lunch? (e.g. 10% of a week is 4 hours) - Rewards agreement | AN2: What is the % mix of time that you spend on these activities below in an average 40 hour work week, excluding lunch? (e.g. 10% of a week is 4 hours) - Return/ Replacement | AO2: What is the % mix of time that you spend on these activities below in an average 40 hour work week, excluding lunch? (e.g. 10% of a week is 4 hours) - Update contact info | AP2: What is the % mix of time that you spend on these activities below in an average 40 hour work week, excluding lunch? (e.g. 10% of a week is 4 hours) - Freight Quote | AQ2: What is the % mix of time that you spend on these activities below in an average 40 hour work week, excluding lunch? (e.g. 10% of a week is 4 hours) - Other supporting activities (Adidas, BSN Construction, Corporate, bid, Training) | AR2: What is the % mix of time that you spend on these activities below in an average 40 hour work week, excluding lunch? (e.g. 10% of a week is 4 hours) - Internal communications (e.g. email/ calls to FSPs) | AS2: What is the % mix of time that you spend on these activities below in an average 40 hour work week, excluding lunch? (e.g. 10% of a week is 4 hours) - External communications (e.g. emails/ calls to vendors) | AT2: What is the % mix of time that you spend on these activities below in an average 40 hour work week, excluding lunch? (e.g. 10% of a week is 4 hours) - Meetings (e.g. team meetings, townhalls) | AU2: What is the % mix of time that you spend on these activities below in an average 40 hour work week, excluding lunch? (e.g. 10% of a week is 4 hours) - Other activities (specify activity and provide details on the following page) | AV2: What is the % mix of time that you spend on these activities below in an average 40 hour work week, excluding lunch? (e.g. 10% of a week is 4 hours) - New Cases | AW2: What is the % mix of time that you spend on these activities below in an average 40 hour work week, excluding lunch? (e.g. 10% of a week is 4 hours) - Order Entry (e.g. creating comp carts, applying coupons from Nike, UA etc.) | AX2: What is the % mix of time that you spend on these activities below in an average 40 hour work week, excluding lunch? (e.g. 10% of a week is 4 hours) - Managing stocking issues | AY2: What is the % mix of time that you spend on these activities below in an average 40 hour work week, excluding lunch? (e.g. 10% of a week is 4 hours) - Internal communication (Emails/ Calls to FSPs) | AZ2: What is the % mix of time that you spend on these activities below in an average 40 hour work week, excluding lunch? (e.g. 10% of a week is 4 hours) - External communications (e.g. emails/ calls to vendors) | BA2: What is the % mix of time that you spend on these activities below in an average 40 hour work week, excluding lunch? (e.g. 10% of a week is 4 hours) - Meetings (e.g. team meetings, townhalls) | BB2: What is the % mix of time that you spend on these activities below in an average 40 hour work week, excluding lunch? (e.g. 10% of a week is 4 hours) - Order Management (tracking order) | BC2: What is the % mix of time that you spend on these activities below in an average 40 hour work week, excluding lunch? (e.g. 10% of a week is 4 hours) - Breaks | BD2: What is the % mix of time that you spend on these activities below in an average 40 hour work week, excluding lunch? (e.g. 10% of a week is 4 hours) - Other activities (specify activity and provide details on the following page) | BE2: What is the % mix of time that you spend on these activities below in an average 40 hour work week, excluding lunch? (e.g. 10% of a week is 4 hours) - New Cases | BF2: What is the % mix of time that you spend on these activities below in an average 40 hour work week, excluding lunch? (e.g. 10% of a week is 4 hours) - Order entry (ZREP/RE Entry) | BG2: What is the % mix of time that you spend on these activities below in an average 40 hour work week, excluding lunch? (e.g. 10% of a week is 4 hours) - Order management (Status review of ZREPs/ RE/Original Order Open) | BH2: What is the % mix of time that you spend on these activities below in an average 40 hour work week, excluding lunch? (e.g. 10% of a week is 4 hours) - Internal communication (Emails/ Calls to FSPs) | BI2: What is the % mix of time that you spend on these activities below in an average 40 hour work week, excluding lunch? (e.g. 10% of a week is 4 hours) - External communications (e.g. emails/ calls to vendors) | BJ2: What is the % mix of time that you spend on these activities below in an average 40 hour work week, excluding lunch? (e.g. 10% of a week is 4 hours) - Meetings (e.g. team meetings, townhalls) | BK2: What is the % mix of time that you spend on these activities below in an average 40 hour work week, excluding lunch? (e.g. 10% of a week is 4 hours) - Breaks | BL2: What is the % mix of time that you spend on these activities below in an average 40 hour work week, excluding lunch? (e.g. 10% of a week is 4 hours) - Other activities (specify activity and provide details on the following page) | BM2: What is the % mix of time that you spend on these activities below in an average 40 hour work week, excluding lunch? (e.g. 10% of a week is 4 hours) - Build Request Lead (new build, duplicate shop, etc..) | BN2: What is the % mix of time that you spend on these activities below in an average 40 hour work week, excluding lunch? (e.g. 10% of a week is 4 hours) - Shop Edits | BO2: What is the % mix of time that you spend on these activities below in an average 40 hour work week, excluding lunch? (e.g. 10% of a week is 4 hours) - Art Submission | BP2: What is the % mix of time that you spend on these activities below in an average 40 hour work week, excluding lunch? (e.g. 10% of a week is 4 hours) - Internal communication (Emails/ Calls to FSPs) | BQ2: What is the % mix of time that you spend on these activities below in an average 40 hour work week, excluding lunch? (e.g. 10% of a week is 4 hours) - External communications (e.g. emails/ calls to vendors) | BR2: What is the % mix of time that you spend on these activities below in an average 40 hour work week, excluding lunch? (e.g. 10% of a week is 4 hours) - Meetings (e.g. team meetings, townhalls) | BS2: What is the % mix of time that you spend on these activities below in an average 40 hour work week, excluding lunch? (e.g. 10% of a week is 4 hours) - Shop Launch | BT2: What is the % mix of time that you spend on these activities below in an average 40 hour work week, excluding lunch? (e.g. 10% of a week is 4 hours) - Issue Resolution / Q& A | BU2: What is the % mix of time that you spend on these activities below in an average 40 hour work week, excluding lunch? (e.g. 10% of a week is 4 hours) - Breaks | BV2: What is the % mix of time that you spend on these activities below in an average 40 hour work week, excluding lunch? (e.g. 10% of a week is 4 hours) - Other activities (specify activity and provide details on the following page)
B3: Response ID | C3: Q1.2 | D3: Q2.1_1 | E3: Q2.1_2 | F3: Q2.1_3 | G3: Q2.1_4 | H3: Q2.1_5 | I3: Q2.1_6 | J3: Q2.1_7 | K3: Q2.1_8 | L3: Q2.1_9 | M3: Q2.1_10 | N3: Q2.1_11 | O3: Q2.1_12 | P3: Q2.1_13 | Q3: Q2.1_15 | R3: Q2.1_16 | S3: Q4.1_1 | T3: Q4.1_2 | U3: Q4.1_3 | V3: Q4.1_4 | W3: Q4.1_5 | X3: Q4.1_6 | Y3: Q4.1_7 | Z3: Q4.1_8 | AA3: Q4.1_9 | AB3: Q4.1_10 | AC3: Q4.1_11 | AD3: Q4.1_12 | AE3: Q4.1_13 | AF3: Q4.1_14 | AG3: Q4.1_15 | AH3: Q4.1_16 | AI3: Q6.1_1 | AJ3: Q6.1_2 | AK3: Q6.1_3 | AL3: Q6.1_4 | AM3: Q6.1_5 | AN3: Q6.1_6 | AO3: Q6.1_7 | AP3: Q6.1_8 | AQ3: Q6.1_9 | AR3: Q6.1_10 | AS3: Q6.1_11 | AT3: Q6.1_12 | AU3: Q6.1_13 | AV3: Q7.1_1 | AW3: Q7.1_2 | AX3: Q7.1_3 | AY3: Q7.1_4 | AZ3: Q7.1_5 | BA3: Q7.1_6 | BB3: Q7.1_7 | BC3: Q7.1_8 | BD3: Q7.1_9 | BE3: Q8.1_1 | BF3: Q8.1_2 | BG3: Q8.1_3 | BH3: Q8.1_4 | BI3: Q8.1_5 | BJ3: Q8.1_6 | BK3: Q8.1_8 | BL3: Q8.1_9 | BM3: Q9.1_1 | BN3: Q9.1_2 | BO3: Q9.1_3 | BP3: Q9.1_4 | BQ3: Q9.1_5 | BR3: Q9.1_6 | BS3: Q9.1_14 | BT3: Q9.1_15 | BU3: Q9.1_8 | BV3: Q9.1_9
B4: R_1AnVoRS4iYqJ2lX | C4: Comp Pod | AV4: 10 | AW4: 10 | AX4: 25 | AY4: 25 | AZ4: 0 | BA4: 5 | BB4: 10 | BC4: 5 | BD4: 10
B5: R_3VedKTzRycYgliq | C5: Comp Pod | AV5: 15 | AW5: 5 | AX5: 20 | AY5: 10 | AZ5: 15 | BA5: 5 | BB5: 15 | BC5: 10 | BD5: 5
B6: R_1bW4eKBmrU1QZwy | C6: Comp Pod | AV6: 15 | AW6: 15 | AX6: 12 | AY6: 18 | AZ6: 5 | BA6: 5 | BB6: 20 | BC6: 10 | BD6: 0
B7: R_1waaneiXKjmxunc | C7: Comp Pod | AV7: 20 | AW7: 30 | AX7: 40 | AY7: 2 | AZ7: 2 | BA7: 2 | BB7: 2 | BC7: 2 | BD7: 0
B8: R_1QWwIT3QRYtnEYm | C8: Comp Pod | AV8: 10 | AW8: 15 | AX8: 25 | AY8: 10 | AZ8: 0 | BA8: 0 | BB8: 30 | BC8: 10 | BD8: 0
B9: R_37gjrYL6f2ot49X | C9: Comp Pod | AV9: 10 | AW9: 10 | AX9: 30 | AY9: 30 | AZ9: 0 | BA9: 3 | BB9: 10 | BC9: 4 | BD9: 3
B10: R_6h58CTLCbXhPX3c | C10: Comp Pod | AV10: 10 | AW10: 10 | AX10: 20 | AY10: 10 | AZ10: 10 | BA10: 10 | BB10: 10 | BC10: 10 | BD10: 10
B11: R_3Ic6xDcJtKZQw0k | C11: Comp Pod | AV11: 10 | AW11: 12 | AX11: 16 | AY11: 11 | AZ11: 10 | BA11: 10 | BB11: 11 | BC11: 10 | BD11: 10
B12: R_3iD9cPclavvXDyv | C12: Comp Pod | AV12: 0 | AW12: 60 | AX12: 10 | AY12: 0 | AZ12: 0 | BA12: 0 | BB12: 20 | BC12: 10 | BD12: 0
B13: R_6WTMCkJWLbvEUYz | C13: Comp Pod | AV13: 15 | AW13: 15 | AX13: 15 | AY13: 5 | AZ13: 10 | BA13: 5 | BB13: 25 | BC13: 10 | BD13: 0
B14: R_6oEXQdRTc0yrRqT | C14: Comp Pod | AV14: 10 | AW14: 10 | AX14: 20 | AY14: 10 | AZ14: 10 | BA14: 10 | BB14: 10 | BC14: 10 | BD14: 10
B15: R_108Oxkf7Y3MVS1z | C15: Comp Pod | AV15: 10 | AW15: 10 | AX15: 20 | AY15: 10 | AZ15: 10 | BA15: 5 | BB15: 20 | BC15: 10 | BD15: 5
... B30: R_3sjfhRoBPU1JbJ4 | C30: Comp Pod | AV30: 10 | AW30: 15 | AX30: 20 | AY30: 20 | AZ30: 5 | BA30: 5 | BB30: 10 | BC30: 10 | BD30: 5
B31: R_1eliuDNduR3ISzx | C31: Customer Care | D31: 10 | E31: 0 | F31: 10 | G31: 0 | H31: 10 | I31: 10 | J31: 0 | K31: 10 | L31: 0 | M31: 10 | N31: 10 | O31: 10 | P31: 10 | Q31: 0 | R31: 10
B32: R_61vzskVuPNAgQK5 | C32: Customer Care | D32: 10 | E32: 5 | F32: 10 | G32: 25 | H32: 10 | I32: 2 | J32: 10 | K32: 10 | L32: 5 | M32: 0 | N32: 1 | O32: 1 | P32: 1 | Q32: 10 | R32: 0
B33: R_1OjP2GJIrX8N4BQ | C33: Customer Care | D33: 0 | E33: 0 | F33: 0 | G33: 0 | H33: 0 | I33: 0 | J33: 0 | K33: 0 | L33: 0 | M33: 0 | N33: 30 | O33: 0 | P33: 20 | Q33: 5 | R33: 45
B34: R_1WPGtgKOrvrC4Kv | C34: Customer Care | D34: 0 | E34: 0 | F34: 0 | G34: 0 | H34: 0 | I34: 0 | J34: 0 | K34: 0 | L34: 0 | M34: 0 | N34: 20 | O34: 0 | P34: 20 | Q34: 10 | R34: 50
B35: R_1PShqTPaTDHUhpu | C35: Customer Care | D35: 50 | E35: 1 | F35: 1 | G35: 30 | H35: 2 | I35: 2 | J35: 2 | K35: 1 | L35: 0 | M35: 0 | N35: 1 | O35: 0 | P35: 0 | Q35: 10 | R35: 0
B36: R_7ONClr7GQGGcEZI | C36: Customer Care | D36: 1 | E36: 0 | F36: 0 | G36: 80 | H36: 0 | I36: 0 | J36: 1 | K36: 10 | L36: 2 | M36: 2 | N36: 2 | O36: 1 | P36: 0 | Q36: 1 | R36: 0
B37: R_52FnavcH7KQFN1n | C37: Customer Care | D37: 10 | E37: 0 | F37: 3 | G37: 5 | H37: 5 | I37: 0 | J37: 10 | K37: 10 | L37: 0 | M37: 10 | N37: 10 | O37: 10 | P37: 6 | Q37: 6 | R37: 15
B38: R_5Rx9hre9EpRvtCX | C38: Customer Care | D38: 8 | E38: 10 | F38: 5 | G38: 15 | H38: 7 | I38: 5 | J38: 10 | K38: 10 | L38: 10 | M38: 3 | N38: 3 | O38: 1 | P38: 3 | Q38: 10 | R38: 0
B39: R_3iwNdnjoZ5g49X7 | C39: Customer Care | D39: 10 | E39: 5 | F39: 1 | G39: 10 | H39: 10 | I39: 1 | J39: 20 | K39: 10 | L39: 10 | M39: 5 | N39: 5 | O39: 2.7 | P39: 0.3 | Q39: 10 | R39: 0
B40: R_3PdOEVwkLoYaMPU | C40: Customer Care | D40: 10 | E40: 10 | F40: 10 | G40: 10 | H40: 10 | I40: 5 | J40: 10 | K40: 10 | L40: 5 | M40: 5 | N40: 5 | O40: 5 | P40: 2 | Q40: 3 | R40: 0
B41: R_5QtbKXJukCpNkM8 | C41: Customer Care | D41: 10 | E41: 10 | F41: 10 | G41: 10 | H41: 3 | I41: 1 | J41: 10 | K41: 10 | L41: 10 | M41: 10 | N41: 5 | O41: 5 | P41: 1 | Q41: 5 | R41: 0
B42: R_54N09DTwuY2ydcZ | C42: Customer Care | D42: 10 | E42: 5 | F42: 10 | G42: 10 | H42: 10 | I42: 5 | J42: 10 | K42: 10 | L42: 1 | M42: 10 | N42: 5 | O42: 2 | P42: 2 | Q42: 10 | R42: 0
... B54: R_6MTchihCp3gR3y2 | C54: Customer Care | D54: 15 | E54: 2 | F54: 2 | G54: 12 | H54: 10 | I54: 3 | J54: 15 | K54: 10 | L54: 5 | M54: 4 | N54: 1 | O54: 20 | P54: 1 | Q54: 0 | R54: 0
B55: R_7CCEJasYyxv9dyz | C55: MTS Pod | BM55: 40 | BN55: 20 | BO55: 10 | BP55: 0 | BQ55: 0 | BR55: 10 | BS55: 10 | BT55: 0 | BU55: 10 | BV55: 0
B56: R_6xJHvtzFlKFoW43 | C56: MTS Pod | BM56: 15 | BN56: 10 | BO56: 1 | BP56: 5 | BQ56: 5 | BR56: 10 | BS56: 5 | BT56: 20 | BU56: 15 | BV56: 14
B57: R_7e8SaO67BnEUoUj | C57: MTS Pod | BM57: 50 | BN57: 30 | BO57: 5 | BP57: 5 | BQ57: 0 | BR57: 0 | BS57: 5 | BT57: 0 | BU57: 5 | BV57: 0
B58: R_6EExy9tcQhR60ph | C58: MTS Pod | BM58: 12 | BN58: 12 | BO58: 12 | BP58: 12 | BQ58: 12 | BR58: 5 | BS58: 10 | BT58: 12 | BU58: 13 | BV58: 0
B59: R_7T8FDek0WB6rVu1 | C59: MTS Pod | BM59: 0 | BN59: 0 | BO59: 0 | BP59: 20 | BQ59: 25 | BR59: 25 | BS59: 0 | BT59: 20 | BU59: 10 | BV59: 0
B60: R_5pWB8atihrYTkdA | C60: MTS Pod | BM60: 40 | BN60: 35 | BO60: 2 | BP60: 3 | BQ60: 0 | BR60: 0 | BS60: 5 | BT60: 5 | BU60: 10 | BV60: 0
B61: R_1rP2lpYGjUI95Gp | C61: MTS Pod | BM61: 45 | BN61: 15 | BO61: 3 | BP61: 10 | BQ61: 5 | BR61: 2 | BS61: 5 | BT61: 5 | BU61: 10 | BV61: 0
B62: R_7krvQJpqUtADD6p | C62: MTS Pod | BM62: 25 | BN62: 10 | BO62: 5 | BP62: 10 | BQ62: 15 | BR62: 3 | BS62: 7 | BT62: 10 | BU62: 10 | BV62: 5
B63: R_6ylpGG7ycEKhxjr | C63: MTS Pod | BM63: 40 | BN63: 15 | BO63: 2 | BP63: 5 | BQ63: 5 | BR63: 2 | BS63: 15 | BT63: 5 | BU63: 10 | BV63: 1
B64: R_617EAeT1VygZsSI | C64: MTS Pod | BM64: 50 | BN64: 20 | BO64: 5 | BP64: 5 | BQ64: 0 | BR64: 5 | BS64: 5 | BT64: 0 | BU64: 10 | BV64: 0
B65: R_6hxWHLg5wuBGHlf | C65: MTS Pod | BM65: 20 | BN65: 25 | BO65: 5 | BP65: 10 | BQ65: 5 | BR65: 5 | BS65: 5 | BT65: 15 | BU65: 10 | BV65: 0
B66: R_5FhCEvagOpLlKOl | C66: MTS Pod | BM66: 40 | BN66: 25 | BO66: 5 | BP66: 0 | BQ66: 0 | BR66: 5 | BS66: 20 | BT66: 0 | BU66: 5 | BV66: 0
... B79: R_7ZCGcc4qKt7gyI6 | C79: MTS Pod | BM79: 50 | BN79: 20 | BO79: 0 | BP79: 0 | BQ79: 10 | BR79: 0 | BS79: 10 | BT79: 10 | BU79: 0 | BV79: 0
B80: R_59cue4jOO91w1tx | C80: R+R Pod | BE80: 26 | BF80: 15 | BG80: 12 | BH80: 12 | BI80: 15 | BJ80: 5 | BK80: 5 | BL80: 10
B81: R_5NhXGOXEetA7QZj | C81: R+R Pod | BE81: 10 | BF81: 20 | BG81: 20 | BH81: 10 | BI81: 15 | BJ81: 10 | BK81: 10 | BL81: 5
B82: R_7WYlKEHbVy6Gklw | C82: R+R Pod | BE82: 25 | BF82: 25 | BG82: 20 | BH82: 10 | BI82: 9 | BJ82: 1 | BK82: 10 | BL82: 0
B83: R_3p7vEkGrFbzevcd | C83: R+R Pod | BE83: 30 | BF83: 20 | BG83: 12.5 | BH83: 5 | BI83: 15 | BJ83: 2.5 | BK83: 10 | BL83: 5
B84: R_70MpwSyolERNr6K | C84: R+R Pod | BE84: 20 | BF84: 25 | BG84: 10 | BH84: 25 | BI84: 5 | BJ84: 5 | BK84: 10 | BL84: 0
B85: R_5pRVuM31AmqIY7y | C85: R+R Pod | BE85: 15 | BF85: 20 | BG85: 46 | BH85: 6 | BI85: 2 | BJ85: 3 | BK85: 8 | BL85: 0
B86: R_6H05a5iYr9e1RDe | C86: R+R Pod | BE86: 20 | BF86: 12.5 | BG86: 12.5 | BH86: 20 | BI86: 10 | BJ86: 5 | BK86: 5 | BL86: 15
B87: R_3xPL3dKr30K9iN0 | C87: R+R Pod | BE87: 30 | BF87: 15 | BG87: 20 | BH87: 10 | BI87: 10 | BJ87: 5 | BK87: 10 | BL87: 0
B88: R_6Rdu9POySeJ7GWj | C88: R+R Pod | BE88: 30 | BF88: 25 | BG88: 15 | BH88: 10 | BI88: 8 | BJ88: 2 | BK88: 10 | BL88: 0
B89: R_5shQQ5mZwIZKO1s | C89: R+R Pod | BE89: 25 | BF89: 25 | BG89: 25 | BH89: 5 | BI89: 5 | BJ89: 5 | BK89: 10 | BL89: 0
B90: R_1njBxwd45ml5anf | C90: R+R Pod | BE90: 25 | BF90: 20 | BG90: 30 | BH90: 10 | BI90: 10 | BJ90: 4 | BK90: 1 | BL90: 0
B91: R_1iwNLHjuRI0qCxb | C91: R+R Pod | BE91: 20 | BF91: 10 | BG91: 20 | BH91: 15 | BI91: 15 | BJ91: 5 | BK91: 10 | BL91: 5
... B110: R_6jN80fio5ZqZQzh | C110: R+R Pod | BE110: 15 | BF110: 30 | BG110: 20 | BH110: 10 | BI110: 10 | BJ110: 10 | BK110: 5 | BL110: 0
B111: R_6n0LsNjfNThAuXh | C111: SSR | S111: 0 | T111: 5 | U111: 0 | V111: 0 | W111: 0 | X111: 40 | Y111: 20 | Z111: 5 | AA111: 5 | AB111: 0 | AC111: 5 | AD111: 0 | AE111: 20 | AF111: 0 | AG111: 0 | AH111: 0
B112: R_3OiTOWeVyYUdppc | C112: SSR | S112: 1 | T112: 5 | U112: 2 | V112: 5 | W112: 10 | X112: 30 | Y112: 15 | Z112: 3 | AA112: 1 | AB112: 1 | AC112: 1 | AD112: 0 | AE112: 15 | AF112: 1 | AG112: 10 | AH112: 0
B113: R_6OFiuMwv2yqcul3 | C113: SSR | S113: 0 | T113: 10 | U113: 5 | V113: 0 | W113: 10 | X113: 30 | Y113: 10 | Z113: 5 | AA113: 10 | AB113: 0 | AC113: 10 | AD113: 0 | AE113: 0 | AF113: 0 | AG113: 10 | AH113: 0
B114: R_50Fmr5YYd0GdfMZ | C114: SSR | S114: 1 | T114: 5 | U114: 10 | V114: 0 | W114: 10 | X114: 50 | Y114: 5 | Z114: 0 | AA114: 5 | AB114: 2 | AC114: 0 | AD114: 0 | AE114: 2 | AF114: 0 | AG114: 10 | AH114: 0
B115: R_5gXCv68kMP0o3EU | C115: SSR | S115: 5 | T115: 10 | U115: 5 | V115: 0 | W115: 15 | X115: 35 | Y115: 5 | Z115: 5 | AA115: 5 | AB115: 0 | AC115: 0 | AD115: 0 | AE115: 5 | AF115: 0 | AG115: 10 | AH115: 0
B116: R_1P7p4dr02LqvkRJ | C116: SSR | S116: 0 | T116: 5 | U116: 5 | V116: 5 | W116: 5 | X116: 50 | Y116: 10 | Z116: 1 | AA116: 2 | AB116: 2 | AC116: 7 | AD116: 0 | AE116: 5 | AF116: 1 | AG116: 2 | AH116: 0
B117: R_1DGOFFlUeBsr8sJ | C117: SSR | S117: 0 | T117: 2 | U117: 2 | V117: 0 | W117: 15 | X117: 20 | Y117: 25 | Z117: 2 | AA117: 2 | AB117: 1 | AC117: 1 | AD117: 0 | AE117: 20 | AF117: 0 | AG117: 10 | AH117: 0
B118: R_7NVYorVMNptooiG | C118: SSR | S118: 5 | T118: 16 | U118: 21 | V118: 2 | W118: 8 | X118: 8 | Y118: 7 | Z118: 2 | AA118: 2 | AB118: 2 | AC118: 5 | AD118: 2 | AE118: 7 | AF118: 3 | AG118: 10 | AH118: 0
B119: R_6dus9DtwrjVHhlc | C119: SSR | S119: 1 | T119: 10 | U119: 10 | V119: 1 | W119: 10 | X119: 25 | Y119: 25 | Z119: 2 | AA119: 2 | AB119: 1 | AC119: 1 | AD119: 0 | AE119: 1 | AF119: 1 | AG119: 10 | AH119: 0
B120: R_7PcR9Nq3W31XjSx | C120: SSR | S120: 2 | T120: 4 | U120: 2 | V120: 4 | W120: 15 | X120: 45 | Y120: 10 | Z120: 0 | AA120: 2 | AB120: 1 | AC120: 1 | AD120: 0 | AE120: 4 | AF120: 0 | AG120: 10 | AH120: 0
B121: R_1zB0erNM8SQpwwe | C121: SSR | S121: 0.5 | T121: 1 | U121: 0.5 | V121: 0.5 | W121: 5 | X121: 50 | Y121: 10 | Z121: 1 | AA121: 1 | AB121: 0.5 | AC121: 5 | AD121: 0 | AE121: 10 | AF121: 1 | AG121: 10 | AH121: 4
B122: R_5RVLGkN17reRB2E | C122: SSR | S122: 0 | T122: 3 | U122: 0 | V122: 3 | W122: 4 | X122: 30 | Y122: 20 | Z122: 5 | AA122: 3 | AB122: 2 | AC122: 5 | AD122: 0 | AE122: 10 | AF122: 5 | AG122: 10 | AH122: 0
... B255: R_3v65T8Hm7cxfWB6 | C255: SSR | S255: 0 | T255: 10 | U255: 0 | V255: 2 | W255: 2 | X255: 10 | Y255: 25 | Z255: 2 | AA255: 5 | AB255: 0 | AC255: 10 | AD255: 2 | AE255: 10 | AF255: 2 | AG255: 10 | AH255: 10
B256: R_10kSt027CYOWXJG | C256: TM | AI256: 15 | AJ256: 30 | AK256: 5 | AL256: 5 | AM256: 2 | AN256: 5 | AO256: 3 | AP256: 0 | AQ256: 10 | AR256: 5 | AS256: 10 | AT256: 10 | AU256: 0
B257: R_6SrYuf3lGeG7eQp | C257: TM | AI257: 60 | AJ257: 30 | AK257: 0 | AL257: 0 | AM257: 5 | AN257: 0 | AO257: 0 | AP257: 0 | AQ257: 0 | AR257: 5 | AS257: 0 | AT257: 0 | AU257: 0
B258: R_6R9gp6sJYpXXrNf | C258: TM | AI258: 40 | AJ258: 40 | AK258: 0 | AL258: 5 | AM258: 0 | AN258: 0 | AO258: 0 | AP258: 0 | AQ258: 0 | AR258: 5 | AS258: 5 | AT258: 5 | AU258: 0
B259: R_1j37HFdJu1TAYWA | C259: TM | AI259: 50 | AJ259: 33 | AK259: 1 | AL259: 13 | AM259: 2 | AN259: 0 | AO259: 0 | AP259: 1 | AQ259: 0 | AR259: 0 | AS259: 0 | AT259: 0 | AU259: 0
B260: R_5f6B8JYEmGMQDFT | C260: TM | AI260: 35 | AJ260: 61 | AK260: 0 | AL260: 1 | AM260: 1 | AN260: 0 | AO260: 0 | AP260: 1 | AQ260: 0 | AR260: 0 | AS260: 0 | AT260: 1 | AU260: 0
B261: R_5k2Q9YuWFdAGUxz | C261: TM | AI261: 40 | AJ261: 15 | AK261: 15 | AL261: 4 | AM261: 1 | AN261: 0.5 | AO261: 0.5 | AP261: 3.5 | AQ261: 0.5 | AR261: 11 | AS261: 8 | AT261: 1 | AU261: 0
B262: R_3g5Aq0FI9ZpfWcH | C262: TM | AI262: 25 | AJ262: 25 | AK262: 5 | AL262: 10 | AM262: 0 | AN262: 0 | AO262: 0 | AP262: 10 | AQ262: 0 | AR262: 10 | AS262: 10 | AT262: 5 | AU262: 0
B263: R_5m3AcMZ3rSKmkmZ | C263: TM | AI263: 20 | AJ263: 50 | AK263: 5 | AL263: 0 | AM263: 4 | AN263: 0 | AO263: 0 | AP263: 1 | AQ263: 3 | AR263: 2 | AS263: 10 | AT263: 5 | AU263: 0
B264: R_78JakWokStUDU0v | C264: TM | AI264: 28 | AJ264: 50 | AK264: 0 | AL264: 0 | AM264: 1 | AN264: 0 | AO264: 0 | AP264: 1 | AQ264: 0 | AR264: 10 | AS264: 5 | AT264: 5 | AU264: 0
B265: R_6o5BrtsLUMAuMON | C265: TM | AI265: 32 | AJ265: 20 | AK265: 1 | AL265: 2 | AM265: 1 | AN265: 1 | AO265: 0 | AP265: 1 | AQ265: 1 | AR265: 20 | AS265: 20 | AT265: 1 | AU265: 0
B266: R_30OhPL2Ln8TrQfD | C266: TM | AI266: 40 | AJ266: 30 | AK266: 0 | AL266: 2 | AM266: 0 | AN266: 2 | AO266: 0 | AP266: 2 | AQ266: 2 | AR266: 10 | AS266: 10 | AT266: 2 | AU266: 0
B267: R_60UJsZnGqWW7OvA | C267: TM | AI267: 68.5 | AJ267: 15 | AK267: 2.5 | AL267: 0 | AM267: 2.5 | AN267: 0 | AO267: 0 | AP267: 2.5 | AQ267: 0 | AR267: 2 | AS267: 2 | AT267: 5 | AU267: 0
... B375: R_7JxumELu2fdbqgX | C375: TM | AI375: 55 | AJ375: 40 | AK375: 0 | AL375: 0 | AM375: 1 | AN375: 2 | AO375: 1 | AP375: 1 | AQ375: 0 | AR375: 0 | AS375: 0 | AT375: 0 | AU375: 0

Sheet SS Answers Cleaned
B2: Type of Question | C2: =_xlfn.XLOOKUP(C4,'SS Questions Cleaned'!$B$3:$B$140,'SS Questions Cleaned'!$G$3:$G$140) -> Neither | D2: =_xlfn.XLOOKUP(D4,'SS Questions Cleaned'!$B$3:$B$140,'SS Questions Cleaned'!$G$3:$G$140) -> Percent | E2: =_xlfn.XLOOKUP(E4,'SS Questions Cleaned'!$B$3:$B$140,'SS Questions Cleaned'!$G$3:$G$140) -> Percent | F2: =_xlfn.XLOOKUP(F4,'SS Questions Cleaned'!$B$3:$B$140,'SS Questions Cleaned'!$G$3:$G$140) -> Percent | G2: =_xlfn.XLOOKUP(G4,'SS Questions Cleaned'!$B$3:$B$140,'SS Questions Cleaned'!$G$3:$G$140) -> Percent | H2: =_xlfn.XLOOKUP(H4,'SS Questions Cleaned'!$B$3:$B$140,'SS Questions Cleaned'!$G$3:$G$140) -> Percent | I2: =_xlfn.XLOOKUP(I4,'SS Questions Cleaned'!$B$3:$B$140,'SS Questions Cleaned'!$G$3:$G$140) -> Percent | J2: =_xlfn.XLOOKUP(J4,'SS Questions Cleaned'!$B$3:$B$140,'SS Questions Cleaned'!$G$3:$G$140) -> Percent | ... EJ2: =_xlfn.XLOOKUP(EJ4,'SS Questions Cleaned'!$B$3:$B$140,'SS Questions Cleaned'!$G$3:$G$140) -> Neither
B3: Response ID | C3: Select your role | D3: What is the % mix of time that you spend on these categories of contact below in an average 40 hour work week, excluding lunch? (e.g. 10% of a week is 4 hours) - Order status/tracking | E3: What is the % mix of time that you spend on these categories of contact below in an average 40 hour work week, excluding lunch? (e.g. 10% of a week is 4 hours) - New order/ quote | F3: What is the % mix of time that you spend on these categories of contact below in an average 40 hour work week, excluding lunch? (e.g. 10% of a week is 4 hours) - Cancellation | G3: What is the % mix of time that you spend on these categories of contact below in an average 40 hour work week, excluding lunch? (e.g. 10% of a week is 4 hours) - Replacements & returns | H3: What is the % mix of time that you spend on these categories of contact below in an average 40 hour work week, excluding lunch? (e.g. 10% of a week is 4 hours) - Order edit/change | I3: What is the % mix of time that you spend on these categories of contact below in an average 40 hour work week, excluding lunch? (e.g. 10% of a week is 4 hours) - Website/ technical support | J3: What is the % mix of time that you spend on these categories of contact below in an average 40 hour work week, excluding lunch? (e.g. 10% of a week is 4 hours) - Sizing issues | K3: What is the % mix of time that you spend on these categories of contact below in an average 40 hour work week, excluding lunch? (e.g. 10% of a week is 4 hours) - Refund request | L3: What is the % mix of time that you spend on these categories of contact below in an average 40 hour work week, excluding lunch? (e.g. 10% of a week is 4 hours) - Missed order deadline | M3: What is the % mix of time that you spend on these categories of contact below in an average 40 hour work week, excluding lunch? (e.g. 10% of a week is 4 hours) - Other customer inquiries | N3: What is the % mix of time that you spend on these categories of contact below in an average 40 hour work week, excluding lunch? (e.g. 10% of a week is 4 hours) - Internal communications (e.g. email/ calls to FSPs) | O3: What is the % mix of time that you spend on these categories of contact below in an average 40 hour work week, excluding lunch? (e.g. 10% of a week is 4 hours) - External communications (e.g. emails/ calls to vendors) | P3: What is the % mix of time that you spend on these categories of contact below in an average 40 hour work week, excluding lunch? (e.g. 10% of a week is 4 hours) - Meetings (e.g. team meetings, townhalls) | Q3: What is the % mix of time that you spend on these categories of contact below in an average 40 hour work week, excluding lunch? (e.g. 10% of a week is 4 hours) - Breaks | R3: What is the % mix of time that you spend on these categories of contact below in an average 40 hour work week, excluding lunch? (e.g. 10% of a week is 4 hours) - Other activities (specify activity and provide details on the following page) | S3: You indicated that part of your time is spent on the "other activities" not listed in the prior question. Please specify these activities. | T3: On average, how long does a single request for each of the following categories of contact take you to complete, excluding wait time or system delays? - Order status/tracking | U3: On average, how long does a single request for each of the following categories of contact take you to complete, excluding wait time or system delays? - New order/ quote | V3: On average, how long does a single request for each of the following categories of contact take you to complete, excluding wait time or system delays? - Cancellation | W3: On average, how long does a single request for each of the following categories of contact take you to complete, excluding wait time or system delays? - Replacements & returns | X3: On average, how long does a single request for each of the following categories of contact take you to complete, excluding wait time or system delays? - Order edit/change | Y3: On average, how long does a single request for each of the following categories of contact take you to complete, excluding wait time or system delays? - Website/ technical support | Z3: On average, how long does a single request for each of the following categories of contact take you to complete, excluding wait time or system delays? - Sizing issues | AA3: On average, how long does a single request for each of the following categories of contact take you to complete, excluding wait time or system delays? - Refund request | AB3: On average, how long does a single request for each of the following categories of contact take you to complete, excluding wait time or system delays? - Missed order deadline | AC3: On average, how long does a single request for each of the following categories of contact take you to complete, excluding wait time or system delays? - Other customer inquiries | AD3: In your view, what tasks can be automated/streamlined to reduce repetition? | AE3: What is the % mix of time that you spend on these activities below in an average 40 hour work week, excluding lunch? (e.g. 10% of a week is 4 hours) - Pushing Carts | AF3: What is the % mix of time that you spend on these activities below in an average 40 hour work week, excluding lunch? (e.g. 10% of a week is 4 hours) - MTS Changes | AG3: What is the % mix of time that you spend on these activities below in an average 40 hour work week, excluding lunch? (e.g. 10% of a week is 4 hours) - Consolidating MTS shops | AH3: What is the % mix of time that you spend on these activities below in an average 40 hour work week, excluding lunch? (e.g. 10% of a week is 4 hours) - MTS Credits | AI3: What is the % mix of time that you spend on these activities below in an average 40 hour work week, excluding lunch? (e.g. 10% of a week is 4 hours) - Core Order Changes | AJ3: What is the % mix of time that you spend on these activities below in an average 40 hour work week, excluding lunch? (e.g. 10% of a week is 4 hours) - Working on Open orders | AK3: What is the % mix of time that you spend on these activities below in an average 40 hour work week, excluding lunch? (e.g. 10% of a week is 4 hours) - Reactive Order Tracking/ Status | AL3: What is the % mix of time that you spend on these activities below in an average 40 hour work week, excluding lunch? (e.g. 10% of a week is 4 hours) - AP/AR | AM3: What is the % mix of time that you spend on these activities below in an average 40 hour work week, excluding lunch? (e.g. 10% of a week is 4 hours) - Invoicing Questions | AN3: What is the % mix of time that you spend on these activities below in an average 40 hour work week, excluding lunch? (e.g. 10% of a week is 4 hours) - Label Requests (Freight) | AO3: What is the % mix of time that you spend on these activities below in an average 40 hour work week, excluding lunch? (e.g. 10% of a week is 4 hours) - Processing Returns/Replacements | AP3: What is the % mix of time that you spend on these activities below in an average 40 hour work week, excluding lunch? (e.g. 10% of a week is 4 hours) - Processing Comp Goods | AQ3: What is the % mix of time that you spend on these activities below in an average 40 hour work week, excluding lunch? (e.g. 10% of a week is 4 hours) - Internal communications (e.g. email/ calls to FSPs) | AR3: What is the % mix of time that you spend on these activities below in an average 40 hour work week, excluding lunch? (e.g. 10% of a week is 4 hours) - Meetings (e.g. team meetings, townhalls) | AS3: What is the % mix of time that you spend on these activities below in an average 40 hour work week, excluding lunch? (e.g. 10% of a week is 4 hours) - Breaks | AT3: What is the % mix of time that you spend on these activities below in an average 40 hour work week, excluding lunch? (e.g. 10% of a week is 4 hours) - Other activities (specify activity and provide details on the following page) | AU3: You indicated that part of your time is spent on the "other activities" not listed in the prior question. Please specify these activities. | AV3: On average, how long does a single request for each of the following activities take you to complete, excluding wait time or system delays? - Pushing Carts | AW3: On average, how long does a single request for each of the following activities take you to complete, excluding wait time or system delays? - MTS Changes | AX3: On average, how long does a single request for each of the following activities take you to complete, excluding wait time or system delays? - Consolidating MTS shops | AY3: On average, how long does a single request for each of the following activities take you to complete, excluding wait time or system delays? - MTS Credits | AZ3: On average, how long does a single request for each of the following activities take you to complete, excluding wait time or system delays? - Core Order Changes | BA3: On average, how long does a single request for each of the following activities take you to complete, excluding wait time or system delays? - Working on Open orders | BB3: On average, how long does a single request for each of the following activities take you to complete, excluding wait time or system delays? - Reactive Order Tracking/ Status | BC3: On average, how long does a single request for each of the following activities take you to complete, excluding wait time or system delays? - AP/AR | BD3: On average, how long does a single request for each of the following activities take you to complete, excluding wait time or system delays? - Invoicing Questions | BE3: On average, how long does a single request for each of the following activities take you to complete, excluding wait time or system delays? - Label Requests (Freight) | BF3: On average, how long does a single request for each of the following activities take you to complete, excluding wait time or system delays? - Processing Returns/Replacements | BG3: On average, how long does a single request for each of the following activities take you to complete, excluding wait time or system delays? - Processing Comp Goods | BH3: In general, how would you rate the following aspects of working with Sales Pros? - Responsiveness of Sales Pros in providing necessary information | BI3: In general, how would you rate the following aspects of working with Sales Pros? - Level of collaboration during support interactions | BJ3: In general, how would you rate the following aspects of working with Sales Pros? - Level of professionalism in interactions | BK3: In general, how would you rate the following aspects of working with Sales Pros? - Sales Pros’ understanding of your role and responsibilities | BL3: Based on your experience, what percentage of the requests you receive from sales pros come with each of the following expected completion timeframes? - Greater than 2-3 days | BM3: Based on your experience, what percentage of the requests you receive from sales pros come with each of the following expected completion timeframes? - Within 2-3 days | BN3: Based on your experience, what percentage of the requests you receive from sales pros come with each of the following expected completion timeframes? - Within 24 hours | BO3: Based on your experience, what percentage of the requests you receive from sales pros come with each of the following expected completion timeframes? - Within a few hours | BP3: Based on your experience, what percentage of the requests you receive from sales pros come with each of the following expected completion timeframes? - Immediately – within the hour | BQ3: What is working well with your current set-up supporting Sales Pros? | BR3: What are some areas that Sales Pros could improve on in communications/ requests to better support your work? | BS3: What are improvements that we could implement to help you better support Sales Pros? | BT3: Are there any tools, resources or processes that can help/ have helped you support Sales Pros more effectively? | BU3: What is the % mix of time that you spend on these activities below in an average 40 hour work week, excluding lunch? (e.g. 10% of a week is 4 hours) - Quote Cart | BV3: What is the % mix of time that you spend on these activities below in an average 40 hour work week, excluding lunch? (e.g. 10% of a week is 4 hours) - Fact Finding | BW3: What is the % mix of time that you spend on these activities below in an average 40 hour work week, excluding lunch? (e.g. 10% of a week is 4 hours) - Purchase Order | BX3: What is the % mix of time that you spend on these activities below in an average 40 hour work week, excluding lunch? (e.g. 10% of a week is 4 hours) - Content Creation | BY3: What is the % mix of time that you spend on these activities below in an average 40 hour work week, excluding lunch? (e.g. 10% of a week is 4 hours) - Rewards agreement | BZ3: What is the % mix of time that you spend on these activities below in an average 40 hour work week, excluding lunch? (e.g. 10% of a week is 4 hours) - Return/ Replacement | CA3: What is the % mix of time that you spend on these activities below in an average 40 hour work week, excluding lunch? (e.g. 10% of a week is 4 hours) - Update contact info | CB3: What is the % mix of time that you spend on these activities below in an average 40 hour work week, excluding lunch? (e.g. 10% of a week is 4 hours) - Freight Quote | CC3: What is the % mix of time that you spend on these activities below in an average 40 hour work week, excluding lunch? (e.g. 10% of a week is 4 hours) - Other supporting activities (Adidas, BSN Construction, Corporate, bid, Training) | CD3: What is the % mix of time that you spend on these activities below in an average 40 hour work week, excluding lunch? (e.g. 10% of a week is 4 hours) - Internal communications (e.g. email/ calls to FSPs) | CE3: What is the % mix of time that you spend on these activities below in an average 40 hour work week, excluding lunch? (e.g. 10% of a week is 4 hours) - External communications (e.g. emails/ calls to vendors) | CF3: What is the % mix of time that you spend on these activities below in an average 40 hour work week, excluding lunch? (e.g. 10% of a week is 4 hours) - Meetings (e.g. team meetings, townhalls) | CG3: What is the % mix of time that you spend on these activities below in an average 40 hour work week, excluding lunch? (e.g. 10% of a week is 4 hours) - Other activities (specify activity and provide details on the following page) | CH3: You indicated that part of your time is spent on the "other activities" not listed in the prior question. Please specify these activities. | CI3: On average, what % of your requests from the field get logged in the ticketing system? (0-100%) - % of total | CJ3: Other sources of requests - a. Direct email from FSPs/ASMs/RSDs | CK3: Other sources of requests - b. Direct Teams Chat | CL3: Other sources of requests - c. Phone/ Texts from FSPs/ASMs/RSDs | CM3: Other sources of requests - d. Request made in scheduled meetings | CN3: Other sources of requests - e. Other (please specify) | CO3: You indicated that part of your time is spent on the "other activities" not listed in the prior question. Please specify these activities. | CP3: On average, how long does a single request for each of the following activities take you to complete, excluding wait time or system delays? - Quote Cart | CQ3: On average, how long does a single request for each of the following activities take you to complete, excluding wait time or system delays? - Fact Finding | CR3: On average, how long does a single request for each of the following activities take you to complete, excluding wait time or system delays? - Purchase Order | CS3: On average, how long does a single request for each of the following activities take you to complete, excluding wait time or system delays? - Content Creation | CT3: On average, how long does a single request for each of the following activities take you to complete, excluding wait time or system delays? - Rewards agreement | CU3: On average, how long does a single request for each of the following activities take you to complete, excluding wait time or system delays? - Return/ Replacement | CV3: On average, how long does a single request for each of the following activities take you to complete, excluding wait time or system delays? - Update contact info | CW3: On average, how long does a single request for each of the following activities take you to complete, excluding wait time or system delays? - Freight Quote | CX3: On average, how long does a single request for each of the following activities take you to complete, excluding wait time or system delays? - Other supporting activities (Adidas, BSN Construction, Corporate, bid, Training) | CY3: What is the % mix of time that you spend on these activities below in an average 40 hour work week, excluding lunch? (e.g. 10% of a week is 4 hours) - New Cases | CZ3: What is the % mix of time that you spend on these activities below in an average 40 hour work week, excluding lunch? (e.g. 10% of a week is 4 hours) - Order Entry (e.g. creating comp carts, applying coupons from Nike, UA etc.) | DA3: What is the % mix of time that you spend on these activities below in an average 40 hour work week, excluding lunch? (e.g. 10% of a week is 4 hours) - Managing stocking issues | DB3: What is the % mix of time that you spend on these activities below in an average 40 hour work week, excluding lunch? (e.g. 10% of a week is 4 hours) - Internal communication (Emails/ Calls to FSPs) | DC3: What is the % mix of time that you spend on these activities below in an average 40 hour work week, excluding lunch? (e.g. 10% of a week is 4 hours) - External communications (e.g. emails/ calls to vendors) | DD3: What is the % mix of time that you spend on these activities below in an average 40 hour work week, excluding lunch? (e.g. 10% of a week is 4 hours) - Meetings (e.g. team meetings, townhalls) | DE3: What is the % mix of time that you spend on these activities below in an average 40 hour work week, excluding lunch? (e.g. 10% of a week is 4 hours) - Order Management (tracking order) | DF3: What is the % mix of time that you spend on these activities below in an average 40 hour work week, excluding lunch? (e.g. 10% of a week is 4 hours) - Breaks | DG3: What is the % mix of time that you spend on these activities below in an average 40 hour work week, excluding lunch? (e.g. 10% of a week is 4 hours) - Other activities (specify activity and provide details on the following page) | DH3: You indicated that part of your time is spent on the "other activities" not listed in the prior question. Please specify these activities. | DI3: On average, how long does a single comp goods case take you to complete, excluding wait time or system delays? - Case | DJ3: What is the % mix of time that you spend on these activities below in an average 40 hour work week, excluding lunch? (e.g. 10% of a week is 4 hours) - New Cases | DK3: What is the % mix of time that you spend on these activities below in an average 40 hour work week, excluding lunch? (e.g. 10% of a week is 4 hours) - Order entry (ZREP/RE Entry) | DL3: What is the % mix of time that you spend on these activities below in an average 40 hour work week, excluding lunch? (e.g. 10% of a week is 4 hours) - Order management (Status review of ZREPs/ RE/Original Order Open) | DM3: What is the % mix of time that you spend on these activities below in an average 40 hour work week, excluding lunch? (e.g. 10% of a week is 4 hours) - Internal communication (Emails/ Calls to FSPs) | DN3: What is the % mix of time that you spend on these activities below in an average 40 hour work week, excluding lunch? (e.g. 10% of a week is 4 hours) - External communications (e.g. emails/ calls to vendors) | DO3: What is the % mix of time that you spend on these activities below in an average 40 hour work week, excluding lunch? (e.g. 10% of a week is 4 hours) - Meetings (e.g. team meetings, townhalls) | DP3: What is the % mix of time that you spend on these activities below in an average 40 hour work week, excluding lunch? (e.g. 10% of a week is 4 hours) - Breaks | DQ3: What is the % mix of time that you spend on these activities below in an average 40 hour work week, excluding lunch? (e.g. 10% of a week is 4 hours) - Other activities (specify activity and provide details on the following page) | DR3: You indicated that part of your time is spent on the "other activities" not listed in the prior question. Please specify these activities. | DS3: On average, how long does a single returns/replacement case take you to complete, excluding wait time or system delays? - Case | DT3: What is the % mix of time that you spend on these activities below in an average 40 hour work week, excluding lunch? (e.g. 10% of a week is 4 hours) - Build Request Lead (new build, duplicate shop, etc..) | DU3: What is the % mix of time that you spend on these activities below in an average 40 hour work week, excluding lunch? (e.g. 10% of a week is 4 hours) - Shop Edits | DV3: What is the % mix of time that you spend on these activities below in an average 40 hour work week, excluding lunch? (e.g. 10% of a week is 4 hours) - Art Submission | DW3: What is the % mix of time that you spend on these activities below in an average 40 hour work week, excluding lunch? (e.g. 10% of a week is 4 hours) - Internal communication (Emails/ Calls to FSPs) | DX3: What is the % mix of time that you spend on these activities below in an average 40 hour work week, excluding lunch? (e.g. 10% of a week is 4 hours) - External communications (e.g. emails/ calls to vendors) | DY3: What is the % mix of time that you spend on these activities below in an average 40 hour work week, excluding lunch? (e.g. 10% of a week is 4 hours) - Meetings (e.g. team meetings, townhalls) | DZ3: What is the % mix of time that you spend on these activities below in an average 40 hour work week, excluding lunch? (e.g. 10% of a week is 4 hours) - Shop Launch | EA3: What is the % mix of time that you spend on these activities below in an average 40 hour work week, excluding lunch? (e.g. 10% of a week is 4 hours) - Issue Resolution / Q& A | EB3: What is the % mix of time that you spend on these activities below in an average 40 hour work week, excluding lunch? (e.g. 10% of a week is 4 hours) - Breaks | EC3: What is the % mix of time that you spend on these activities below in an average 40 hour work week, excluding lunch? (e.g. 10% of a week is 4 hours) - Other activities (specify activity and provide details on the following page) | ED3: You indicated that part of your time is spent on the "other activities" not listed in the prior question. Please specify these activities. | EE3: On average, how long does a single request for each of the following take you to complete, excluding wait time or system delays? - Average MTS Shop | EF3: On average, how long does a single request for each of the following take you to complete, excluding wait time or system delays? - Average Sprint Shop | EG3: How does working with the sales pro versus directly with the school/coach change the amount of time to complete an MTS shop? | EH3: You indicated that it takes longer to work with a sales pro on completing an MTS shop than it does when working directly with a school/coach. In your estimate, how much longer does it take for a single shop? | EI3: What are the main reasons for the longer build time? (select all that apply) | EJ3: You indicated that part of your time is spent on the "other activities" not listed in the prior question. Please specify these activities.
B4: ResponseId | C4: Q1.2 | D4: Q2.1_1 | E4: Q2.1_2 | F4: Q2.1_3 | G4: Q2.1_4 | H4: Q2.1_5 | I4: Q2.1_6 | J4: Q2.1_7 | K4: Q2.1_8 | L4: Q2.1_9 | M4: Q2.1_10 | N4: Q2.1_11 | O4: Q2.1_12 | P4: Q2.1_13 | Q4: Q2.1_15 | R4: Q2.1_16 | S4: Q2.2 | T4: Q2.3_1 | U4: Q2.3_2 | V4: Q2.3_3 | W4: Q2.3_4 | X4: Q2.3_5 | Y4: Q2.3_6 | Z4: Q2.3_7 | AA4: Q2.3_8 | AB4: Q2.3_9 | AC4: Q2.3_10 | AD4: Q3.1 | AE4: Q4.1_1 | AF4: Q4.1_2 | AG4: Q4.1_3 | AH4: Q4.1_4 | AI4: Q4.1_5 | AJ4: Q4.1_6 | AK4: Q4.1_7 | AL4: Q4.1_8 | AM4: Q4.1_9 | AN4: Q4.1_10 | AO4: Q4.1_11 | AP4: Q4.1_12 | AQ4: Q4.1_13 | AR4: Q4.1_14 | AS4: Q4.1_15 | AT4: Q4.1_16 | AU4: Q4.2 | AV4: Q4.3_1 | AW4: Q4.3_2 | AX4: Q4.3_3 | AY4: Q4.3_4 | AZ4: Q4.3_5 | BA4: Q4.3_6 | BB4: Q4.3_7 | BC4: Q4.3_8 | BD4: Q4.3_9 | BE4: Q4.3_10 | BF4: Q4.3_11 | BG4: Q4.3_12 | BH4: Q5.1_1 | BI4: Q5.1_2 | BJ4: Q5.1_3 | BK4: Q5.1_4 | BL4: Q5.2_1 | BM4: Q5.2_2 | BN4: Q5.2_3 | BO4: Q5.2_4 | BP4: Q5.2_5 | BQ4: Q5.3 | BR4: Q5.4 | BS4: Q5.5 | BT4: Q5.6 | BU4: Q6.1_1 | BV4: Q6.1_2 | BW4: Q6.1_3 | BX4: Q6.1_4 | BY4: Q6.1_5 | BZ4: Q6.1_6 | CA4: Q6.1_7 | CB4: Q6.1_8 | CC4: Q6.1_9 | CD4: Q6.1_10 | CE4: Q6.1_11 | CF4: Q6.1_12 | CG4: Q6.1_13 | CH4: Q6.2 | CI4: Q6.3_1 | CJ4: Q6.4_1 | CK4: Q6.4_2 | CL4: Q6.4_3 | CM4: Q6.4_4 | CN4: Q6.4_5 | CO4: Q6.5 | CP4: Q6.6_1 | CQ4: Q6.6_2 | CR4: Q6.6_3 | CS4: Q6.6_4 | CT4: Q6.6_5 | CU4: Q6.6_6 | CV4: Q6.6_7 | CW4: Q6.6_8 | CX4: Q6.6_9 | CY4: Q7.1_1 | CZ4: Q7.1_2 | DA4: Q7.1_3 | DB4: Q7.1_4 | DC4: Q7.1_5 | DD4: Q7.1_6 | DE4: Q7.1_7 | DF4: Q7.1_8 | DG4: Q7.1_9 | DH4: Q7.2 | DI4: Q7.3_1 | DJ4: Q8.1_1 | DK4: Q8.1_2 | DL4: Q8.1_3 | DM4: Q8.1_4 | DN4: Q8.1_5 | DO4: Q8.1_6 | DP4: Q8.1_8 | DQ4: Q8.1_9 | DR4: Q8.2 | DS4: Q8.3_1 | DT4: Q9.1_1 | DU4: Q9.1_2 | DV4: Q9.1_3 | DW4: Q9.1_4 | DX4: Q9.1_5 | DY4: Q9.1_6 | DZ4: Q9.1_14 | EA4: Q9.1_15 | EB4: Q9.1_8 | EC4: Q9.1_9 | ED4: Q9.2 | EE4: Q9.3_1 | EF4: Q9.3_2 | EG4: Q9.4 | EH4: Q9.5 | EI4: Q9.6 | EJ4: Q9.7
B5: R_10kSt027CYOWXJG | C5: TM | AD5: to be honest I dont mind having FSP reach out for whatever they need, that is what we are here for. The more we have them check here or look over here before reaching out makes them unhappy.. they already cant keep up with who to ask between all the pods and is that a TM or SSR question.. or do I email account service or AR or bsn billing... In my opinion it should be 1 person (TM) then we take that request and work with all of the internal departments to get an answer or start whatever they need and get back to them. Even if it is the TM getting tracking or looking at the notes of the order in engage and we (TM) still cant get the info then we email the SSR to get the info.. but all of this its not my swim lane or email this person is not servicing the FSP its just too many emails and things for them to remember.. We the TM should be the 1st and only stop on who they need to contact to get whatever info they need. | BH5: 3 | BI5: 3 | BJ5: 4 | BK5: 2 | BL5: 0 | BM5: 10 | BN5: 40 | BO5: 30 | BP5: 20 | BQ5: open communication, taking their request however they want to send it.. VIA requests, email, call, Teams message | BR5: to understand we are not mind readers and need all the info in the 1st request | BS5: VOE - Duplicate entries in cart creation- need this fixed | BT5: learning more about deco and custom. so we can help with all orders | BU5: 15 | BV5: 30 | BW5: 5 | BX5: 5 | BY5: 2 | BZ5: 5 | CA5: 3 | CB5: 0 | CC5: 10 | CD5: 5 | CE5: 10 | CF5: 10 | CG5: 0 | CI5: 70 | CJ5: 40 | CK5: 20 | CL5: 30 | CM5: 10 | CN5: 0 | CP5: 10-20 mins | CQ5: 20-40 mins | CR5: 5-10 mins | CS5: 20-40 mins | CT5: 10-20 mins | CU5: 10-20 mins | CV5: 10-20 mins | CW5: 5-10 mins | CX5: 40-60 mins
B6: R_6SrYuf3lGeG7eQp | C6: TM | AD6: All school Deals | BH6: 5 - Very High | BI6: 5 - Very High | BJ6: 5 - Very High | BK6: 5 - Very High | BL6: 0 | BM6: 10 | BN6: 90 | BO6: 0 | BP6: 0 | BQ6: Communcation on everything!! | BR6: N/A | BS6: N/A | BT6: perfect at this moment | BU6: 60 | BV6: 30 | BW6: 0 | BX6: 0 | BY6: 5 | BZ6: 0 | CA6: 0 | CB6: 0 | CC6: 0 | CD6: 5 | CE6: 0 | CF6: 0 | CG6: 0 | CI6: 95 | CJ6: 90 | CK6: 0 | CL6: 10 | CM6: 0 | CN6: 0 | CP6: 20-40 mins | CQ6: 2-3h | CT6: 20-40 mins | CU6: 20-40 mins | CW6: 2-3h
B7: R_1eliuDNduR3ISzx | C7: Customer Care | D7: 10 | E7: 0 | F7: 10 | G7: 0 | H7: 10 | I7: 10 | J7: 0 | K7: 10 | L7: 0 | M7: 10 | N7: 10 | O7: 10 | P7: 10 | Q7: 0 | R7: 10 | S7: Manager will ask me to assist in other areas. | T7: 10-20 mins | U7: 10-20 mins | V7: 20-40 mins | W7: 20-40 mins | X7: 20-40 mins | Y7: 40-60 mins | Z7: 20-40 mins | AA7: 20-40 mins | AC7: 40-60 mins | AD7: Releasing Sideline orders and assisting with cancelling and refunding customers on the Nike backlog list. These two tasks take a lot of time.
B8: R_1AnVoRS4iYqJ2lX | C8: Comp Pod | AD8: More prefilled areas in Engage, sales reps actually reading and responding to what we are needing, more accurate inventory visual | BH8: 3 | BI8: 3 | BJ8: 3 | BK8: 2 | BL8: 20 | BM8: 20 | BN8: 20 | BO8: 20 | BP8: 20 | BQ8: Generated templates, order forms. | BR8: Taking the time to read our emails when have questions or need more information/assistance. Also understanding that we are not Nike, we do not have control of inventory/availability as its always changing. Not alot, but a good handful come off very rude in their responses and we only trying to help take something off their plate. | BS8: Making sure they understand HOW comp works, what we can and can not do. And sending in completed order forms and not chicken scratch | BT8: They have the tools, its who chooses to use them correctly | CY8: 10 | CZ8: 10 | DA8: 25 | DB8: 25 | DC8: 0 | DD8: 5 | DE8: 10 | DF8: 5 | DG8: 10 | DH8: Dealing with Nike support, reaching out to deco, helping out others with order issues | DI8: 10-20 mins
B9: R_6n0LsNjfNThAuXh | C9: SSR | AD9: AN OPTION TO SEND THE PRO A NOTIFICATION WHEN WE PUSH OUT A TASK IN ENAGAGE. THIS WOULD CUT DOWN ON EMAILS AND KEEP THE PRO UPDATED IN REAL TIME | AE9: 0 | AF9: 5 | AG9: 0 | AH9: 0 | AI9: 0 | AJ9: 40 | AK9: 20 | AL9: 5 | AM9: 5 | AN9: 0 | AO9: 5 | AP9: 0 | AQ9: 20 | AR9: 0 | AS9: 0 | AT9: 0 | AV9: <5 mins | AW9: 5-10 mins | AX9: <5 mins | AY9: 5-10 mins | AZ9: <5 mins | BA9: <5 mins | BB9: <5 mins | BC9: <5 mins | BD9: <5 mins | BE9: <5 mins | BF9: <5 mins | BH9: 4 | BI9: 4 | BJ9: 5 - Very High | BK9: 3 | BL9: 0 | BM9: 0 | BN9: 10 | BO9: 80 | BP9: 10 | BQ9: GOOD COMMUNICATION | BR9: DETAILED REQUESTS | BS9: AN OPTION TO SEND THE PRO A NOTIFICATION WHEN WE PUSH OUT A TASK IN ENAGAGE. THIS WOULD CUT DOWN ON EMAILS AND KEEP THE PRO UPDATED IN REAL TIME | BT9: AN OPTION TO SEND THE PRO A NOTIFICATION WHEN WE PUSH OUT A TASK IN ENAGAGE. THIS WOULD CUT DOWN ON EMAILS AND KEEP THE PRO UPDATED IN REAL TIME
B10: R_61vzskVuPNAgQK5 | C10: Customer Care | D10: 10 | E10: 5 | F10: 10 | G10: 25 | H10: 10 | I10: 2 | J10: 10 | K10: 10 | L10: 5 | M10: 0 | N10: 1 | O10: 1 | P10: 1 | Q10: 10 | R10: 0 | T10: <5 mins | U10: 5-10 mins | V10: 5-10 mins | W10: 5-10 mins | X10: 10-20 mins | Y10: 5-10 mins | Z10: <5 mins | AA10: 10-20 mins | AB10: 10-20 mins | AC10: 10-20 mins | AD10: The refund process for SPRINT orders. Filling out the AR forms can be time consuming. Entering a nonphysical return on SAP also takes some time. I wish there was something like ZSLrefund that worked for SPRINT MTS.
B11: R_3OiTOWeVyYUdppc | C11: SSR | AD11: Label creations and placing NIKE custom POs! | AE11: 1 | AF11: 5 | AG11: 2 | AH11: 5 | AI11: 10 | AJ11: 30 | AK11: 15 | AL11: 3 | AM11: 1 | AN11: 1 | AO11: 1 | AP11: 0 | AQ11: 15 | AR11: 1 | AS11: 10 | AT11: 0 | AV11: <5 mins | AW11: 5-10 mins | AX11: 5-10 mins | AY11: <5 mins | AZ11: 5-10 mins | BA11: 10-20 mins | BB11: <5 mins | BC11: <5 mins | BD11: 10-20 mins | BE11: <5 mins | BF11: <5 mins | BH11: 5 - Very High | BI11: 5 - Very High | BJ11: 5 - Very High | BK11: 4 | BL11: 4 | BM11: 6 | BN11: 20 | BO11: 30 | BP11: 40 | BQ11: I believe everything is working well! | BR11: Checking engage for status updates! | BS11: N/A | BT11: N/A
B12: R_6R9gp6sJYpXXrNf | C12: TM | AD12: content creation | BH12: 4 | BI12: 4 | BJ12: 4 | BK12: 4 | BL12: 0 | BM12: 0 | BN12: 30 | BO12: 70 | BP12: 0 | BQ12: veteran slaes pros for the most part | BR12: All info on the front end of the request. Provide all inofo needed for request | BS12: Require a customer # to submit the ticket | BT12: Vault | BU12: 40 | BV12: 40 | BW12: 0 | BX12: 5 | BY12: 0 | BZ12: 0 | CA12: 0 | CB12: 0 | CC12: 0 | CD12: 5 | CE12: 5 | CF12: 5 | CG12: 0 | CI12: 94 | CJ12: 40 | CK12: 20 | CL12: 40 | CM12: 0 | CN12: 0 | CP12: 5-10 mins | CQ12: 5-10 mins | CR12: 5-10 mins | CS12: 10-20 mins | CT12: 20-40 mins | CU12: 10-20 mins | CV12: 5-10 mins | CW12: 5-10 mins | CX12: 5-10 mins
B13: R_1j37HFdJu1TAYWA | C13: TM | AD13: Discounts linked directly to account with active rewards deals | BH13: 4 | BI13: 5 - Very High | BJ13: 5 - Very High | BK13: 4 | BL13: 5 | BM13: 5 | BN13: 50 | BO13: 30 | BP13: 10 | BQ13: I've been working with the same team for 2 years now so our communication has developed into a streamlined process | BR13: The may need some basic training on what questions to ask the coach before sending me a request for maximum efficiency. | BS13: I am satisfied with my role at this point, and am able to succeed in helping my team. | BT13: The addition of the Out Of Office folder is incredibly helpful for the entire team to chip in and help when another TM is on vacation. I wouldn't think someone could take on my entire day to day, while still being able to do their own tasks for the day (let alone a week or two) | BU13: 50 | BV13: 33 | BW13: 1 | BX13: 13 | BY13: 2 | BZ13: 0 | CA13: 0 | CB13: 1 | CC13: 0 | CD13: 0 | CE13: 0 | CF13: 0 | CG13: 0 | CI13: 100 | CJ13: 0 | CK13: 0 | CL13: 0 | CM13: 0 | CN13: 100 | CO13: None | CP13: 40-60 mins | CQ13: 10-20 mins | CR13: 5-10 mins | CS13: 5-10 mins | CT13: 20-40 mins | CU13: 20-40 mins | CV13: 5-10 mins | CW13: 10-20 mins | CX13: 40-60 mins
B14: R_6OFiuMwv2yqcul3 | C14: SSR | AD14: -constantly answering emails from SP's and even SAPHD sometimes about the status of an order on LWO when we take the time to put in engage. -All MTS being wizard or plus. -internal deco going straight to R&R for all ZREP request. -Easier time getting a status from some vendors like Adidas and Schutt | AE14: 0 | AF14: 10 | AG14: 5 | AH14: 0 | AI14: 10 | AJ14: 30 | AK14: 10 | AL14: 5 | AM14: 10 | AN14: 0 | AO14: 10 | AP14: 0 | AQ14: 0 | AR14: 0 | AS14: 10 | AT14: 0 | AV14: <5 mins | AW14: 5-10 mins | AX14: <5 mins | AY14: 5-10 mins | AZ14: 10-20 mins | BA14: 2-3h | BB14: 10-20 mins | BC14: 10-20 mins | BD14: 10-20 mins | BE14: 5-10 mins | BF14: 10-20 mins | BH14: 4 | BI14: 3 | BJ14: 3 | BK14: 3 | BL14: 0 | BM14: 5 | BN14: 10 | BO14: 10 | BP14: 75 | BQ14: Familiarity with my sales pros. I know what they want before they ask half the time | BR14: -always including order number in the subject line. -some need to work on always putting the needed information in orders I.E. UD# what flavor Gatorade they want -They answering my emails in a timely manner | BS14: MAKE THEM USE ENGAGE | BT14: more training for the SP's the newer guys are are so lost sometimes on procedure
B15: R_7CCEJasYyxv9dyz | C15: MTS Pod | AD15: na | BH15: 4 | BI15: 5 - Very High | BJ15: 5 - Very High | BK15: 4 | BL15: 0 | BM15: 0 | BN15: 75 | BO15: 20 | BP15: 5 | BQ15: if leads have all pertinent info, it works well | BR15: if they have specific requests put in lead info. | BS15: na | BT15: na | DT15: 40 | DU15: 20 | DV15: 10 | DW15: 0 | DX15: 0 | DY15: 10 | DZ15: 10 | EA15: 0 | EB15: 10 | EC15: 0 | EE15: 20-40 mins | EF15: 20-40 mins | EG15: Both are about the same
B16: R_50Fmr5YYd0GdfMZ | C16: SSR | AD16: MTS Processing. The issue is we have it automated but SP are still allowed to build MTS that requires the SSR to process so we have a system that is automated but SP can work around it causing the SSR to have to still process MTS. | AE16: 1 | AF16: 5 | AG16: 10 | AH16: 0 | AI16: 10 | AJ16: 50 | AK16: 5 | AL16: 0 | AM16: 5 | AN16: 2 | AO16: 0 | AP16: 0 | AQ16: 2 | AR16: 0 | AS16: 10 | AT16: 0 | AV16: <5 mins | AW16: 20-40 mins | AX16: 20-40 mins | AY16: 5-10 mins | AZ16: 10-20 mins | BA16: 1-2h | BB16: 5-10 mins | BC16: 5-10 mins | BD16: <5 mins | BE16: 5-10 mins | BF16: <5 mins | BH16: 3 | BI16: 3 | BJ16: 5 - Very High | BK16: 2 | BL16: 0 | BM16: 0 | BN16: 0 | BO16: 50 | BP16: 50 | BQ16: Unsure | BR16: Including all information in the requests. So many times a request is made with missing info. | BS16: SP need to start using Engage. We take all the time updating notes for them not to even check. | BT16: Allowing SP to update their own PO's would give me some time back to help with other things.
B17: R_5gXCv68kMP0o3EU | C17: SSR | AD17: Consolidation of non wizard MTS shops | AE17: 5 | AF17: 10 | AG17: 5 | AH17: 0 | AI17: 15 | AJ17: 35 | AK17: 5 | AL17: 5 | AM17: 5 | AN17: 0 | AO17: 0 | AP17: 0 | AQ17: 5 | AR17: 0 | AS17: 10 | AT17: 0 | AV17: <5 mins | AW17: 10-20 mins | AX17: 10-20 mins | AZ17: 5-10 mins | BA17: 5-10 mins | BB17: <5 mins | BC17: <5 mins | BD17: <5 mins | BH17: 4 | BI17: 4 | BJ17: 5 - Very High | BK17: 5 - Very High | BL17: 0 | BM17: 0 | BN17: 0 | BO17: 95 | BP17: 5 | BQ17: Sales reps have been using MTS Wizard shops more often creating less work on my end to close shops. | BR17: Sending return/replacement request straight to the returns team. Use engage to request updates on orders. | BS17: i am not sure at this time | BT17: Engage has been the biggest help
B18: R_59cue4jOO91w1tx | C18: R+R Pod | AD18: follow up emails for returns | BH18: 2 | BI18: 2 | BJ18: 2 | BK18: 2 | BL18: 40 | BM18: 30 | BN18: 15 | BO18: 10 | BP18: 5 | BQ18: when they use the grid properly | BR18: making sure they have approvals for our request before they submit them and giving us all the information we need | BS18: have them use the grid and fill out all information when submitting a request | BT18: N/A | DJ18: 26 | DK18: 15 | DL18: 12 | DM18: 12 | DN18: 15 | DO18: 5 | DP18: 5 | DQ18: 10 | DR18: emailing back with the SP for more info, getting updates from deco and vendors | DS18: 10-20 mins
B19: R_5NhXGOXEetA7QZj | C19: R+R Pod | AD19: Sending tracking to printers and sales pros. | BH19: 4 | BI19: 5 - Very High | BJ19: 5 - Very High | BK19: 4 | BL19: 75 | BM19: 10 | BN19: 10 | BO19: 3 | BP19: 2 | BQ19: Communication for the most part is good with the sales pro. They respond to the emails in a timely manner. | BR19: Filling out the request fully without typos. Also, providing deco approval when the order is a deco error before we ask them for it. | BS19: A form fill that pulls up the items on an order so they can click what they would like to return. | BT19: The SharePoint has been a game changer on giving the sales pros answers to questions in a timely manner. | DJ19: 10 | DK19: 20 | DL19: 20 | DM19: 10 | DN19: 15 | DO19: 10 | DP19: 10 | DQ19: 5 | DR19: Researching products, and working on projects. | DS19: 10-20 mins
B20: R_1P7p4dr02LqvkRJ | C20: SSR | AD20: We need the system to recognize and automatically change source plant issues | AE20: 0 | AF20: 5 | AG20: 5 | AH20: 5 | AI20: 5 | AJ20: 50 | AK20: 10 | AL20: 1 | AM20: 2 | AN20: 2 | AO20: 7 | AP20: 0 | AQ20: 5 | AR20: 1 | AS20: 2 | AT20: 0 | AV20: <5 mins | AW20: <5 mins | AX20: 5-10 mins | AY20: 5-10 mins | AZ20: 5-10 mins | BA20: <5 mins | BB20: <5 mins | BC20: 5-10 mins | BD20: 5-10 mins | BE20: <5 mins | BF20: <5 mins | BH20: 3 | BI20: 5 - Very High | BJ20: 5 - Very High | BK20: 3 | BL20: 5 | BM20: 10 | BN20: 85 | BO20: 0 | BP20: 0 | BQ20: Engage is the best tool for working open orders | BR20: Understanding the issues and amount of steps involved in making order changes | BS20: Automatic source plant changes | BT20: Sales pros being able to request and receive their own shipping labels was a nice time saver, but it lasted less than a week before they were coming back to SSRs on these requests.
B21: R_5f6B8JYEmGMQDFT | C21: TM | AD21: Entering rewards agreements | BH21: 4 | BI21: 5 - Very High | BJ21: 5 - Very High | BK21: 5 - Very High | BL21: 0 | BM21: 25 | BN21: 0 | BO21: 50 | BP21: 25 | BQ21: Communication I have with my pros, via phone, text, chat, calls, and emails. | BR21: On a request, providing all info needed so there is no back and forth. Have a template they can use to identify what info would be needed to get a request completed. | BS21: None at the moment | BT21: Having my reps send requests in with Account#, Contact Name, and description of what is needed. This has stopped lots of back and forth communications. | BU21: 35 | BV21: 61 | BW21: 0 | BX21: 1 | BY21: 1 | BZ21: 0 | CA21: 0 | CB21: 1 | CC21: 0 | CD21: 0 | CE21: 0 | CF21: 1 | CG21: 0 | CI21: 95 | CJ21: 50 | CK21: 25 | CL21: 25 | CM21: 0 | CN21: 0 | CP21: 20-40 mins | CQ21: 10-20 mins | CR21: 5-10 mins | CS21: 10-20 mins | CT21: 20-40 mins | CU21: 5-10 mins | CV21: 5-10 mins | CW21: 40-60 mins | CX21: 20-40 mins
B22: R_5k2Q9YuWFdAGUxz | C22: TM | AD22: Ticket creation. It would be better if tickets would create new instead of reopening old tickets. | BH22: 5 - Very High | BI22: 4 | BJ22: 5 - Very High | BK22: 5 - Very High | BL22: 5 | BM22: 5 | BN22: 55 | BO22: 25 | BP22: 10 | BQ22: The rapport with my team is great. We both understand our roles of each other. | BR22: Upfront information. Sometimes there are not enough details to start the cart or case. | BS22: I would like to see VOE be more user friendly and be capable of copying a cart from QOE once it's pushed there. Also, an easier breakdown of our vendors and what product they offer. I have a pretty good understanding of what I can find and where but newer TMs do not have that luxury. If Engage could vendor search by sport or product would be ideal. | BT22: I feel like taking away the ability for me to create accounts has caused a handicap to both me and the sales pros. The extra step adds more wait time until a cart/case can be completed. | BU22: 40 | BV22: 15 | BW22: 15 | BX22: 4 | BY22: 1 | BZ22: 0.5 | CA22: 0.5 | CB22: 3.5 | CC22: 0.5 | CD22: 11 | CE22: 8 | CF22: 1 | CG22: 0 | CI22: 90 | CJ22: 0 | CK22: 0 | CL22: 50 | CM22: 0 | CN22: 50 | CO22: Add on to an existing or closed out ticket. | CP22: 5-10 mins | CQ22: 5-10 mins | CR22: <5 mins | CS22: <5 mins | CT22: 5-10 mins | CU22: <5 mins | CV22: <5 mins | CW22: 5-10 mins | CX22: <5 mins
B23: R_1DGOFFlUeBsr8sJ | C23: SSR | AD23: removing out of stock items from MTS, Sprint shops to allow extensions. requiring SP's to use engage for status before they call for a status. | AE23: 0 | AF23: 2 | AG23: 2 | AH23: 0 | AI23: 15 | AJ23: 20 | AK23: 25 | AL23: 2 | AM23: 2 | AN23: 1 | AO23: 1 | AP23: 0 | AQ23: 20 | AR23: 0 | AS23: 10 | AT23: 0 | AV23: <5 mins | AW23: 10-20 mins | AX23: 10-20 mins | AZ23: 5-10 mins | BA23: >3h | BB23: 2-3h | BC23: 5-10 mins | BD23: 5-10 mins | BE23: 5-10 mins | BF23: <5 mins | BH23: 5 - Very High | BI23: 4 | BJ23: 5 - Very High | BK23: 3 | BL23: 0 | BM23: 5 | BN23: 45 | BO23: 45 | BP23: 5 | BQ23: each SP works differently. This one is hard to pin down. | BR23: again, all are different, but only a couple of my SP's even go to engage for any info. Some didn't even know they could access the vendor tab for price sheets/ b2b info, etc. | BS23: having them use the request status button on engage for updates rather than a call or email. | BT23: the mts kickback resolution is SUCH a great time saver, taking the majority of MTS issues off our plate has been nice.
B24: R_7NVYorVMNptooiG | C24: SSR | AD24: na | AE24: 5 | AF24: 16 | AG24: 21 | AH24: 2 | AI24: 8 | AJ24: 8 | AK24: 7 | AL24: 2 | AM24: 2 | AN24: 2 | AO24: 5 | AP24: 2 | AQ24: 7 | AR24: 3 | AS24: 10 | AT24: 0 | AV24: <5 mins | AW24: 1-2h | AX24: 20-40 mins | AY24: <5 mins | AZ24: 10-20 mins | BA24: 20-40 mins | BB24: 5-10 mins | BC24: <5 mins | BD24: <5 mins | BE24: 10-20 mins | BF24: 5-10 mins | BG24: <5 mins | BH24: 3 | BI24: 3 | BJ24: 4 | BK24: 2 | BL24: 10 | BM24: 15 | BN24: 50 | BO24: 20 | BP24: 5 | BQ24: SAP | BR24: Using Engage | BS24: na | BT24: na
B25: R_3g5Aq0FI9ZpfWcH | C25: TM | AD25: n/a | BH25: 4 | BI25: 4 | BJ25: 4 | BK25: 2 | BL25: 10 | BM25: 10 | BN25: 40 | BO25: 20 | BP25: 20 | BQ25: communication, ive known my team for a while so i have no issues calling their phone or on teams | BR25: more detail in requests | BS25: defining the role to FSP, we a lot of CSR work | BT25: n/a | BU25: 25 | BV25: 25 | BW25: 5 | BX25: 10 | BY25: 0 | BZ25: 0 | CA25: 0 | CB25: 10 | CC25: 0 | CD25: 10 | CE25: 10 | CF25: 5 | CG25: 0 | CI25: 50 | CJ25: 60 | CK25: 25 | CL25: 5 | CM25: 10 | CN25: 0 | CP25: 5-10 mins | CQ25: 5-10 mins | CR25: <5 mins | CS25: <5 mins | CT25: 5-10 mins | CU25: <5 mins | CV25: 5-10 mins | CW25: >3h | CX25: 5-10 mins
B26: R_7WYlKEHbVy6Gklw | C26: R+R Pod | AD26: NA | BH26: 3 | BI26: 5 - Very High | BJ26: 4 | BK26: 1 = Very Low | BL26: 20 | BM26: 50 | BN26: 10 | BO26: 10 | BP26: 10 | BQ26: na | BR26: making sure all information is available. If the problem is with decoration, providing deco approval before submitting the request to RR. | BS26: na | BT26: na | DJ26: 25 | DK26: 25 | DL26: 20 | DM26: 10 | DN26: 9 | DO26: 1 | DP26: 10 | DQ26: 0 | DS26: 10-20 mins
B27: R_3VedKTzRycYgliq | C27: Comp Pod | AD27: Sales Pro Zemps filled in on comps page with account number when SP adds the information to the email | BH27: 3 | BI27: 3 | BJ27: 4 | BK27: 4 | BL27: 5 | BM27: 5 | BN27: 25 | BO27: 35 | BP27: 30 | BQ27: Having all information to place the order | BR27: Reading emails with regards to problems with inventory/substitutes offered. Using forms for Nike/Under Armour | BS27: Have them use the tools (forms for comp items) provided | BT27: Using comp order forms, giving them quality substitutes | CY27: 15 | CZ27: 5 | DA27: 20 | DB27: 10 | DC27: 15 | DD27: 5 | DE27: 15 | DF27: 10 | DG27: 5 | DH27: Worked with Returns Pod and still have open cases with them | DI27: 10-20 mins
B28: R_6dus9DtwrjVHhlc | C28: SSR | AD28: When making changes to MTS if RTI is on then the shop shouldn't make you go in and individually remove all the BO items that are already not able to be ordered on the shop anyway. | AE28: 1 | AF28: 10 | AG28: 10 | AH28: 1 | AI28: 10 | AJ28: 25 | AK28: 25 | AL28: 2 | AM28: 2 | AN28: 1 | AO28: 1 | AP28: 0 | AQ28: 1 | AR28: 1 | AS28: 10 | AT28: 0 | AV28: <5 mins | AW28: 10-20 mins | AX28: 10-20 mins | AY28: 5-10 mins | AZ28: 5-10 mins | BA28: <5 mins | BB28: <5 mins | BC28: 5-10 mins | BD28: 5-10 mins | BE28: <5 mins | BF28: <5 mins | BH28: 4 | BI28: 4 | BJ28: 5 - Very High | BK28: 5 - Very High | BL28: 0 | BM28: 5 | BN28: 90 | BO28: 5 | BP28: 0 | BQ28: The pods, and the bots pushing carts and MTS | BR28: Some of my reps do not respond to emails I send regarding their orders. They also don't CC me in some communications, or just go off on their own to cancel POs with the vendors without going through the proper steps. | BS28: I would like for them to have a place to reach out for AR/billing questions. somewhere they can get the invoices and cc receipts instead of asking me for them. Accounts services takes too long for them so they come back to me. | BT28: Having the reps use engage. they can check the order statuses there. Less emails for us asking "what's going on with this order"
B29: R_5m3AcMZ3rSKmkmZ | C29: TM | AD29: link or attach rewards deals to pullover pricing and discounts to customer account in qoe/voe/sap pricing, remove the need to go research on each schools cart | BH29: 4 | BI29: 5 - Very High | BJ29: 5 - Very High | BK29: 5 - Very High | BL29: 0 | BM29: 20 | BN29: 40 | BO29: 20 | BP29: 20 | BQ29: ticket system keeps task clean and easy to track and communicate with FSP's | BR29: more detail and specs on custom hardgoods and size and colors/logos | BS29: lag times on systems and programs, seem to run slow if not shut down during some points of the month, create bottlneck | BT29: updated cost sheets and vendor updates(engage) | BU29: 20 | BV29: 50 | BW29: 5 | BX29: 0 | BY29: 4 | BZ29: 0 | CA29: 0 | CB29: 1 | CC29: 3 | CD29: 2 | CE29: 10 | CF29: 5 | CG29: 0 | CI29: 80 | CJ29: 25 | CK29: 25 | CL29: 50 | CM29: 0 | CN29: 0 | CP29: 5-10 mins | CQ29: 10-20 mins | CR29: <5 mins | CS29: 10-20 mins | CT29: 20-40 mins | CW29: 5-10 mins | CX29: 20-40 mins
B30: R_78JakWokStUDU0v | C30: TM | AD30: QOE should be synced up with Engage regarding rewards deals for school. Have a code for what percentage comes off pricing. | BH30: 4 | BI30: 5 - Very High | BJ30: 5 - Very High | BK30: 5 - Very High | BL30: 0 | BM30: 10 | BN30: 20 | BO30: 20 | BP30: 50 | BQ30: easy to communicate with FSP's and easy to track tickets. | BR30: send in all information for bigger projects | BS30: keep Engage updated | BT30: keep vendor updates up to date. Let us know if a vendor is on vendor is on credit hold | BU30: 28 | BV30: 50 | BW30: 0 | BX30: 0 | BY30: 1 | BZ30: 0 | CA30: 0 | CB30: 1 | CC30: 0 | CD30: 10 | CE30: 5 | CF30: 5 | CG30: 0 | CI30: 80 | CJ30: 25 | CK30: 25 | CL30: 50 | CM30: 0 | CN30: 0 | CP30: 5-10 mins | CQ30: 10-20 mins | CR30: 5-10 mins | CS30: 10-20 mins | CT30: 20-40 mins | CW30: 5-10 mins | CX30: 20-40 mins
B31: R_6o5BrtsLUMAuMON | C31: TM | AD31: The reps should not create a cart if they need a TM to add items to one. | BH31: 4 | BI31: 5 - Very High | BJ31: 5 - Very High | BK31: 4 | BL31: 10 | BM31: 10 | BN31: 50 | BO31: 20 | BP31: 10 | BQ31: My reps are really good at putting the account number with their requests. If I see an account number or name in the ticket then I will automatically put it in a cart for them if we have access to it or something similar. | BR31: I believe they should be better with giving more details when ordering custom items. They do not understand that we cannot assume details on custom items. | BS31: Updating the descriptions of products on our site and give images on the links where they are shown. | BT31: Having a reminder of sports coming up in the next seasons so we can prep flyers and spotlight emails to send out to them. | BU31: 32 | BV31: 20 | BW31: 1 | BX31: 2 | BY31: 1 | BZ31: 1 | CA31: 0 | CB31: 1 | CC31: 1 | CD31: 20 | CE31: 20 | CF31: 1 | CG31: 0 | CI31: 92 | CJ31: 80 | CK31: 10 | CL31: 10 | CM31: 0 | CN31: 0 | CP31: 10-20 mins | CQ31: 10-20 mins | CR31: 5-10 mins | CS31: 10-20 mins | CT31: 10-20 mins | CU31: <5 mins | CV31: <5 mins | CW31: <5 mins | CX31: <5 mins
B32: R_6xJHvtzFlKFoW43 | C32: MTS Pod | AD32: The customer service phone number being pre-loaded in the shop, so we don't have to keep retyping it, a preloading the sport type on the Summary page based on the activity selection on the Start page. | BH32: 4 | BI32: 3 | BJ32: 4 | BK32: 4 | BL32: 0 | BM32: 5 | BN32: 75 | BO32: 15 | BP32: 5 | BQ32: Our Lead Form is set up so nicely for Sales Professionals. All the tools are there to have them supply us the information. | BR32: When utilizing the MTS POD, there should be an understanding that we use the latest technology available ( i.e. TAL for shop builds). We should be moving away from full manual QOE builds, as this takes the team 3 times longer to build out than using TAL. We understand there are certain situations where a full manual build may be needed, but if it's just because they don't want to pay art fees, that should be something we can push back on. This comes into play with Licensed accounts that NEED to see artwork previewed on each item. | BS32: Interactive EMB, better personalization process--right now you have to click each individual item to add and it's very time-consuming and manual. | BT32: Most of the TAL upgrades, and the CAL. | DT32: 15 | DU32: 10 | DV32: 1 | DW32: 5 | DX32: 5 | DY32: 10 | DZ32: 5 | EA32: 20 | EB32: 15 | EC32: 14 | ED32: Other activities include QA, collaborating on projects, helping the team with Manual Approvals and Campaign changes. | EE32: 20-40 mins | EF32: 20-40 mins | EG32: Working with school/coach takes much longer
B33: R_7PcR9Nq3W31XjSx | C33: SSR | AD33: Not sure if the rep is notified when an order invoices/closes but this would help a few of my reps | AE33: 2 | AF33: 4 | AG33: 2 | AH33: 4 | AI33: 15 | AJ33: 45 | AK33: 10 | AL33: 0 | AM33: 2 | AN33: 1 | AO33: 1 | AP33: 0 | AQ33: 4 | AR33: 0 | AS33: 10 | AT33: 0 | AV33: <5 mins | AW33: <5 mins | AX33: 5-10 mins | AY33: <5 mins | AZ33: 5-10 mins | BA33: >3h | BB33: 1-2h | BC33: 5-10 mins | BD33: 5-10 mins | BE33: <5 mins | BF33: <5 mins | BH33: 4 | BI33: 4 | BJ33: 4 | BK33: 3 | BL33: 0 | BM33: 0 | BN33: 50 | BO33: 25 | BP33: 25 | BQ33: I like the new mts consolidation team. That has helped a ton. | BR33: Make sure they are checking engage before askig for status requests | BS33: Notifying of order invoicing/complete. | BT33: I wish we would get an mts consolidation email since we still recieve the workflow email.
B34: R_3p7vEkGrFbzevcd | C34: R+R Pod | AD34: Label creation possibly but I wouldn't have any idea how that would work | BH34: 4 | BI34: 4 | BJ34: 5 - Very High | BK34: 4 | BL34: 10 | BM34: 10 | BN34: 10 | BO34: 30 | BP34: 40 | BQ34: The grid as long as they fill it out | BR34: Stating how many labels they need when they send the request as many times they come back later needing more because it was never specified | BS34: N/A | BT34: Being clear and concise with questions and listing them as bullet points if there are more than one | DJ34: 30 | DK34: 20 | DL34: 12.5 | DM34: 5 | DN34: 15 | DO34: 2.5 | DP34: 10 | DQ34: 5 | DR34: Updating dates on tracking or investigating a case outside of the normal flow of activities. | DS34: 5-10 mins
B35: R_70MpwSyolERNr6K | C35: R+R Pod | AD35: put the sales pros email on every customer account they use so they get the order confirmation and can let the customers know. Have a system built on the website so sale pros and customers can request their own return labels or have a return label be automatically created once we create the return and sent to them as long as it can be brought in house so have that be a function we click on and for return follow ups once the return label is sent I think the system should be reminding the person the label is sent to that they have "X" amount of time left before the return is cancelled and the label is deactivated. | BH35: 1 = Very Low | BI35: 2 | BJ35: 3 | BK35: 1 = Very Low | BL35: 10 | BM35: 10 | BN35: 10 | BO35: 20 | BP35: 50 | BQ35: the way I just do my cases, it is hard to explain in fact I cannot explain it | BR35: answer emails asap/ provide the R&R grid and all information that is required to process the case. | BS35: more detailed grid | BT35: not that I can think of besides the grid | DJ35: 20 | DK35: 25 | DL35: 10 | DM35: 25 | DN35: 5 | DO35: 5 | DP35: 10 | DQ35: 0 | DS35: 10-20 mins
B36: R_1zB0erNM8SQpwwe | C36: SSR | AD36: Having a folder just for Sprint orders would be nice. | AE36: 0.5 | AF36: 1 | AG36: 0.5 | AH36: 0.5 | AI36: 5 | AJ36: 50 | AK36: 10 | AL36: 1 | AM36: 1 | AN36: 0.5 | AO36: 5 | AP36: 0 | AQ36: 10 | AR36: 1 | AS36: 10 | AT36: 4 | AU36: Helping other SSRs. | AV36: <5 mins | AW36: 5-10 mins | AX36: 5-10 mins | AY36: <5 mins | AZ36: 5-10 mins | BA36: 5-10 mins | BB36: <5 mins | BC36: <5 mins | BD36: <5 mins | BE36: <5 mins | BF36: 5-10 mins | BG36: <5 mins | BH36: 5 - Very High | BI36: 5 - Very High | BJ36: 5 - Very High | BK36: 4 | BL36: 5 | BM36: 5 | BN36: 10 | BO36: 60 | BP36: 20 | BQ36: Engage works well for the ones that use it. | BR36: I would like for more of my sales pros to use Engage for order information and requesting updates on their orders. | BS36: It would be nice if there could be a way to have Nike Teams POs entered like Nike USA POs. | BT36: The BOTS, Label automation, Wizard shop Bots. All of these have made my role as an SSR easier to support Sales Pros.
B37: R_30OhPL2Ln8TrQfD | C37: TM | AD37: Badger NSP's. Instead of creating a NSP for Badger items that are blocked (Use BSN First). We should be able to still use the SKU but there be some sort of approval system like the pre-order approval process. It would save time creating lines. | BH37: 3 | BI37: 4 | BJ37: 5 - Very High | BK37: 4 | BL37: 0 | BM37: 0 | BN37: 70 | BO37: 20 | BP37: 10 | BQ37: Open communication. | BR37: As much details as possible or send generic request and follow up with a phone call to give more detail if too much to type. | BS37: N/A | BT37: TM Sharepoint site has helped a lot. A central location for most information. | BU37: 40 | BV37: 30 | BW37: 0 | BX37: 2 | BY37: 0 | BZ37: 2 | CA37: 0 | CB37: 2 | CC37: 2 | CD37: 10 | CE37: 10 | CF37: 2 | CG37: 0 | CI37: 90 | CJ37: 20 | CK37: 10 | CL37: 70 | CM37: 0 | CN37: 0 | CP37: 10-20 mins | CQ37: 10-20 mins | CR37: <5 mins | CS37: <5 mins | CT37: 5-10 mins | CU37: <5 mins | CV37: <5 mins | CW37: <5 mins | CX37: <5 mins
B38: R_5pRVuM31AmqIY7y | C38: R+R Pod | AD38: Emails for RH approvols, 60 day rejections | BH38: 3 | BI38: 4 | BJ38: 3 | BK38: 3 | BL38: 10 | BM38: 15 | BN38: 25 | BO38: 25 | BP38: 25 | BQ38: n/a | BR38: provide all information in initial request, make sure we have inventory before submitting request, reply within 24 hours rather than days requiring multiple follow ups, providing correct information | BS38: the form fill project | BT38: Sharepoint that Patrick created | DJ38: 15 | DK38: 20 | DL38: 46 | DM38: 6 | DN38: 2 | DO38: 3 | DP38: 8 | DQ38: 0 | DS38: 5-10 mins
B39: R_6H05a5iYr9e1RDe | C39: R+R Pod | AD39: I'm currently unsure which parts of the process can be automated or streamlined, but one area that could significantly reduce back-and-forth and improve case averages is obtaining necessary approvals before submitting requests to the R+R Team. Suggested Pre-Submission Approvals: -RSM/VP Approval for credit amounts. -Freight Issue Resolution: Contact the appropriate freight team when freight-related issues arise. -Decorator Issue Resolution: -Internal Deco: Secure approval to place the request under Krisy's ZEMP. -External Deco: Obtain approval to cover the cost of goods for replacements. By ensuring these approvals are in place beforehand, we can process requests immediately upon receipt, minimizing delays and improving overall efficiency. | BH39: 3 | BI39: 3 | BJ39: 3 | BK39: 3 | BL39: 5 | BM39: 5 | BN39: 10 | BO39: 30 | BP39: 50 | BQ39: I've been receiving good responses when tracking information is provided for replacement orders to sales pros/decorators. This has helped improve communication and customer satisfaction, and supports smoother follow-up on order status. | BR39: To ensure timely and efficient processing, it's essential that requesters provide all correct information along with the appropriate approvals when submitting requests to the R+R Team. This helps eliminate delays and allows the team to act on the request immediately upon receipt. | BS39: To improve efficiency, it would be beneficial to allow the R+R Team to cancel requests that lack the necessary information to be completed upon receipt. This would help avoid delays caused by incomplete submissions and ensure that only actionable requests are processed, ultimately improving turnaround times and case averages. | BT39: Hopefully the form fill for request gets released soon. | DJ39: 20 | DK39: 12.5 | DL39: 12.5 | DM39: 20 | DN39: 10 | DO39: 5 | DP39: 5 | DQ39: 15 | DR39: Working on Projects and updating/maintain the R+R SharePoint | DS39: 5-10 mins
B40: R_5RVLGkN17reRB2E | C40: SSR | AD40: tracking for sales pro's | AE40: 0 | AF40: 3 | AG40: 0 | AH40: 3 | AI40: 4 | AJ40: 30 | AK40: 20 | AL40: 5 | AM40: 3 | AN40: 2 | AO40: 5 | AP40: 0 | AQ40: 10 | AR40: 5 | AS40: 10 | AT40: 0 | AV40: <5 mins | AW40: 10-20 mins | AX40: <5 mins | AY40: 5-10 mins | AZ40: 5-10 mins | BA40: 2-3h | BB40: >3h | BC40: 10-20 mins | BD40: 5-10 mins | BE40: <5 mins | BF40: <5 mins | BG40: <5 mins | BH40: 4 | BI40: 5 - Very High | BJ40: 5 - Very High | BK40: 4 | BL40: 0 | BM40: 5 | BN40: 85 | BO40: 10 | BP40: 0 | BQ40: engage and communication on issues with them | BR40: Order number in subject line and only 1 order per email and not multiple orders to check on in 1 email | BS40: making sure sales pro's are aware of changes and their roles | BT40: wishing we could change the source plant ourselves, too many back and forth emails to get changed to correct warehouse
B41: R_60UJsZnGqWW7OvA | C41: TM | AD41: Updating rewards seems like something that could have drop down selections that could be transferred directly into Engage without our touching it. | BH41: 4 | BI41: 4 | BJ41: 5 - Very High | BK41: 5 - Very High | BL41: 0 | BM41: 0 | BN41: 15 | BO41: 85 | BP41: 0 | BQ41: Familiarity with one another. I think the longer we work together the more each of us knows what the other needs in order to make this system more efficient. Most of my FSPs understand where I am best used. Someone sends you on a scavenger hunt for something too far outside of the TM lane and you end up with diminishing returns. This hurts the entire team. | BR41: They sometimes come across as a bit hurried and leave out key details. Having to go back and forth on art details, quantities, and such slow the process for sure. | BS41: Stress (really stress) to the sales team where we are most efficient. I have very little trouble with my team but I notice tons of tickets come through the OOO queue that are way outside of our normal tasks. We already have literature stating how we are best utilized but it appears that there are many sales pros out there who ignore this altogether and send everything to the TM queue. | BT41: I have a couple of sales pros who use templates in their requests. They are different from one another but each makes it much easier to navigate the tickets. It helps them with delivering the needed info consistently and it helps me see exactly what they are needing. I know immediately when I see their tickets come through Engage that they will be good tickets. | BU41: 68.5 | BV41: 15 | BW41: 2.5 | BX41: 0 | BY41: 2.5 | BZ41: 0 | CA41: 0 | CB41: 2.5 | CC41: 0 | CD41: 2 | CE41: 2 | CF41: 5 | CG41: 0 | CI41: 85 | CJ41: 34 | CK41: 33 | CL41: 33 | CM41: 0 | CN41: 0 | CP41: 20-40 mins | CQ41: 10-20 mins | CR41: 5-10 mins | CS41: 5-10 mins | CT41: 10-20 mins | CU41: 10-20 mins | CV41: 5-10 mins | CW41: 10-20 mins | CX41: 10-20 mins
B42: R_5q9yjSsOdWTX5W4 | C42: SSR | AD42: printing invoices | AE42: 1 | AF42: 10 | AG42: 5 | AH42: 2 | AI42: 10 | AJ42: 20 | AK42: 10 | AL42: 1 | AM42: 2 | AN42: 1 | AO42: 5 | AP42: 0 | AQ42: 10 | AR42: 1 | AS42: 10 | AT42: 12 | AU42: Engage | AV42: 5-10 mins | AW42: 20-40 mins | AX42: 1-2h | AY42: 10-20 mins | AZ42: 20-40 mins | BA42: 20-40 mins | BB42: 20-40 mins | BC42: 10-20 mins | BD42: 10-20 mins | BE42: 5-10 mins | BF42: 10-20 mins | BG42: <5 mins | BH42: 4 | BI42: 4 | BJ42: 4 | BK42: 3 | BL42: 5 | BM42: 10 | BN42: 50 | BO42: 30 | BP42: 5 | BQ42: One of my sales pro only uses INDY deco. | BR42: Getting all info in initial email request. | BS42: Having less salespeople per SSR | BT42: Being able to input credit cards into all SAP orders instead of calling into AR.
B43: R_5K8wjaQ5kPqilnO | C43: SSR | AD43: When extending a shop, it would be cool if we could just remove all items that are no longer available at oce. At minimum, if we could just get the actual sku instead of a date. Sometimes there is a green circle, but there is no stock. When this occurs, it's time consuming to find the item that is not available. | AE43: 1 | AF43: 7 | AG43: 0 | AH43: 0 | AI43: 6 | AJ43: 35 | AK43: 10 | AL43: 2 | AM43: 1 | AN43: 2 | AO43: 4 | AP43: 0 | AQ43: 20 | AR43: 2 | AS43: 10 | AT43: 0 | AV43: 5-10 mins | AW43: 10-20 mins | AX43: 10-20 mins | AY43: <5 mins | AZ43: 40-60 mins | BA43: 5-10 mins | BB43: 5-10 mins | BC43: <5 mins | BD43: <5 mins | BE43: <5 mins | BF43: <5 mins | BH43: 3 | BI43: 4 | BJ43: 5 - Very High | BK43: 4 | BL43: 0 | BM43: 0 | BN43: 0 | BO43: 0 | BP43: 100 | BQ43: For the most part, everything. No complaints. | BR43: Just check all of their tools first before asking questions. Sometimes I have literally updated the status of the order in Engage, then I get a question about the order. Or I'll get a question about if the decorator has all product, then I go to check their dashboard. | BS43: It would be cool to not have to go through 3 steps or create a new order because an item is pulling from the wrong source plant. | BT43: Nothing comes to mind.
B44: R_5cYYSGCZv9nmJeL | C44: TM | AD44: N/A | BH44: 4 | BI44: 5 - Very High | BJ44: 4 | BK44: 4 | BL44: 0 | BM44: 5 | BN44: 5 | BO44: 10 | BP44: 80 | BQ44: The number of resources and amount of help with get to find answers for sales pros | BR44: Reading the information that's sent to them. Sending more details up front, rather than basic requests with little to no info/context. | BS44: Filling CM roles for sport specific questions. | BT44: vault/playbook and the TM homepage have been a game changer! | BU44: 40 | BV44: 25 | BW44: 0 | BX44: 2 | BY44: 0 | BZ44: 0 | CA44: 0 | CB44: 0 | CC44: 0 | CD44: 14 | CE44: 14 | CF44: 5 | CG44: 0 | CI44: 85 | CJ44: 85 | CK44: 5 | CL44: 10 | CM44: 0 | CN44: 0 | CP44: 5-10 mins | CQ44: 10-20 mins | CR44: <5 mins | CS44: <5 mins | CT44: <5 mins | CW44: <5 mins | CX44: <5 mins
B45: R_1GZI17WQJP01MyG | C45: TM | AD45: Entering Reward Deals | BH45: 4 | BI45: 4 | BJ45: 5 - Very High | BK45: 4 | BL45: 3 | BM45: 5 | BN45: 5 | BO45: 87 | BP45: 0 | BQ45: The tools we have to get them the right information. | BR45: Give all information needed when they send in a request. | BS45: Keep Engage updated | BT45: Have a better streamline entering system for ASD | BU45: 80 | BV45: 9 | BW45: 1 | BX45: 1 | BY45: 1 | BZ45: 1 | CA45: 1 | CB45: 1 | CC45: 1 | CD45: 1 | CE45: 1 | CF45: 1 | CG45: 1 | CH45: NA | CI45: 100 | CJ45: 5 | CK45: 5 | CL45: 90 | CM45: 0 | CN45: 0 | CP45: 10-20 mins | CQ45: 10-20 mins | CR45: 5-10 mins | CS45: <5 mins | CT45: 10-20 mins | CU45: <5 mins | CV45: <5 mins | CW45: <5 mins | CX45: 5-10 mins
B46: R_3xPL3dKr30K9iN0 | C46: R+R Pod | AD46: not sure | BH46: 3 | BI46: 3 | BJ46: 3 | BK46: 3 | BL46: 80 | BM46: 5 | BN46: 5 | BO46: 5 | BP46: 5 | BQ46: giving them a deadline to respond | BR46: knowing the proper procedure for returns | BS46: allow us to email internal decorators from engage | BT46: not that i can think of | DJ46: 30 | DK46: 15 | DL46: 20 | DM46: 10 | DN46: 10 | DO46: 5 | DP46: 10 | DQ46: 0 | DS46: 10-20 mins
B47: R_1OjP2GJIrX8N4BQ | C47: Customer Care | D47: 0 | E47: 0 | F47: 0 | G47: 0 | H47: 0 | I47: 0 | J47: 0 | K47: 0 | L47: 0 | M47: 0 | N47: 30 | O47: 0 | P47: 20 | Q47: 5 | R47: 45 | S47: Documenting policy and processes, preparing for and conducting training, conducting contact quality assurance, team coaching, SPRINT Order Error queue management. | T47: 5-10 mins | U47: <5 mins | V47: <5 mins | W47: 10-20 mins | X47: 5-10 mins | Y47: 10-20 mins | Z47: 5-10 mins | AA47: 5-10 mins | AB47: 5-10 mins | AC47: 10-20 mins | AD47: Customer Cancelation requests could be automated and refund requests could be significantly streamlined to reduce the amount of steps and multi-department involvement.
B48: R_3fRYwUBgvq0hUjv | C48: SSR | AD48: unsure | AE48: 10 | AF48: 10 | AG48: 20 | AH48: 2 | AI48: 4 | AJ48: 10 | AK48: 10 | AL48: 10 | AM48: 2 | AN48: 10 | AO48: 10 | AP48: 0 | AQ48: 0 | AR48: 2 | AS48: 0 | AT48: 0 | AV48: 20-40 mins | AW48: 20-40 mins | AX48: 10-20 mins | AY48: 5-10 mins | AZ48: 20-40 mins | BA48: 20-40 mins | BB48: 20-40 mins | BC48: 5-10 mins | BD48: 5-10 mins | BE48: 5-10 mins | BF48: 5-10 mins | BG48: <5 mins | BH48: 3 | BI48: 3 | BJ48: 3 | BK48: 3 | BL48: 1 | BM48: 1 | BN48: 1 | BO48: 1 | BP48: 96 | BQ48: unsure | BR48: be more clear with requests and questions the first time they send an email. | BS48: Fishing lanes | BT48: unsure
B49: R_5MAuPcYopXelwUw | C49: SSR | AD49: labels, sales pros being able to extend shops even with BO items, sometimes I am removing items in the yellow in one single shop for over a half hour | AE49: 5 | AF49: 13 | AG49: 5 | AH49: 1 | AI49: 10 | AJ49: 25 | AK49: 12 | AL49: 5 | AM49: 5 | AN49: 3 | AO49: 4 | AP49: 0 | AQ49: 5 | AR49: 2 | AS49: 5 | AT49: 0 | AV49: <5 mins | AW49: 20-40 mins | AX49: 10-20 mins | AY49: <5 mins | AZ49: 10-20 mins | BA49: 2-3h | BB49: 10-20 mins | BC49: 5-10 mins | BD49: 5-10 mins | BE49: <5 mins | BF49: 5-10 mins | BG49: <5 mins | BH49: 3 | BI49: 4 | BJ49: 4 | BK49: 2 | BL49: 10 | BM49: 10 | BN49: 40 | BO49: 20 | BP49: 20 | BQ49: most of my sales pros are beginning to use pods themselves as well as other self service areas | BR49: They could utilize engage more, start sending their own requests to Returns/AR/ Other self service departments that some of my sales pros do not utilize themselves | BS49: If they could extend shops even with BO items on them that would free up a lot of time | BT49: The pods have helped free up time to go through open orders more thoroughly
B50: R_1bW4eKBmrU1QZwy | C50: Comp Pod | AD50: Providing SP with a weekly/monthly list of well stocked items AHEAD of time to reduce finding replacements or "rechecking" stock that is not available | BH50: 4 | BI50: 4 | BJ50: 4 | BK50: 3 | BL50: 2 | BM50: 3 | BN50: 80 | BO50: 10 | BP50: 5 | BQ50: MOST (but not all) of SP respond quickly and that helps manage expectations for items that are currently in stock, vs a SP that responds back 2-3 days later and items for their initial order are now out of stock as well | BR50: using an order form. if an order is 1-2 items and a simple shipping address I have no problem processing that from an email. But 20-30 items in the body of an email or a word document allow for a LOT of room for human error | BS50: letting the comp team provide a "suggested" product update monthly weekly, items that are in great stock, easy to get a hold of etc | BT50: if they could have access to Nike coupon side that would be lovely (a few do and utilize that ahead of time) | CY50: 15 | CZ50: 15 | DA50: 12 | DB50: 18 | DC50: 5 | DD50: 5 | DE50: 20 | DF50: 10 | DG50: 0 | DI50: 20-40 mins
B51: R_6osUWsAkWHSkcBW | C51: SSR | AD51: Engage activities for Nike, and stock backorders that have been pushed back. Source plant changes for internal warehouses. My team shop extensions with backordered or out of stock product | AE51: 3 | AF51: 2 | AG51: 0 | AH51: 1 | AI51: 5 | AJ51: 40 | AK51: 10 | AL51: 2 | AM51: 1 | AN51: 2 | AO51: 2 | AP51: 0 | AQ51: 15 | AR51: 2 | AS51: 10 | AT51: 5 | AU51: Office space management, cleaning and organization | AV51: <5 mins | AW51: 5-10 mins | AX51: 5-10 mins | AY51: <5 mins | AZ51: 5-10 mins | BA51: 1-2h | BB51: 5-10 mins | BC51: 5-10 mins | BD51: 5-10 mins | BE51: <5 mins | BF51: <5 mins | BH51: 4 | BI51: 4 | BJ51: 4 | BK51: 3 | BL51: 5 | BM51: 5 | BN51: 10 | BO51: 40 | BP51: 40 | BQ51: I make sure that most requests are emailed so I have a paper trail | BR51: Knowing swim lane. When a process is updated or changed, making sure that is communicated to sales pros | BS51: If sales pros had access to SAP, they could answer many of there requests to SSR's by themselves. That would leave more time to work open orders. | BT51: Better back order tracking
B52: R_6Rdu9POySeJ7GWj | C52: R+R Pod | AD52: being able to select multiple cases in engage at once to move them to a new date - ex) open orders needing to be pushed out | BH52: 4 | BI52: 4 | BJ52: 4 | BK52: 4 | BL52: 60 | BM52: 35 | BN52: 5 | BO52: 0 | BP52: 0 | BQ52: when they utilize the grid and provide complete info, | BR52: they need to be reaching out to internal deco before sending in requests for replacements | BS52: their managers to remind them of the responsibilities of each team and how to communicate with them | BT52: signatures that are efficient and provide all the info | DJ52: 30 | DK52: 25 | DL52: 15 | DM52: 10 | DN52: 8 | DO52: 2 | DP52: 10 | DQ52: 0 | DS52: 10-20 mins
B53: R_3GDMrE93SloTW5r | C53: SSR | AD53: I am fairly new to the company, and just learning the ropes. I really don't have an opinion on this question yet. | AE53: 0 | AF53: 0 | AG53: 0 | AH53: 0 | AI53: 0 | AJ53: 50 | AK53: 20 | AL53: 0 | AM53: 0 | AN53: 0 | AO53: 0 | AP53: 0 | AQ53: 20 | AR53: 0 | AS53: 10 | AT53: 0 | BA53: 10-20 mins | BB53: 20-40 mins | BH53: 5 - Very High | BI53: 5 - Very High | BJ53: 5 - Very High | BK53: 5 - Very High | BL53: 0 | BM53: 0 | BN53: 75 | BO53: 20 | BP53: 5 | BQ53: I look at my Engage first thing in the morning. As I complete the Engage activities, I put each of them on the calendar. This allows me to see if a particular day is going to be super busy. After completing Engage, I go through my emails and complete any needed actions for those including adding them to the calendar if necessary. | BR53: I haven't been with the company long enough to have an opinion on that, and most of my sales pros are new. We are learning together. | BS53: There is not anything that I can think of at this time. | BT53: I think that if all of our vendors had live inventory, that would be a big help. The vendors that do have live inventory have been a blessing in completing the Engage activities.
B54: R_7vlc2ezdEOo8uT6 | C54: SSR | AD54: MTS availability issues should automatically be removed from shops. | AE54: 1 | AF54: 2 | AG54: 3 | AH54: 1 | AI54: 20 | AJ54: 40 | AK54: 7 | AL54: 1 | AM54: 1 | AN54: 1 | AO54: 7 | AP54: 1 | AQ54: 1 | AR54: 1 | AS54: 10 | AT54: 3 | AU54: FBL5 | AV54: 10-20 mins | AW54: 40-60 mins | AX54: 20-40 mins | AY54: 10-20 mins | AZ54: 20-40 mins | BA54: >3h | BB54: 2-3h | BC54: <5 mins | BD54: 5-10 mins | BE54: <5 mins | BF54: 5-10 mins | BG54: <5 mins | BH54: 2 | BI54: 2 | BJ54: 3 | BK54: 1 = Very Low | BL54: 2 | BM54: 5 | BN54: 65 | BO54: 15 | BP54: 13 | BQ54: Emailing for updates/changes needed. | BR54: Using engage! | BS54: Getting information on orders quicker. | BT54: Closing out orders more quickly once tracking has been entered in engage to close out completed orders.
B55: R_1HnXbgi9OPIBLCV | C55: SSR | AD55: NA | AE55: 1 | AF55: 3 | AG55: 5 | AH55: 2 | AI55: 5 | AJ55: 50 | AK55: 5 | AL55: 1 | AM55: 5 | AN55: 2 | AO55: 5 | AP55: 0 | AQ55: 5 | AR55: 1 | AS55: 10 | AT55: 0 | AV55: <5 mins | AW55: 5-10 mins | AX55: <5 mins | AY55: <5 mins | AZ55: 5-10 mins | BA55: >3h | BB55: <5 mins | BC55: <5 mins | BD55: 10-20 mins | BE55: <5 mins | BF55: <5 mins | BH55: 3 | BI55: 4 | BJ55: 4 | BK55: 4 | BL55: 0 | BM55: 0 | BN55: 0 | BO55: 25 | BP55: 75 | BQ55: We work well together | BR55: BE sure to give the sales order number or cart so I can find what order they are looking for | BS55: Make sure they are using Engage for order status | BT55: Engage as long as they use it
B56: R_5Qot3SrVjn18s2j | C56: TM | AD56: the weekly Top Proprietary Products email | BH56: 3 | BI56: 4 | BJ56: 5 - Very High | BK56: 4 | BL56: 3 | BM56: 5 | BN56: 80 | BO56: 10 | BP56: 2 | BQ56: We have a good working relationship, and they seem to trust me and what I do. | BR56: Lack of information. They get so busy they don't send QTYs, colors, art etc. | BS56: making some our NSP processes a little easier. | BT56: What has helped is my manager coming up with and maintaining the TeaMwork sharepoint site. | BU56: 30 | BV56: 30 | BW56: 5 | BX56: 0 | BY56: 3 | BZ56: 2 | CA56: 0 | CB56: 3 | CC56: 2 | CD56: 10 | CE56: 10 | CF56: 5 | CG56: 0 | CI56: 93 | CJ56: 85 | CK56: 5 | CL56: 10 | CM56: 0 | CN56: 0 | CP56: 10-20 mins | CQ56: 20-40 mins | CR56: 10-20 mins | CS56: 10-20 mins | CT56: 5-10 mins | CU56: 40-60 mins | CW56: >3h | CX56: 20-40 mins
B57: R_57qau1X43pGJlmh | C57: SSR | AD57: Order Status/Tracking | AE57: 1 | AF57: 5 | AG57: 0 | AH57: 1 | AI57: 5 | AJ57: 45 | AK57: 10 | AL57: 5 | AM57: 0 | AN57: 0 | AO57: 2 | AP57: 0 | AQ57: 25 | AR57: 1 | AS57: 0 | AT57: 0 | AV57: <5 mins | AW57: 5-10 mins | AX57: 5-10 mins | AY57: 5-10 mins | AZ57: 10-20 mins | BA57: 1-2h | BB57: <5 mins | BC57: 10-20 mins | BD57: <5 mins | BE57: <5 mins | BF57: <5 mins | BG57: <5 mins | BH57: 2 | BI57: 4 | BJ57: 5 - Very High | BK57: 4 | BL57: 1 | BM57: 1 | BN57: 3 | BO57: 75 | BP57: 20 | BQ57: Communication is key! We can do everything and anything efficiently and timely if we have great communication between us, the customer, decorators, and vendors. | BR57: Utilize Engage more- whenever they ask for a status update/tracking my first move is to go look at my notes in Engage, when they could also be doing that on their own! | BS57: I wish the system could block Nike socks/hats that are not entered in the correct minimum quantities! | BT57: Fed Ex Label Creator, MTS Consolidation Team have been a huge help! Thank you!
B58: R_1g5XmtYYnTN1AHA | C58: TM | AD58: Not sure , each request is so different. Assigning SKu's to Nike Golf pants, we sell tons of these for football coaches. NSP's take more time for sure | BH58: 4 | BI58: 3 | BJ58: 5 - Very High | BK58: 3 | BL58: 20 | BM58: 50 | BN58: 15 | BO58: 5 | BP58: 10 | BQ58: Most of the B2B accuracy's | BR58: Give all needed info to fulfill the request. Read the TM response email completely | BS58: Better understanding of SSR, MTS, TM roles | BT58: Adidas sku's vs Color codes, What they need to use. | BU58: 82 | BV58: 10 | BW58: 1 | BX58: 0 | BY58: 1 | BZ58: 0 | CA58: 0 | CB58: 1 | CC58: 1 | CD58: 1 | CE58: 2 | CF58: 1 | CG58: 0 | CI58: 95 | CJ58: 100 | CK58: 0 | CL58: 0 | CM58: 0 | CN58: 0 | CP58: 10-20 mins | CQ58: 5-10 mins | CR58: <5 mins | CS58: <5 mins | CT58: 10-20 mins | CU58: 5-10 mins | CV58: 5-10 mins
B59: R_6V7TEWTr0hgbhsb | C59: TM | AD59: None | BH59: 3 | BI59: 5 - Very High | BJ59: 5 - Very High | BK59: 2 | BL59: 0 | BM59: 0 | BN59: 0 | BO59: 5 | BP59: 95 | BQ59: The availability of my sales is good. they are quick to answer questions and phone calls from me when follow-ups to a request of theirs is needed. | BR59: Giving all info needed in initial email. i.e. color, sizes, attachment of logos, pictures of damaged goods | BS59: Some Sales Pros come to BSN and have NO product knowledge. So, TMs have to at times decipher what Sales Pros and their customers are asking for. | BT59: I believe all the tools are at our (TM's) disposal to help support our Sales Pros. | BU59: 27 | BV59: 55 | BW59: 12 | BX59: 1 | BY59: 1 | BZ59: 0 | CA59: 0 | CB59: 1 | CC59: 0 | CD59: 1 | CE59: 1 | CF59: 1 | CG59: 0 | CI59: 99 | CJ59: 95 | CK59: 0 | CL59: 5 | CM59: 0 | CN59: 0 | CP59: 5-10 mins | CQ59: 10-20 mins | CS59: 5-10 mins | CT59: 5-10 mins | CU59: 5-10 mins | CV59: <5 mins | CW59: 20-40 mins
